Workbook

Sheet DASHBOARD
B1: Performance Dashboard
B2: Client Name: ATC
B4: Last updated: 2/5/2026
B13: 6 Rs
B16: Success Factor | C16: Measurement | D16: 2019 | E16: 2022 | F16: 2023 | G16: 2024 | H16: Historic Average | I16: 2026 Actual | J16: 2026 Goal | K16: 2026 Percent to Goal | L16: Goal
B17: Reach​ | C17: Total Attendees | D17: 4077 | E17: 3927 | F17: 5019 | H17: =AVERAGE(D17:G17) -> 4341 | K17: =I17/J17 -> #DIV/0! | L17: 1
C18: Paid Attendees | F18: 3634 | H18: =AVERAGE(D18:G18) -> 3634 | K18: =I18/J18 -> #DIV/0! | L18: 1
B19: Retention​ | C19: +40% Returning Attendees | D19: . | E19: . | F19: 0.37 | H19: =AVERAGE(D19:G19) -> 0.37 | K19: =I19/J19 -> #DIV/0! | L19: 1
B20: Relevance​ | C20: +20% of Addressable Audience | D20: . | E20: . | F20: 0.16 | H20: =AVERAGE(D20:G20) -> 0.16 | K20: =I20/J20 -> #DIV/0! | L20: 1
B21: Reputation​ | C21: NPS of 60+ | D21: . | E21: . | F21: . | H21: =AVERAGE(D21:G21) -> #DIV/0! | K21: =I21/J21 -> #DIV/0! | L21: 1
B22: Revenue​ | C22: Gross Revenue | D22: 4887599 | E22: 4881907 | F22: 4844787 | H22: =AVERAGE(D22:G22) -> 4871431 | K22: =I22/J22 -> #DIV/0! | L22: 1
B23: ROI​ | C23: Net Profit* | D23: 2074035 | E23: 1332966 | F23: 1565737 | H23: =AVERAGE(D23:G23) -> 1657579.3 | K23: =I23/J23 -> #DIV/0! | L23: 1
C24: +20% Margin | D24: 0.42 | E24: 0.27 | F24: 0.32 | H24: =AVERAGE(D24:G24) -> 0.33666667 | K24: =I24/J24 -> #DIV/0! | L24: 1
B31: Event Registrations
B70: Email
B109: Organic Social
B143: Paid Media
B148: Date Range: xxxx (Totals / Averages)
B150: LinkedIn | G150: Meta | V150: Google Search | AA150: Google Display
B152: Impressions | C152: Clicks | D152: Cost | E152: CPC | G152: Impressions | H152: Clicks | I152: Cost | J152: CPC | V152: Impressions | W152: Clicks | X152: Cost | Y152: CPC | AA152: Impressions | AB152: Clicks | AC152: Cost | AD152: CPC
B153: ='Paid Media'!B34 -> 111528 | C153: ='Paid Media'!C34 -> 1096 | D153: ='Paid Media'!D34 -> 1136.35 | E153: ='Paid Media'!E34 -> 1.0368157 | G153: ='Paid Media'!J34 -> 510884 | H153: ='Paid Media'!K34 -> 4007 | I153: ='Paid Media'!L34 -> 5264.58 | J153: ='Paid Media'!M34 -> 1.3138458 | V153: ='Paid Media'!R34 -> 55823 | W153: ='Paid Media'!S34 -> 993 | X153: ='Paid Media'!T34 -> 3905.06 | Y153: ='Paid Media'!U34 -> 3.9325881 | AA153: ='Paid Media'!Z34 -> 498415 | AB153: ='Paid Media'!AA34 -> 555 | AC153: ='Paid Media'!AB34 -> 1658.88 | AD153: ='Paid Media'!AC34 -> 2.988973
V154: 6
B155: CTR | C155: Conversions | D155: Conversion Rate | E155: CPA | G155: CTR | H155: Conversions | I155: Conversion Rate | J155: CPA | V155: CTR | W155: Conversions | X155: Conversion Rate | Y155: CPA | AA155: CTR | AB155: Conversions | AC155: Conversion Rate | AD155: CPA
B156: ='Paid Media'!F34 -> 0.0098271286 | C156: ='Paid Media'!G34 -> 0 | D156: ='Paid Media'!H34 -> 0 | E156: ='Paid Media'!I34 -> #DIV/0! | G156: ='Paid Media'!N34 -> 0.0078432677 | H156: ='Paid Media'!O34 -> 5 | I156: ='Paid Media'!P34 -> 0.0012478163 | J156: ='Paid Media'!Q34 -> 1052.916 | V156: ='Paid Media'!V34 -> 0.017788367 | W156: ='Paid Media'!X34 -> 0.71237664 | X156: ='Paid Media'!X34 -> 0.71237664 | Y156: ='Paid Media'!Y34 -> 5.5203777 | AA156: ='Paid Media'!AD34 -> 0.0011135299 | AB156: ='Paid Media'!AE34 -> 0 | AC156: ='Paid Media'!AF34 -> 0 | AD156: ='Paid Media'!AG34 -> #DIV/0!
B159: Total Campaigns | C159: Total Budget | D159: Total Spent | E159: LI Total Remaining | G159: Total Campaigns | H159: Total Budget | I159: Total Spent | J159: FB Total Remaining | V159: Total Campaigns | W159: Total Budget | X159: Total Spent | Y159: X Total Remaining | AA159: Total Campaigns | AB159: Total Budget | AC159: Total Spent | AD159: X Total Remaining
AA160: 5 | AB160: 10000 | AC160: 5000 | AD160: =AB160-AC160 -> 5000

Sheet MARKETING DATA -->

Sheet Emails
A1: ATC
A2: Email Name | B2: Audience (List) | C2: Deployment Date | D2: Deployment Day of Week | E2: Deployment Time of Day | F2: Total Emails Sent | G2: Open Rate | H2: Open Rate (Benchmark) | I2: Click-Through Rate (clicks / devilieries) | J2: CTR (Benchmark) | K2: Click-To-Open Rate | L2: CTO (Benchmark) | M2: Delivery Rate | N2: Delivery Rate (Benchmark) | O2: Unsubscribe % | P2: Unsubscribe % (Benchmark) | Q2: Subject Line | R2: Notes | S2: Footer
A3: Call for Proposals Email #1 (All Prospects) | B3: All Prospects | C3: 45821 | D3: Friday | E3: 0.54166667 | F3: 21125 | G3: 0.409 | H3: 0.15 | I3: =463/17430 -> 0.026563396 | J3: 0.03 | K3: =463/7135 -> 0.064891381 | L3: 0.06 | M3: =17430/21125 -> 0.82508876 | N3: 0.95 | O3: =10/17430 -> 0.00057372347 | P3: 0.0025 | Q3: {NOW OPEN} ATC 2026 Call for Programs
A4: Call for Proposals Email #2 (All Prospects) | B4: All Prospects | C4: 45828 | D4: Friday | E4: 0.58888889 | F4: 21109 | G4: 0.576 | H4: 0.15 | I4: =4064/17327 -> 0.23454724 | J4: 0.03 | K4: =4064/9980 -> 0.40721443 | L4: 0.06 | M4: =17327/21109 -> 0.82083472 | N4: 0.95 | O4: =10/17327 -> 0.00057713395 | P4: 0.0025 | Q4: Your Voice. Your Ideas. Your Congress.
A5: Call for Proposals Email #3 (All Prospects) | B5: All Prospects | C5: 45834 | D5: Thursday | E5: 0.61458333 | F5: 21091 | G5: 0.49 | H5: 0.15 | I5: 0.093 | J5: 0.03 | K5: =1627/8578 -> 0.18967125 | L5: 0.06 | M5: =17501/21091 -> 0.82978522 | N5: 0.95 | O5: =12/17501 -> 0.0006856751 | P5: 0.0025 | Q5: Tips to Strengthen Your ATC 2026 Session Proposal
A6: Call for Proposals Email #4a (Past Submitters) | B6: Past Submitters | C6: 45847 | D6: Wednesday | E6: 0.70833333 | F6: 190 | G6: 0.705 | H6: 0.15 | I6: =28/176 -> 0.15909091 | J6: 0.03 | K6: =28/124 -> 0.22580645 | L6: 0.06 | M6: =176/190 -> 0.92631579 | N6: 0.95 | O6: 0 | P6: 0.0025 | Q6: You're Invited Back: Call for 2026 Proposals
A7: Call for Proposals Email #4b (All Prospects) | B7: All Prospects | C7: 45847 | D7: Wednesday | E7: 0.70833333 | F7: 20866 | G7: 0.443 | H7: 0.15 | I7: 0.09 | J7: 0.03 | K7: =1530/7552 -> 0.20259534 | L7: 0.06 | M7: =17044/20866 -> 0.81683121 | N7: 0.95 | O7: =8/17044 -> 0.00046937339 | P7: 0.0025 | Q7: Be Heard at ATC 2026: Submit Your Idea
A8: Call for Proposals Email #5 (All Prospects) | B8: All Prospects | C8: 45855 | D8: Thursday | E8: 0.45833333 | F8: 21041 | G8: 0.415 | H8: 0.15 | I8: =1112/17315 -> 0.064221773 | J8: 0.03 | K8: =1112/7178 -> 0.1549178 | L8: 0.06 | M8: =17315/21041 -> 0.82291716 | N8: 0.95 | O8: =7/17315 -> 0.00040427375 | P8: 0.0025 | Q8: Final Weeks! Submit Your Proposal for ATC 2026
A9: INTL Email #1 - Survey (International Attendees) | B9: International Attendees | C9: 45861 | D9: Wednesday | E9: 0.35416667 | F9: 2824 | G9: 0.511 | H9: 0.15 | I9: 0.086 | J9: 0.03 | K9: =195/1145 -> 0.17030568 | L9: 0.06 | M9: =2521/2824 -> 0.89270538 | N9: 0.95 | O9: =1/2521 -> 0.00039666799 | P9: 0.0025 | Q9: Your Input Is Needed
A10: Call for Proposals Email #6 (All Prospects) | B10: All Prospects | C10: 45860 | D10: Tuesday | E10: 0.58333333 | F10: 21026 | G10: 0.512 | H10: 0.15 | I10: 0.017 | J10: 0.03 | K10: =273/7750 -> 0.035225806 | L10: 0.06 | M10: =17193/21026 -> 0.81770189 | N10: 0.95 | O10: =12/17193 -> 0.00069795847 | P10: 0.0025 | Q10: Your Perspective Matters: Submit Your ATC 2026 Proposal
A11: Call for Proposals Email #7 (All Prospects) | B11: All Prospects | C11: 45876 | D11: Thursday | E11: 0.70833333 | F11: 21002 | G11: 0.46 | H11: 0.15 | I11: =374/17126 -> 0.021838141 | J11: 0.03 | K11: =374/7875 -> 0.047492063 | L11: 0.06 | M11: =17126/21002 -> 0.81544615 | N11: 0.95 | O11: =6/17126 -> 0.00035034451 | P11: 0.0025 | Q11: Deadline Approaching: Final Week to Submit for ATC 2026
A12: Call for Proposals Email #8 (All Prospects) | B12: All Prospects | C12: 45881 | D12: Tuesday | E12: 0.46388889 | F12: 20993 | G12: 0.443 | H12: 0.15 | I12: =245/17103 -> 0.014324972 | J12: 0.03 | K12: =245/7577 -> 0.032334697 | L12: 0.06 | M12: =17103/20993 -> 0.81470014 | N12: 0.95 | O12: =11/17103 -> 0.00064316202 | P12: 0.0025 | Q12: 48 Hours Left
A13: Call for Proposals & State-of-the-Art Speakers Email #9.5 Deadline Extended (All Prospects) | B13: All Prospects | C13: 45883 | D13: Thursday | E13: 0.70833333 | F13: 33567 | G13: 0.43 | H13: 0.15 | I13: 0.012 | J13: 0.03 | K13: =350/12269 -> 0.028527182 | L13: 0.06 | M13: =28520/33567 -> 0.849644 | N13: 0.95 | O13: =27/28520 -> 0.00094670407 | P13: 0.0025 | Q13: Deadline Extended for ATC 2026 Proposals
A14: Call for Abstracts Email #10 (All Prospects) | B14: All Prospects | C14: 45887 | D14: Monday | E14: 0.54166667 | F14: 19571 | G14: 0.443 | H14: 0.15 | I14: =222/17937 -> 0.012376652 | J14: 0.03 | K14: =222/7940 -> 0.027959698 | L14: 0.06 | M14: =17937/19571 -> 0.91650912 | N14: 0.95 | O14: =3/17937 -> 0.00016725205 | P14: 0.0025 | Q14: Now Open: ATC 2026 Abstract Submissions
A15: Email #9 - Call for Proposals - 24 Hours Left 8/21 (All Prospects) | B15: All Prospects | C15: 45890 | D15: Thursday | E15: 0.48125 | F15: 19570 | G15: 0.42 | H15: 0.15 | I15: =1354/17859 -> 0.075816115 | J15: 0.03 | K15: =1354/7508 -> 0.18034097 | L15: 0.06 | M15: =17859/19570 -> 0.91257026 | N15: 0.95 | O15: =11/17859 -> 0.00061593594 | P15: 0.0025 | Q15: Ends Tonight: Your Last Chance to Submit
A16: Call for Abstracts Email #10.5 | B16: Past Abstract Submitters & Past Attendees: ATC2026 | C16: 45904 | D16: Thursday | E16: 0.45833333 | F16: 5851 | G16: 0.095 | H16: 0.15 | I16: =499/5227 -> 0.09546585 | J16: 0.03 | K16: =499/499 -> 1 | L16: 0.06 | M16: =5227/5851 -> 0.89335156 | N16: 0.95 | O16: =3/5227 -> 0.00057394299 | P16: 0.0025 | Q16: ATC 2026 Abstracts Deadline Is November 13
A17: Awareness Email #1 Save the Date | B17: WTC Attendees | C17: 45908 | D17: Monday | E17: 0.70833333 | F17: 6180 | G17: 0.016 | H17: 0.15 | I17: =95/5939 -> 0.015995959 | J17: 0.03 | K17: 1 | L17: 0.06 | M17: =5939/6180 -> 0.96100324 | N17: 0.95 | O17: =15/5939 -> 0.0025256777 | P17: 0.0025 | Q17: Learning Doesn't Have An Expiration Date
A18: Awareness Email #2 Save the Date | B18: All Prospects excluding WTC Attendees | C18: 45908 | D18: Monday | E18: 0.70833333 | F18: 16868 | G18: 0.01 | H18: 0.15 | I18: 0.01 | J18: 0.03 | K18: 1 | L18: 0.06 | M18: =15099/16868 -> 0.89512687 | N18: 0.95 | O18: =5/15099 -> 0.00033114776 | P18: 0.0025 | Q18: Is Boston in Your Budget Yet?
A19: Call for Abstracts Email #11a | B19: All Prospects (11a Half) | C19: 45911 | D19: Thursday | E19: 0.58333333 | F19: 10089 | G19: 0.433 | H19: 0.15 | I19: 0.005 | J19: 0.03 | K19: =48/3998 -> 0.012006003 | L19: 0.06 | M19: =9227/10089 -> 0.91456041 | N19: 0.95 | O19: =4/9227 -> 0.00043351035 | P19: 0.0025 | Q19: Have You Submitted Your ATC 2026 Abstract?
A20: Call For Abstracts Email #11b | B20: All Prospects (11b Half) | C20: 45911 | D20: Thursday | E20: 0.58333333 | F20: 10087 | G20: 0.44 | H20: 0.15 | I20: =73/9201 -> 0.0079339202 | J20: 0.03 | K20: =73/4046 -> 0.018042511 | L20: 0.06 | M20: =9201/10087 -> 0.91216417 | N20: 0.95 | O20: =2/9201 -> 0.00021736768 | P20: 0.0025 | Q20: Have You Submitted Your ATC 2026 Abstract?
A21: Call for Abstracts Email #12a Visa Focus (International) | B21: International Attendees | C21: 45924 | D21: Wednesday | E21: 0.35416667 | F21: 2711 | G21: 0.467 | H21: 0.15 | I21: 0.027 | J21: 0.03 | K21: =71/1241 -> 0.057211926 | L21: 0.06 | M21: =2655/2711 -> 0.97934342 | N21: 0.95 | O21: =2/2655 -> 0.00075329567 | P21: 0.0025 | Q21: Important - Abstract Submissions for ATC 2026
A22: Call for Abstracts Email #12b | B22: 2026 Attendee House Marketing List (excluding unsubs & undeliverable & INTL) | C22: 45930 | D22: Tuesday | E22: 0.70833333 | F22: 16156 | G22: 0.42 | H22: 0.15 | I22: 0.0009 | J22: 0.03 | K22: =146/6578 -> 0.022195196 | L22: 0.06 | M22: =15671/16156 -> 0.96998019 | N22: 0.95 | O22: =8/15671 -> 0.0005104971 | P22: 0.0025 | Q22: Be Part of the Breakthroughs at ATC 2026
A23: Call for Abstracts Email #13 | B23: 2026 Attendee House Marketing List (excluding unsubs & undeliverable & INTL) | C23: 45938 | D23: Wednesday | E23: 0.58333333 | F23: 18863 | G23: 0.43 | H23: 0.15 | I23: 0.091 | J23: 0.03 | K23: =1668/7843 -> 0.21267372 | L23: 0.06 | M23: =18245/18863 -> 0.96723745 | N23: 0.95 | O23: =4/18245 -> 0.00021923815 | P23: 0.0025 | Q23: Keep This In Mind Before Hitting Submit
A24: Awareness Email #3 Save the Date | B24: 2026 Attendee House Marketing List (excluding unsubs & undeliverable) | C24: 45946 | D24: Thursday | E24: 0.45833333 | F24: 18868 | G24: 0.455 | H24: 0.15 | I24: =2113/18248 -> 0.11579351 | J24: 0.03 | K24: =2113/8304 -> 0.25445568 | L24: 0.06 | M24: =18248/18868 -> 0.96714013 | N24: 0.95 | O24: =3/18248 -> 0.00016440158 | P24: 0.0025 | Q24: ATC 2026 is Close to Home!
A25: Call for Abstracts Email #14 | B25: 2026 Attendee House Marketing List (excluding unsubs & undeliverable) | C25: 45953 | D25: Thursday | E25: 0.70833333 | F25: 18871 | G25: 0.524 | H25: 0.15 | I25: =189/18217 -> 0.010374925 | J25: 0.03 | K25: =189/9452 -> 0.019995768 | L25: 0.06 | M25: =18217/18871 -> 0.96534365 | N25: 0.95 | O25: =3/18217 -> 0.00016468134 | P25: 0.0025 | Q25: ATC 2026: Where Ambition Shapes the Future
A26: Call for Abstracts Email #15 | B26: 2026 Attendee House Marketing List (excluding unsubs & undeliverable) | C26: 45959 | D26: Wednesday | E26: 0.45833333 | F26: 19067 | G26: 0.365 | H26: 0.15 | I26: =169/18393 -> 0.0091882781 | J26: 0.03 | K26: =169/6719 -> 0.025152552 | L26: 0.06 | M26: =18393/19067 -> 0.96465097 | N26: 0.95 | O26: =8/18393 -> 0.00043494808 | P26: 0.0025 | Q26: Get Published in the American Journal of Transplantation
A27: Call for Abstracts Email #16 | B27: 2026 Attendee House Marketing List (excluding unsub & undeliverable & INTL "no" | C27: 45967 | D27: Thursday | E27: 0.58333333 | F27: 18922 | G27: 0.458 | H27: 0.15 | I27: 0.013 | J27: 0.03 | K27: =244/8397 -> 0.029057997 | L27: 0.06 | M27: =18322/18992 -> 0.96472199 | N27: 0.95 | O27: =7/18322 -> 0.00038205436 | P27: 0.0025 | Q27: Submit your abstract before the Nov. 13 deadline and advance the science of transplantation
A28: Call for Abstracts Email #17 | B28: 2026 Attendee House Marketing List (excluding unsub & undeliverable & INTL "no") | C28: 45972 | D28: Tuesday | E28: 0.45833333 | F28: 18989 | G28: 0.036 | H28: 0.15 | I28: 0.014 | J28: 0.03 | K28: =261/663 -> 0.39366516 | L28: 0.06 | M28: =18282/18989 -> 0.96276792 | N28: 0.95 | O28: =11/18282 -> 0.00060168472 | P28: 0.0025 | Q28: The Clock is Ticking | S28: AST
A29: Call for Abstracts Email #18 | B29: 2026 Attendee House Marketing List (excluding unsub & undeliverable & INTL "no") | C29: 45974 | D29: Thursday | E29: 0.58333333 | F29: 18971 | G29: 0.012 | H29: 0.15 | I29: 0.012 | J29: 0.03 | K29: 1 | L29: 0.06 | M29: =18264/18971 -> 0.96273259 | N29: 0.95 | O29: =4/18264 -> 0.00021901007 | P29: 0.0025 | Q29: Important Update: Abstracts Deadline Extended | S29: ASTS
A30: Call for Abstracts Email #19 (+ resend) | B30: 2026 Attendee House Marketing List (excluding unsub & undeliverable & INTL "no") | C30: 45980 | D30: Wednesday | E30: 0.58333333 | F30: 29132 | G30: 0.527 | H30: 0.15 | I30: 0.018 | J30: 0.03 | K30: =334/10042 -> 0.033260307 | L30: 0.06 | M30: =28341/29132 -> 0.97284773 | N30: 0.95 | O30: =11/28341 -> 0.00038813027 | P30: 0.0025 | Q30: Abstract Deadline is TOMORROW at 11:59 PM ET | S30: skip
A31: Awareness Email #4 Save the Date | B31: 2026 Attendee House Marketing List (excluding unsub & undeliverable & INTL "no") | C31: 45993 | D31: Tuesday | E31: 0.45833333 | F31: 18955 | G31: 0.416 | H31: 0.15 | I31: 0.015 | J31: 0.03 | K31: =267/7595 -> 0.035154707 | L31: 0.06 | M31: =18244/18955 -> 0.96249011 | N31: 0.95 | O31: =11/18244 -> 0.00060293795 | P31: 0.0025 | Q31: ATC 2026: Where The Transplant Ecosystem Unites | S31: AST
A32: Awareness Email #5A Save the Date | B32: 2026 Attendee House Marketing List (excluding unsubs & undeliverable & INTL)) | C32: 46008 | D32: Wednesday | E32: 0.58333333 | F32: 16335 | G32: 0.376 | H32: 0.15 | I32: 0.02 | J32: 0.03 | K32: =308/5885 -> 0.052336449 | L32: 0.06 | M32: =15642/16335 -> 0.95757576 | N32: 0.95 | O32: =7/15642 -> 0.00044751311 | P32: 0.0025 | Q32: Get Ready - Registration Opens Soon | S32: ASTS
A33: Awareness Email #5B Save the Date | B33: International Attendees | C33: 46008 | D33: Wednesday | E33: 0.58333333 | F33: 2367 | G33: 0.394 | H33: 0.15 | I33: 0.019 | J33: 0.03 | K33: =44/900 -> 0.048888889 | L33: 0.06 | M33: =2285/2367 -> 0.96535699 | N33: 0.95 | O33: =1/2285 -> 0.00043763676 | P33: 0.0025 | Q33: Get Ready - Registration Opens Soon | S33: ASTS
A34: Call for Abstracts Email #19.5 | B34: 2026 Attendee House Marketing List (excluding unsub & undeliverable & INTL "no") | C34: 46028 | D34: Monday | E34: 0.58333333 | F34: 18958 | G34: 0.429 | H34: 0.15 | I34: =194/18156 -> 0.010685173 | J34: 0.03 | K34: =194/7784 -> 0.024922919 | L34: 0.06 | M34: =18156/18958 -> 0.95769596 | N34: 0.95 | O34: =7/18156 -> 0.00038554748 | P34: 0.0025 | Q34: How to Prepare: Late-Breaking Abstracts Open Next Week | S34: skip
A35: Call for Late-Breaking Abstracts Email #20 | B35: 2026 Attendee House Marketing List (excluding unsub & undeliverable & INTL "no") | C35: 46034 | D35: Monday | E35: 0.45833333 | F35: 18968 | G35: 0.396 | H35: 0.15 | I35: =565/18123 -> 0.031175854 | J35: 0.03 | K35: =568/7184 -> 0.079064588 | L35: 0.06 | M35: =18123/18968 -> 0.95545129 | N35: 0.95 | O35: =4/18123 -> 0.00022071401 | P35: 0.0025 | Q35: Portal Open: Late-Breaking Abstracts | S35: AST
A36: Awareness Email #6 Save the Date | B36: 2026 Attendee House Marketing List (excluding unsub & undeliverable & INTL "no") | C36: 46037 | D36: Thursday | E36: 0.58333333 | F36: 19986 | G36: 0.417 | H36: 0.15 | I36: 0.019 | J36: 0.03 | K36: =340/7560 -> 0.044973545 | L36: 0.06 | M36: =18140/18986 -> 0.95544085 | N36: 0.95 | O36: =5/18140 -> 0.00027563396 | P36: 0.0025 | Q36: Your ATC 2026 Guide: 5 Days of Breakthroughs | S36: ASTS
A37: Call for Late Breaking Abstracts Email #21a | B37: International Attendees | C37: 46044 | D37: Thursday | E37: 0.45833333 | F37: 2362 | G37: 0.384 | H37: 0.15 | I37: 0.021 | J37: 0.03 | K37: =48/873 -> 0.054982818 | L37: 0.06 | M37: =2271/2362 -> 0.96147333 | N37: 0.95 | O37: 0 | P37: 0.0025 | Q37: Submit Your Late-Breaking Abstract for ATC 2026 | S37: skipped
A38: Call for Late Breaking Abstracts Email #21b | B38: 2026 Attendee House Marketing List (excluding unsubs & undeliverable & INTL)) | C38: 46044 | D38: Thursday | E38: 0.45833333 | F38: 16352 | G38: 0.385 | H38: 0.15 | I38: 0.032 | J38: 0.03 | K38: =494/6004 -> 0.082278481 | L38: 0.06 | M38: =15589/16352 -> 0.95333904 | N38: 0.95 | O38: 0.00032073898 | P38: 0.0025 | Q38: Submit Your Late-Breaking Abstract for ATC 2026 | S38: skipped
A39: Registration Email #1 | B39: 2026 Attendee House Marketing List (excluding unsub & undeliverable & INTL "no") | C39: 46048 | D39: Monday | E39: 0.47916667 | F39: 18763 | G39: 0.376 | H39: 0.15 | I39: 0.019 | J39: 0.03 | K39: =340/6879 -> 0.049425789 | L39: 0.06 | M39: =18310/18763 -> 0.97585674 | N39: 0.95 | O39: =7/18310 -> 0.00038230475 | P39: 0.0025 | Q39: {NOW OPEN} Register for ATC 2026 | S39: skipped
A40: Call for Late Breaking Abstracts Email #22 | B40: 2026 Attendee House Marketing List (excluding unsub & undeliverable & INTL "no") | C40: 46059 | D40: Friday | E40: 0.45833333 | F40: 18592 | G40: 0.611 | H40: 0.15 | I40: =106/18069 -> 0.005866401 | J40: 0.03 | K40: =106/11049 -> 0.0095936284 | L40: 0.06 | M40: =18069/18592 -> 0.97186962 | N40: 0.95 | O40: =1/18069 -> 5.5343406e-05 | P40: 0.0025 | Q40: 72 Hours Left: Late-Breaking Abstracts Due Feb. 9
A41: Registration Email #2 | B41: 2026 Attendee House Marketing List (excluding unsub & undeliverable & INTL "no") | C41: 46052 | D41: Friday | E41: 0.45833333 | F41: 18586 | G41: 0.414 | H41: 0.15 | I41: 0.013 | J41: 0.03 | K41: =234/7505 -> 0.031179214 | L41: 0.06 | M41: =18139/18586 -> 0.97594964 | N41: 0.95 | O41: =7/18139 -> 0.00038590882 | P41: 0.0025 | Q41: ATC 2026 Is Taking Shape – Join Us!
A42: Registration Email #2 - Resend | B42: 2026 Attendee House Marketing List (excluding unsub & undeliverable & INTL "no") | C42: 46056 | D42: Tuesday | E42: 0.58333333 | F42: 10658 | G42: 0.174 | H42: 0.15 | I42: 0.128 | J42: 0.03 | K42: =1354/1845 -> 0.73387534 | L42: 0.06 | M42: =10609/10658 -> 0.99540251 | N42: 0.95 | O42: =4/10609 -> 0.00037703836 | P42: 0.0025
A43: Registration Email #2.5 | B43: 2026 Main Prospecting Registration Send List | C43: 46064 | D43: Wednesday | E43: 0.58333333 | F43: 18757 | G43: 0.418 | H43: 0.15 | I43: 0.269 | J43: 0.03 | K43: =4912/7622 -> 0.64445028 | L43: 0.06 | M43: =18252/18757 -> 0.97307672 | N43: 0.95 | O43: =6/18252 -> 0.0003287311 | P43: 0.0025 | Q43: Introducing the State-of-the-Art Speakers
A44: Registration Email #2.5 Send to Non-Openers | B44: Reg Email 2.5 Non-Openers Resend | C44: 46070 | D44: Tuesday | E44: 0.45833333 | F44: 10646 | H44: 0.15 | J44: 0.03 | L44: 0.06 | N44: 0.95 | P44: 0.0025
A45: Registration Email #3c | B45: Boston Drive-In Audience | C45: 46073 | D45: Friday | E45: 0.45833333 | F45: 445 | G45: 0.555 | H45: 0.15 | I45: 0.028 | J45: 0.03 | K45: =12/239 -> 0.050209205 | L45: 0.06 | M45: =431/445 -> 0.96853933 | N45: 0.95 | O45: 0 | P45: 0.0025 | Q45: ATC 2026 Is Heading to You
A46: Registration Email #3b | B46: International Attendees | C46: 46073 | D46: Friday | E46: 0.45833333 | F46: 2315 | G46: 0.442 | H46: 0.15 | I46: 0.025 | J46: 0.03 | K46: =57/994 -> 0.057344064 | L46: 0.06 | M46: =2250/2315 -> 0.97192225 | N46: 0.95 | O46: 0 | P46: 0.0025 | Q46: ATC 2026: A Global Gathering in Boston
A47: Registration Email #3a | B47: ATC 2026 US Attendees | C47: 46073 | D47: Friday | E47: 0.45833333 | F47: 16122 | G47: 0.49 | H47: 0.15 | I47: 0.027 | J47: 0.03 | K47: =423/7657 -> 0.055243568 | L47: 0.06 | M47: =15622/16122 -> 0.96898648 | N47: 0.95 | O47: 0 | P47: 0.0025 | Q47: ATC 2026 Is Heading to Boston
A48: Registration Email #4a | B48: Past Registrations: 2024 | C48: 46078 | D48: Wednesday | E48: 0.58333333 | F48: 4299 | G48: 0.492 | H48: 0.15 | I48: 0.029 | J48: 0.03 | K48: =113/1899 -> 0.059505003 | L48: 0.06 | M48: =3862/4299 -> 0.89834845 | N48: 0.95 | O48: =12/3862 -> 0.0031071983 | P48: 0.0025 | Q48: New Experiences Await at ATC 2026
A49: Registration Email #4b | B49: International Attendees | C49: 46078 | D49: Wednesday | E49: 0.58333333 | F49: 2309 | G49: 0.391 | H49: 0.15 | I49: 0.031 | J49: 0.03 | K49: =69/872 -> 0.07912844 | L49: 0.06 | M49: =2230/2309 -> 0.96578605 | N49: 0.95 | O49: 0 | P49: 0.0025 | Q49: Plan Your Trip & Save by March 6
A50: Registration Email #4c | B50: Main Prospecting Send (Excluding International & Past Attendees) | C50: 46078 | D50: Wednesday | E50: 0.58333333 | F50: 13776 | G50: 0.451 | H50: 0.15 | I50: 0.023 | J50: 0.03 | K50: =300/5974 -> 0.05021761 | L50: 0.06 | M50: =13249/13776 -> 0.96174506 | N50: 0.95 | O50: =6/13249 -> 0.00045286437 | P50: 0.0025 | Q50: Don’t Miss Early Bird Savings for ATC 2026
A51: Registration Email #5 | B51: 2026 Main Prospecting Registration | C51: 46087 | D51: Friday | E51: 0.45833333 | F51: 17907 | G51: 0.415 | H51: 0.15 | I51: =1616/17326 -> 0.09327023 | J51: 0.03 | K51: =1616/7190 -> 0.22475661 | L51: 0.06 | M51: =17326/17907 -> 0.96755459 | N51: 0.95 | O51: =13/17326 -> 0.00075031744 | P51: 0.0025 | Q51: {DEADLINE}: Early Bird Ends TONIGHT
A52: Registration Email #6 | B52: 2026 Main Prospecting Registration Send List | C52: 46099 | D52: Wednesday | E52: 0.58333333 | F52: 17526 | G52: 0.374 | H52: 0.15 | I52: 0.029 | J52: 0.03 | K52: =492/6329 -> 0.077737399 | L52: 0.06 | M52: =16921/17526 -> 0.96547986 | N52: 0.95 | O52: =3/16291 -> 0.00018415076 | P52: 0.0025 | Q52: Inside the ATC 2026 Education Program
A53: Nurture Email #1 | B53: 2026 Registered Attendees | C53: 46104 | D53: Monday | E53: 0.58333333 | F53: 1890 | G53: 0.509 | H53: 0.15 | I53: 0.053 | J53: 0.03 | K53: =98/942 -> 0.10403397 | L53: 0.06 | M53: =1851/1890 -> 0.97936508 | N53: 0.95 | O53: 0 | P53: 0.0025 | Q53: Plan Ahead: Secure Your Hotel + See What’s Ahead
A54: Registration Email #7a | B54: US Prospects ATC 2026 | C54: 46112 | D54: Tuesday | E54: 0.45833333 | F54: 16202 | G54: 0.39 | H54: 0.15 | I54: 0.027 | J54: 0.03 | K54: =417/6107 -> 0.068282299 | L54: 0.06 | M54: =15656/16202 -> 0.96630046 | N54: 0.95 | O54: =8/15656 -> 0.0005109862 | P54: 0.0025 | Q54: REMINDER} Register For ATC 2026 Today
A55: Registration Email #7b | B55: England & Ghana - Scotland & Morocco | C55: 46112 | D55: Tuesday | E55: 0.35416667 | F55: 112 | G55: 0.472 | H55: 0.15 | I55: 0.056 | J55: 0.03 | K55: =6/51 -> 0.11764706 | L55: 0.06 | M55: =109/112 -> 0.97321429 | N55: 0.95 | O55: 0 | P55: 0.0025 | Q55: {REMINDER} Register For ATC 2026 Today
A56: Registration Email #7d | B56: Norway vs. France | C56: 46112 | D56: Tuesday | E56: 0.36458333 | F56: 97 | G56: 0.462 | H56: 0.15 | I56: 0.022 | J56: 0.03 | K56: =2/43 -> 0.046511628 | L56: 0.06 | M56: =93/97 -> 0.95876289 | N56: 0.95 | O56: 0 | P56: 0.0025 | Q56: {REMINDER} Register For ATC 2026 Today
A57: Registration Email #7e | B57: International Excluding Ghana, UK, Morocco, Scotland, France, Norway | C57: 46112 | D57: Tuesday | E57: 0.375 | F57: 2331 | G57: 0.383 | H57: 0.15 | I57: 0.02 | J57: 0.03 | K57: =45/866 -> 0.051963048 | L57: 0.06 | M57: =2260/2331 -> 0.96954097 | N57: 0.95 | O57: =1/2260 -> 0.00044247788 | P57: 0.0025 | Q57: Plan Your Trip & Save
A58: Registration Email #8 | B58: 2026 Main Prospecting Registration Send List | C58: 46115 | D58: Friday | E58: 0.58333333 | F58: 17395 | G58: 0.414 | H58: 0.15 | I58: 0.07 | J58: 0.03 | K58: =1169/6974 -> 0.1676226 | L58: 0.06 | M58: 0.9633 | N58: 0.95 | O58: =5/16757 -> 0.00029838277 | P58: 0.0025 | Q58: Honor Donate Life Month and Advance Transplantation
A59: Registration Email #9 | B59: 2026 Main Prospecting Registration Send List | C59: 46121 | D59: Thursday | E59: 0.45833333 | F59: 17398 | G59: 0.376 | H59: 0.15 | I59: 0.021 | J59: 0.03 | K59: =345/5934 -> 0.058139535 | L59: 0.06 | M59: =16811/17398 -> 0.96626049 | N59: 0.95 | O59: =4/16811 -> 0.00023793944 | P59: 0.0025 | Q59: Don't Miss the Opportunity to Learn from Nobel Laureates
A60: Registration Email #10a | B60: 2026 Main Prospecting Registration Send Excluding International | C60: 46126 | D60: Tuesday | E60: 0.45833333 | F60: 14897 | G60: 0.411 | H60: 0.15 | I60: 0.043 | J60: 0.03 | K60: =620/3126 -> 0.19833653 | L60: 0.06 | M60: =14336/14897 -> 0.96234141 | N60: 0.95 | O60: =4/14336 -> 0.00027901786 | P60: 0.0025 | Q60: Register Now | Hotels Are Nearly Full for ATC
A61: Registration Email #10b | B61: International Attendees | C61: 46126 | D61: Tuesday | E61: 0.45833333 | F61: 2470 | G61: 0.443 | H61: 0.15 | I61: 0.032 | J61: 0.03 | K61: =76/568 -> 0.13380282 | L61: 0.06 | M61: =2396/2470 -> 0.97004049 | N61: 0.95 | O61: 0 | P61: 0.0025 | Q61: Register Now | Hotels Are Nearly Full for ATC
A62: Registration Email #11 | B62: 2026 Main Prospecting Registration Send List | C62: 46128 | D62: Thursday | E62: 0.45833333 | F62: 17363 | G62: 0.409 | H62: 0.15 | I62: 0.026 | J62: 0.03 | K62: =432/3549 -> 0.12172443 | L62: 0.06 | M62: =16722/17363 -> 0.96308242 | N62: 0.95 | O62: =5/16722 -> 0.0002990073 | P62: 0.0025 | Q62: Your Questions About ATC, Answered
A63: Nurture Email #2 | B63: 2026 Registered Attendees | C63: 46132 | D63: Monday | E63: 0.58333333 | F63: 2200 | G63: 0.561 | H63: 0.15 | I63: 0.059 | J63: 0.03 | K63: =128/796 -> 0.16080402 | L63: 0.06 | M63: =2160/2200 -> 0.98181818 | N63: 0.95 | O63: 0 | P63: 0.0025 | Q63: We were wondering...
A64: Registration Email #12a | B64: AST & ASTS Members | C64: 46137 | D64: Saturday | E64: 0.45833333 | F64: 4936 | G64: 0.529 | H64: 0.15 | I64: 0.033 | J64: 0.03 | K64: =157/1273 -> 0.12333071 | L64: 0.06 | M64: =4697/4936 -> 0.95158023 | N64: 0.95 | O64: 0 | P64: 0.0025 | Q64: {MEMBER RATE} Advance Pricing Ends April 30
A65: Registration Email #12b | B65: 2026 Main Prospecting Send (Excluding Members) | C65: 46137 | D65: Saturday | E65: 0.45833333 | F65: 12534 | G65: 0.393 | H65: 0.15 | I65: 0.091 | J65: 0.03 | K65: =1091/2409 -> 0.45288501 | L65: 0.06 | M65: =11982/12534 -> 0.95595979 | N65: 0.95 | O65: =4/11982 -> 0.00033383408 | P65: 0.0025 | Q65: Advance Pricing Ends April 30 (Members Pay Less)
A66: Registration Email #13 | B66: 2026 Main Prospecting Registration Send List | C66: 46135 | D66: Thursday | E66: 0.45833333 | F66: 17296 | G66: 0.434 | H66: 0.15 | I66: 0.097 | J66: 0.03 | K66: =1611/3868 -> 0.41649431 | L66: 0.06 | M66: =16639/17296 -> 0.96201434 | N66: 0.95 | O66: =2/16639 -> 0.00012019953 | P66: 0.0025 | Q66: JUST RELEASED: ATC 2026 Program
A67: Registration Email #14 | B67: 2026 Main Prospecting Registration Send List | C67: 46141 | D67: Wednesday | E67: 0.45833333 | F67: 17290 | G67: 0.363 | H67: 0.15 | I67: 0.025 | J67: 0.03 | K67: =411/3159 -> 0.13010446 | L67: 0.06 | M67: =16695/17290 -> 0.96558704 | N67: 0.95 | O67: =2/16695 -> 0.00011979635 | P67: 0.0025 | Q67: 24 Hours Left to Save $200
A68: Registration Email #15a | B68: Past Registrations: 2024 | C68: 46149 | D68: Thursday | E68: 0.45833333 | F68: 3200 | G68: 0.43 | H68: 0.15 | I68: 0.038 | J68: 0.03 | K68: =109/695 -> 0.15683453 | L68: 0.06 | M68: 0.8978125 | N68: 0.95 | O68: =2/2873 -> 0.00069613644 | P68: 0.0025 | Q68: Reconnecting at ATC
A69: Registration Email #15b | B69: ATC Propsects with no Prior Attendance | C69: 46149 | D69: Thursday | E69: 0.45833333 | F69: 14461 | G69: 0.373 | H69: 0.15 | I69: 0.022 | J69: 0.03 | K69: =304/2315 -> 0.13131749 | L69: 0.06 | M69: 0.96 | N69: 0.95 | O69: =4/13884 -> 0.00028810141 | P69: 0.0025 | Q69: Who could you meet at ATC?
A70: Registration Email #16a | B70: NP / Advanced Practice | C70: 46155 | D70: Wednesday | E70: 0.625 | F70: 159 | G70: 0.408 | H70: 0.15 | I70: 0.027 | J70: 0.03 | K70: =4/25 -> 0.16 | L70: 0.06 | M70: =147/159 -> 0.9245283 | N70: 0.95 | O70: 0 | P70: 0.0025 | Q70: The AI Sessions at ATC 2026 Are Built for Your Practice
A71: Registration Email #16b | B71: Transplant Program Directors | C71: 46155 | D71: Wednesday | E71: 0.63541667 | F71: 473 | G71: 0.478 | H71: 0.15 | I71: 0.04 | J71: 0.03 | K71: =17/102 -> 0.16666667 | L71: 0.06 | M71: =429/473 -> 0.90697674 | N71: 0.95 | O71: 0 | P71: 0.0025 | Q71: What AI Means for Your Program: Sessions at ATC 2026
A72: Registration Email #16c | B72: Trainees | C72: 46155 | D72: Wednesday | E72: 0.64236111 | F72: 1597 | G72: 0.43 | H72: 0.15 | I72: 0.019 | J72: 0.03 | K72: =26/305 -> 0.085245902 | L72: 0.06 | M72: =1347/1597 -> 0.84345648 | N72: 0.95 | O72: =1/1347 -> 0.0007423905 | P72: 0.0025 | Q72: The Career You’re Entering Runs on AI. These ATC Sessions Show You How.
A73: Registration Email #16d | B73: All Other Prospects | C73: 46155 | D73: Wednesday | E73: 0.64583333 | F73: 15411 | G73: 0.387 | H73: 0.15 | I73: 0.035 | J73: 0.03 | K73: =516/2552 -> 0.20219436 | L73: 0.06 | M73: =14806/15411 -> 0.96074233 | N73: 0.95 | O73: =7/14806 -> 0.0004727813 | P73: 0.0025 | Q73: ATC 2026 Goes Deep on AI. Here’s What’s on the Program.
A74: Registration Email #17 | B74: 2026 Main Prospecting Registration Send List | C74: 46157 | D74: Friday | E74: 0.45833333 | F74: 17274 | G74: 0.471 | H74: 0.15 | I74: 0.021 | J74: 0.03 | K74: =311/2955 -> 0.10524535 | L74: 0.06 | M74: =16600/17274 -> 0.96098182 | N74: 0.95 | O74: =7/16600 -> 0.00042168675 | P74: 0.0025 | Q74: Who could you meet at ATC?
A75: Registration Email #18a | B75: Past Registrations: 2024 (who have not registered for ATC 2026) | C75: 46163 | D75: Thursday | E75: 0.45833333 | F75: 2981 | G75: 0.414 | H75: 0.15 | I75: 0.029 | J75: 0.03 | K75: =77/604 -> 0.12748344 | L75: 0.06 | M75: =2657/2981 -> 0.89131164 | N75: 0.95 | O75: =3/2657 -> 0.001129093 | P75: 0.0025 | Q75: You know the value of ATC. Don’t miss these Immunology Sessions.
A76: Registration Email #18b | B76: 2026 Main Prospecting Registration Send List (excluding past attendees) | C76: 46163 | D76: Thursday | E76: 0.45833333 | F76: 16111 | G76: 0.394 | H76: 0.15 | I76: 0.019 | J76: 0.03 | K76: =290/2872 -> 0.10097493 | L76: 0.06 | M76: =15482/16111 -> 0.96095835 | N76: 0.95 | O76: =4/15482 -> 0.00025836455 | P76: 0.0025 | Q76: Explore the latest advances in Immunology at ATC 2026
A77: Registration Email #19a | B77: 2026 Boston Drive-In Audience | C77: 46164 | D77: Friday | E77: 0.69791667 | F77: 358 | G77: 0.436 | H77: 0.15 | I77: 0.009 | J77: 0.03 | K77: =3/73 -> 0.04109589 | L77: 0.06 | M77: =342/358 -> 0.95530726 | N77: 0.95 | O77: =1/342 -> 0.0029239766 | P77: 0.0025 | Q77: Check this off your list before the Memorial Day Weekend
A78: Registration Email #19b | B78: 2026 Main Prospecting Registration Send List (excluding Drive-In) | C78: 46164 | D78: Friday | E78: 0.69791667 | F78: 16526 | G78: 0.41 | H78: 0.15 | I78: 0.018 | J78: 0.03 | K78: =285/3178 -> 0.089679043 | L78: 0.06 | M78: =15862/16526 -> 0.95982089 | N78: 0.95 | O78: =5/15862 -> 0.00031521876 | P78: 0.0025 | Q78: Book Your Flight Before Memorial Day Weekend
A79: Nurture Email #3 | B79: Nurture Emails: 2026 ATC Registrants | C79: 46168 | D79: Tuesday | E79: 0.73263889 | F79: 3347 | G79: 0.574 | H79: 0.15 | I79: 0.189 | J79: 0.03 | K79: =617/1314 -> 0.4695586 | L79: 0.06 | M79: =3272/3347 -> 0.97759187 | N79: 0.95 | O79: =1/3272 -> 0.00030562347 | P79: 0.0025 | Q79: Get More From Your ATC Experience
A80: Nurture Email #4 | B80: Nurture Emails: 2026 ATC Registrants | C80: 46170 | D80: Thursday | E80: 0.68541667 | F80: 3422 | G80: 0.646 | H80: 0.15 | I80: 0.15 | J80: 0.03 | K80: =465/1345 -> 0.34572491 | L80: 0.06 | M80: =3344/3422 -> 0.97720631 | N80: 0.95 | O80: 2.9904306e-06 | P80: 0.0025 | Q80: Live Event: Sneak Peek at ATC 2026
A81: Registration Email #20 | B81: 2026 Main Prospecting Registration Send List | C81: 46171 | D81: Friday | E81: 0.42708333 | F81: 16798 | G81: 0.4 | H81: 0.15 | I81: 0.088 | J81: 0.03 | K81: =1421/3238 -> 0.43885114 | L81: 0.06 | M81: =16121/16798 -> 0.95969758 | N81: 0.95 | O81: 0 | P81: 0.0025 | Q81: What Impact Could Robotics Have On Your Practice?
A82: Nurture Email #5 | B82: Nurture Emails: 2026 ATC Registrants | C82: 46176 | D82: Wednesday | E82: 0.54166667 | F82: 3504 | G82: 0.543 | H82: 0.15 | I82: 0.103 | J82: 0.03 | K82: =354/1304 -> 0.27147239 | L82: 0.06 | M82: =3427/3504 -> 0.97802511 | N82: 0.95 | O82: =1/3427 -> 0.00029180041 | P82: 0.0025 | Q82: Plan Your Breakfast and Lunch Symposia at ATC
A83: Registration Email #21a | B83: 2026 Boston Drive-In Audience | C83: 46175 | D83: Tuesday | E83: 0.45833333 | F83: 349 | G83: 0.47 | H83: 0.15 | I83: 0.033 | J83: 0.03 | K83: =11/83 -> 0.13253012 | L83: 0.06 | M83: =333/349 -> 0.95415473 | N83: 0.95 | O83: 0 | P83: 0.0025 | Q83: ATC Is This Month. See You Around the Corner.
A84: Registration Email #21b | B84: 2026 Main Prospecting Registration Send List (excluding Drive-In) | C84: 46175 | D84: Tuesday | E84: 0.45972222 | F84: 16432 | G84: 0.467 | H84: 0.15 | I84: 0.078 | J84: 0.03 | K84: =1220/3659 -> 0.33342443 | L84: 0.06 | M84: =15727/16432 -> 0.95709591 | N84: 0.95 | O84: =5/15727 -> 0.00031792459 | P84: 0.0025 | Q84: ATC Is This Month. Be Part Of What Comes Next.
A85: Registration Email #22 | B85: 2026 Main Prospecting Registration Send List | C85: 46183 | D85: Wednesday | E85: 0.51041667 | F85: 16681 | G85: 0.394 | H85: 0.15 | I85: 0.016 | J85: 0.03 | K85: =255/3101 -> 0.082231538 | L85: 0.06 | M85: =15952/16681 -> 0.95629758 | N85: 0.95 | O85: =7/15952 -> 0.00043881645 | P85: 0.0025 | Q85: Less Than 2 Weeks Until ATC. Don't Miss What's Next.
H86: 0.15 | J86: 0.03 | L86: 0.06 | N86: 0.95 | P86: 0.0025
H87: 0.15 | J87: 0.03 | L87: 0.06 | N87: 0.95 | P87: 0.0025

Sheet Emails (Sponsored)
A1: ATC
A2: Email Name | B2: Audience (List) | C2: Deployment Date | D2: Deployment Day of Week | E2: Deployment Time of Day | F2: Total Emails Sent | G2: Open Rate | H2: Open Rate (Benchmark) | I2: Click-Through Rate (clicks / devilieries) | J2: CTR (Benchmark) | K2: Click-To-Open Rate | L2: CTO (Benchmark) | M2: Delivery Rate | N2: Delivery Rate (Benchmark) | O2: Unsubscribe % | P2: Unsubscribe % (Benchmark) | Q2: Subject Line | R2: Notes | S2: Footer
A3: Eurofins Sponsored EBlast 6/9/26 | B3: ATC Registrations | C3: 46182 | D3: Tuesday | E3: 0.40625 | F3: 3700 | G3: 0.54 | H3: 0.15 | I3: 0.04 | J3: 0.03 | K3: =145/1366 -> 0.10614934 | L3: 0.06 | M3: =3613/3700 -> 0.97648649 | N3: 0.95 | O3: =1/3613 -> 0.0002767783 | P3: 0.0025 | Q3: ATC Attendees: Exclusive Invites + Meet the Scientists
A4: Apellis Sponsored Eblast | B4: 6.11.26 Apellis Sponsor Email List | C4: 46184 | D4: Thursday | E4: 0.48958333 | F4: 1288 | G4: 0.536 | H4: 0.15 | I4: 0.029 | J4: 0.03 | K4: =37/473 -> 0.078224101 | L4: 0.06 | M4: =1261/1288 -> 0.97903727 | N4: 0.95 | O4: 0 | P4: 0.0025 | Q4: Attending ATC? Discover an option for your patients
H5: 0.15 | J5: 0.03 | L5: 0.06 | N5: 0.95 | P5: 0.0025
H6: 0.15 | J6: 0.03 | L6: 0.06 | N6: 0.95 | P6: 0.0025
H7: 0.15 | J7: 0.03 | L7: 0.06 | N7: 0.95 | P7: 0.0025
H8: 0.15 | J8: 0.03 | L8: 0.06 | N8: 0.95 | P8: 0.0025
H9: 0.15 | J9: 0.03 | L9: 0.06 | N9: 0.95 | P9: 0.0025
H10: 0.15 | J10: 0.03 | L10: 0.06 | N10: 0.95 | P10: 0.0025
H11: 0.15 | J11: 0.03 | L11: 0.06 | N11: 0.95 | P11: 0.0025
H12: 0.15 | J12: 0.03 | L12: 0.06 | N12: 0.95 | P12: 0.0025
H13: 0.15 | J13: 0.03 | L13: 0.06 | N13: 0.95 | P13: 0.0025
H14: 0.15 | J14: 0.03 | L14: 0.06 | N14: 0.95 | P14: 0.0025
H15: 0.15 | J15: 0.03 | L15: 0.06 | N15: 0.95 | P15: 0.0025
H16: 0.15 | J16: 0.03 | L16: 0.06 | N16: 0.95 | P16: 0.0025
... H87: 0.15 | J87: 0.03 | L87: 0.06 | N87: 0.95 | P87: 0.0025

Sheet Emails (2)
A1: ATC
A2: Email Name | B2: Open Rate | C2: Open Rate (Benchmark) | D2: Click-Through Rate | E2: CTR (Benchmark) | F2: Click-To-Open Rate | G2: CTO (Benchmark)
A3: Call for Abstracts Email #10 | B3: 0.443 | C3: 0.15 | D3: =222/17937 -> 0.012376652 | E3: 0.03 | F3: =222/7940 -> 0.027959698 | G3: 0.06
A4: Call for Abstracts Email #10.5 | B4: 0.095 | C4: 0.15 | D4: =499/5227 -> 0.09546585 | E4: 0.03 | F4: =499/499 -> 1 | G4: 0.06
A5: Call for Abstracts Email #11a | B5: 0.433 | C5: 0.15 | D5: 0.005 | E5: 0.03 | F5: =48/3998 -> 0.012006003 | G5: 0.06
A6: Call For Abstracts Email #11b | B6: 0.44 | C6: 0.15 | D6: =73/9201 -> 0.0079339202 | E6: 0.03 | F6: =73/4046 -> 0.018042511 | G6: 0.06
A7: Call for Abstracts Email #12a | B7: 0.467 | C7: 0.15 | D7: 0.027 | E7: 0.03 | F7: =71/1241 -> 0.057211926 | G7: 0.06
A8: Call for Abstracts Email #12b | B8: 0.42 | C8: 0.15 | D8: 0.0009 | E8: 0.03 | F8: =146/6578 -> 0.022195196 | G8: 0.06
A9: Call for Abstracts Email #13 | B9: 0.43 | C9: 0.15 | D9: 0.091 | E9: 0.03 | F9: =1668/7843 -> 0.21267372 | G9: 0.06
A10: Call for Abstracts Email #14 | B10: 0.524 | C10: 0.15 | D10: =189/18217 -> 0.010374925 | E10: 0.03 | F10: =189/9452 -> 0.019995768 | G10: 0.06
A11: Call for Abstracts Email #15 | B11: 0.365 | C11: 0.15 | D11: =169/18393 -> 0.0091882781 | E11: 0.03 | F11: =169/6719 -> 0.025152552 | G11: 0.06
A12: Call for Abstracts Email #16 | B12: 0.458 | C12: 0.15 | D12: 0.013 | E12: 0.03 | F12: =244/8397 -> 0.029057997 | G12: 0.06
A13: Call for Abstracts Email #17 | B13: 0.036 | C13: 0.15 | D13: 0.014 | E13: 0.03 | F13: =261/663 -> 0.39366516 | G13: 0.06
A14: Call for Abstracts Email #18 | B14: 0.012 | C14: 0.15 | D14: 0.012 | E14: 0.03 | F14: 1 | G14: 0.06
A15: Call for Abstracts Email #19 (+ resend) | B15: 0.527 | C15: 0.15 | D15: 0.018 | E15: 0.03 | F15: =334/10042 -> 0.033260307 | G15: 0.06
A16: Call for Abstracts Email #19.5 | B16: 0.429 | C16: 0.15 | D16: =194/18156 -> 0.010685173 | E16: 0.03 | F16: =194/7784 -> 0.024922919 | G16: 0.06
A17: Call for Late-Breaking Abstracts Email #20 | B17: 0.396 | C17: 0.15 | D17: =565/18123 -> 0.031175854 | E17: 0.03 | F17: =568/7184 -> 0.079064588 | G17: 0.06
A18: Call for Late Breaking Abstracts Email #21a | B18: 0.384 | C18: 0.15 | D18: 0.021 | E18: 0.03 | F18: =48/873 -> 0.054982818 | G18: 0.06
A19: Call for Late Breaking Abstracts Email #21b | B19: 0.385 | C19: 0.15 | D19: 0.032 | E19: 0.03 | F19: =494/6004 -> 0.082278481 | G19: 0.06
A20: Call for Late Breaking Abstracts Email #22 | B20: 0.611 | C20: 0.15 | D20: =106/18069 -> 0.005866401 | E20: 0.03 | F20: =106/11049 -> 0.0095936284 | G20: 0.06 | J20: =1/18069 -> 5.5343406e-05 | K20: 0.0025 | L20: 72 Hours Left: Late-Breaking Abstracts Due Feb. 9
C21: 0.15 | E21: 0.03 | G21: 0.06
C22: 0.15 | E22: 0.03 | G22: 0.06
C23: 0.15 | E23: 0.03 | G23: 0.06
C24: 0.15 | E24: 0.03 | G24: 0.06
C25: 0.15 | E25: 0.03 | G25: 0.06
C26: 0.15 | E26: 0.03 | G26: 0.06
C27: 0.15 | E27: 0.03 | G27: 0.06
C28: 0.15 | E28: 0.03 | G28: 0.06
C29: 0.15 | E29: 0.03 | G29: 0.06
C30: 0.15 | E30: 0.03 | G30: 0.06
C31: 0.15 | E31: 0.03 | G31: 0.06
C32: 0.15 | E32: 0.03 | G32: 0.06
... C36: 0.15 | E36: 0.03 | G36: 0.06
A37: ATC
A38: Email Name | B38: Open Rate | C38: Open Rate (Benchmark) | D38: Click-Through Rate (clicks / devilieries) | E38: CTR (Benchmark) | F38: Click-To-Open Rate | G38: CTO (Benchmark)
A39: Save the Date Email #1 | B39: 0.016 | C39: 0.15 | D39: =95/5939 -> 0.015995959 | E39: 0.03 | F39: 1 | G39: 0.06
A40: Save the Date Email #2 | B40: 0.01 | C40: 0.15 | D40: 0.01 | E40: 0.03 | F40: 1 | G40: 0.06
A41: Save the Date Email #3 | B41: 0.455 | C41: 0.15 | D41: =2113/18248 -> 0.11579351 | E41: 0.03 | F41: =2113/8304 -> 0.25445568 | G41: 0.06
A107: Awareness Email #4 Save the Date | B107: 0.416 | C107: 0.15 | D107: 0.015 | E107: 0.03 | F107: =267/7595 -> 0.035154707 | G107: 0.06
A108: Awareness Email #5A Save the Date | B108: 0.376 | C108: 0.15 | D108: 0.02 | E108: 0.03 | F108: =308/5885 -> 0.052336449 | G108: 0.06
A109: Awareness Email #5B Save the Date | B109: 0.394 | C109: 0.15 | D109: 0.019 | E109: 0.03 | F109: =44/900 -> 0.048888889 | G109: 0.06
A134: Awareness Email #4 Save the Date | B134: =267/7595 -> 0.035154707 | C134: 0.06
A135: Awareness Email #5A Save the Date | B135: =308/5885 -> 0.052336449 | C135: 0.06
A136: Awareness Email #5B Save the Date | B136: =44/900 -> 0.048888889 | C136: 0.06
A162: Awareness Email #1 Save the Date | B162: 0.016 | C162: 0.15 | D162: =95/5939 -> 0.015995959 | E162: 0.03 | F162: 1 | G162: 0.06 | H162: =5939/6180 -> 0.96100324 | I162: 0.95 | J162: =15/5939 -> 0.0025256777 | K162: 0.0025
A163: Awareness Email #2 Save the Date | B163: 0.01 | C163: 0.15 | D163: 0.01 | E163: 0.03 | F163: 1 | G163: 0.06 | H163: =15099/16868 -> 0.89512687 | I163: 0.95 | J163: =5/15099 -> 0.00033114776 | K163: 0.0025
A164: Awareness Email #3 Save the Date | B164: 0.455 | C164: 0.15 | D164: =2113/18248 -> 0.11579351 | E164: 0.03 | F164: =2113/8304 -> 0.25445568 | G164: 0.06 | H164: =18248/18868 -> 0.96714013 | I164: 0.95 | J164: =3/18248 -> 0.00016440158 | K164: 0.0025
A165: Awareness Email #4 Save the Date | B165: 0.416 | C165: 0.15 | D165: 0.015 | E165: 0.03 | F165: =267/7595 -> 0.035154707 | G165: 0.06 | H165: =18244/18955 -> 0.96249011 | I165: 0.95 | J165: =11/18244 -> 0.00060293795 | K165: 0.0025
A166: Awareness Email #5A Save the Date | B166: 0.376 | C166: 0.15 | D166: 0.02 | E166: 0.03 | F166: =308/5885 -> 0.052336449 | G166: 0.06 | H166: =15642/16335 -> 0.95757576 | I166: 0.95 | J166: =7/15642 -> 0.00044751311 | K166: 0.0025
A167: Awareness Email #5B Save the Date | B167: 0.394 | C167: 0.15 | D167: 0.019 | E167: 0.03 | F167: =44/900 -> 0.048888889 | G167: 0.06 | H167: =2285/2367 -> 0.96535699 | I167: 0.95 | J167: =1/2285 -> 0.00043763676 | K167: 0.0025
A168: Awareness Email #6 Save the Date | B168: 0.417 | C168: 0.15 | D168: 0.019 | E168: 0.03 | F168: =340/7560 -> 0.044973545 | G168: 0.06
A200: ATC
A201: Email Name | B201: Open Rate | C201: Open Rate (Benchmark) | D201: Click-Through Rate | E201: CTR (Benchmark) | F201: Click-To-Open Rate | G201: CTO (Benchmark)
A202: Registration Email #1 | B202: 0.376 | C202: 0.15 | D202: 0.019 | E202: 0.03 | F202: =340/6879 -> 0.049425789 | G202: 0.06
A203: Registration Email #2 | B203: 0.414 | C203: 0.15 | D203: 0.013 | E203: 0.03 | F203: =234/7505 -> 0.031179214 | G203: 0.06
A204: Registration Email #2.5 | B204: 0.418 | C204: 0.15 | D204: 0.269 | E204: 0.03 | F204: =4912/7622 -> 0.64445028 | G204: 0.06
A205: Registration Email #3a | B205: 0.49 | C205: 0.15 | D205: 0.027 | E205: 0.03 | F205: =423/7657 -> 0.055243568 | G205: 0.06
A206: Registration Email #3b | B206: 0.442 | C206: 0.15 | D206: 0.025 | E206: 0.03 | F206: =57/994 -> 0.057344064 | G206: 0.06
A207: Registration Email #3c | B207: 0.555 | C207: 0.15 | D207: 0.028 | E207: 0.03 | F207: =12/239 -> 0.050209205 | G207: 0.06
A208: Registration Email #4a | B208: 0.492 | C208: 0.15 | D208: 0.029 | E208: 0.03 | F208: =113/1899 -> 0.059505003 | G208: 0.06
A209: Registration Email #4b | B209: 0.391 | C209: 0.15 | D209: 0.031 | E209: 0.03 | F209: =69/872 -> 0.07912844 | G209: 0.06
A210: Registration Email #4c | B210: 0.451 | C210: 0.15 | D210: 0.023 | E210: 0.03 | F210: =300/5974 -> 0.05021761 | G210: 0.06
A211: Registration Email #5 | B211: 0.415 | C211: 0.15 | D211: =1616/17326 -> 0.09327023 | E211: 0.03 | F211: =1616/7190 -> 0.22475661 | G211: 0.06
A212: Registration Email #6 | B212: 0.374 | C212: 0.15 | D212: 0.029 | E212: 0.03 | F212: =492/6329 -> 0.077737399 | G212: 0.06
A213: Registration Email #7a | B213: 0.39 | C213: 0.15 | D213: 0.027 | E213: 0.03 | F213: =417/6107 -> 0.068282299 | G213: 0.06
A214: Registration Email #7b | B214: 0.472 | C214: 0.15 | D214: 0.056 | E214: 0.03 | F214: =6/51 -> 0.11764706 | G214: 0.06
A215: Registration Email #7d | B215: 0.462 | C215: 0.15 | D215: 0.022 | E215: 0.03 | F215: =2/43 -> 0.046511628 | G215: 0.06
A216: Registration Email #7e | B216: 0.383 | C216: 0.15 | D216: 0.02 | E216: 0.03 | F216: =45/866 -> 0.051963048 | G216: 0.06
A217: Registration Email #8 | B217: 0.414 | C217: 0.15 | D217: 0.07 | E217: 0.03 | F217: =1169/6974 -> 0.1676226 | G217: 0.06
A218: Registration Email #9 | B218: 0.376 | C218: 0.15 | D218: 0.021 | E218: 0.03 | F218: =345/5934 -> 0.058139535 | G218: 0.06
A219: Registration Email #10a | B219: 0.411 | C219: 0.15 | D219: 0.043 | E219: 0.03 | F219: =620/3126 -> 0.19833653 | G219: 0.06
A220: Registration Email #10b | B220: 0.443 | C220: 0.15 | D220: 0.032 | E220: 0.03 | F220: =76/568 -> 0.13380282 | G220: 0.06
A221: Registration Email #11 | B221: 0.409 | C221: 0.15 | D221: 0.026 | E221: 0.03 | F221: =432/3549 -> 0.12172443 | G221: 0.06
A222: Registration Email #12a | B222: 0.529 | C222: 0.15 | D222: 0.033 | E222: 0.03 | F222: =157/1273 -> 0.12333071 | G222: 0.06
A223: Registration Email #12b | B223: 0.393 | C223: 0.15 | D223: 0.091 | E223: 0.03 | F223: =1091/2409 -> 0.45288501 | G223: 0.06
A224: Registration Email #13 | B224: 0.434 | C224: 0.15 | D224: 0.097 | E224: 0.03 | F224: =1611/3868 -> 0.41649431 | G224: 0.06
A225: Registration Email #14 | B225: 0.363 | C225: 0.15 | D225: 0.025 | E225: 0.03 | F225: =411/3159 -> 0.13010446 | G225: 0.06
A226: Registration Email #15a | B226: 0.43 | C226: 0.15 | D226: 0.038 | E226: 0.03 | F226: =109/695 -> 0.15683453 | G226: 0.06
A227: Registration Email #15b | B227: 0.373 | C227: 0.15 | D227: 0.022 | E227: 0.03 | F227: =304/2315 -> 0.13131749 | G227: 0.06
A228: Registration Email #16a | B228: 0.408 | C228: 0.15 | D228: 0.027 | E228: 0.03 | F228: =4/25 -> 0.16 | G228: 0.06
A229: Registration Email #16b | B229: 0.478 | C229: 0.15 | D229: 0.04 | E229: 0.03 | F229: =17/102 -> 0.16666667 | G229: 0.06
A230: Registration Email #16c | B230: 0.43 | C230: 0.15 | D230: 0.019 | E230: 0.03 | F230: =26/305 -> 0.085245902 | G230: 0.06
A231: Registration Email #16d | B231: 0.387 | C231: 0.15 | D231: 0.035 | E231: 0.03 | F231: =516/2552 -> 0.20219436 | G231: 0.06
A232: Registration Email #17 | B232: 0.471 | C232: 0.15 | D232: 0.021 | E232: 0.03 | F232: =311/2955 -> 0.10524535 | G232: 0.06
A233: Registration Email #18a | B233: 0.414 | C233: 0.15 | D233: 0.029 | E233: 0.03 | F233: =77/604 -> 0.12748344 | G233: 0.06
A234: Registration Email #18b | B234: 0.394 | C234: 0.15 | D234: 0.019 | E234: 0.03 | F234: =290/2872 -> 0.10097493 | G234: 0.06
A235: Registration Email #19a | B235: 0.436 | C235: 0.15 | D235: 0.009 | E235: 0.03 | F235: =3/73 -> 0.04109589 | G235: 0.06
A236: Registration Email #19b | B236: 0.41 | C236: 0.15 | D236: 0.018 | E236: 0.03 | F236: =285/3178 -> 0.089679043 | G236: 0.06
A237: Registration Email #20 | B237: 0.4 | C237: 0.15 | D237: 0.088 | E237: 0.03 | F237: 0.4416 | G237: 0.06
A246: ATC
A247: Email Name | B247: Open Rate | C247: Open Rate (Benchmark) | D247: Click-Through Rate | E247: CTR (Benchmark) | F247: Click-To-Open Rate | G247: CTO (Benchmark)
A248: Call for Abstracts Email #19.5 | B248: 0.429 | C248: 0.15 | D248: =194/18156 -> 0.010685173 | E248: 0.03 | F248: =194/7784 -> 0.024922919 | G248: 0.06
A249: Call for Late-Breaking Abstracts Email #20 | B249: 0.396 | C249: 0.15 | D249: =565/18123 -> 0.031175854 | E249: 0.03 | F249: =568/7184 -> 0.079064588 | G249: 0.06
A250: Call for Late Breaking Abstracts Email #21a | B250: 0.384 | C250: 0.15 | D250: 0.021 | E250: 0.03 | F250: =48/873 -> 0.054982818 | G250: 0.06
A251: Call for Late Breaking Abstracts Email #21b | B251: 0.385 | C251: 0.15 | D251: 0.032 | E251: 0.03 | F251: =494/6004 -> 0.082278481 | G251: 0.06
A252: Call for Late Breaking Abstracts Email #22 | B252: 0.611 | C252: 0.15 | D252: 0.0059 | E252: 0.03 | F252: 0.0096 | G252: 0.06
A256: Email Name | B256: Open Rate | C256: Open Rate (Benchmark) | D256: Click-Through Rate | E256: CTR (Benchmark) | F256: Click-To-Open Rate | G256: CTO (Benchmark)
A257: Nurture Email #1 | B257: 0.509 | C257: 0.15 | D257: 0.053 | E257: 0.03 | F257: =98/942 -> 0.10403397 | G257: 0.06
A258: Nurture Email #2 | B258: 0.561 | C258: 0.15 | D258: 0.059 | E258: 0.03 | F258: =128/796 -> 0.16080402 | G258: 0.06
A259: Nurture Email #3 | B259: 0.574 | C259: 0.15 | D259: 0.189 | E259: 0.03 | F259: =617/1314 -> 0.4695586 | G259: 0.06
...

Sheet Heatmap
A1: ATC
A2: Email Name | B2: Audience (List) | C2: Total Clicks | D2: Top Button Clicks | E2: % Total Clicked Top Button | F2: Top Logo Clicks | G2: % Total Clicked Top Logo | H2: Header Image Clicks | I2: % Total Clicked Header Image | J2: First Button Clicks | K2: % Total Clicked First Button
A3: Call for Proposals Email #1 (All Prospects) | C3: 1432 | D3: 358 | E3: =(D3/C3) -> 0.25 | F3: 347 | G3: =(F3/C3) -> 0.24231844 | H3: 346 | I3: =(H3/C3) -> 0.24162011 | J3: 381 | K3: =(J3/C3) -> 0.26606145
A4: Call for Proposals Email #2 (All Prospects) | C4: 10843 | D4: 3611 | E4: =(D4/C4) -> 0.33302592 | F4: 0 | G4: =(F4/C4) -> 0 | H4: 3613 | I4: =(H4/C4) -> 0.33321037 | J4: 3619 | K4: =(J4/C4) -> 0.33376372
A5: Call for Proposals Email #3 (All Prospects) | C5: 9810 | D5: =2433+8 -> 2441 | E5: =(D5/C5) -> 0.24882773 | F5: =1+2431 -> 2432 | G5: =(F5/C5) -> 0.2479103 | H5: =2428+3 -> 2431 | I5: =(H5/C5) -> 0.24780836 | J5: =21+2485 -> 2506 | K5: =(J5/C5) -> 0.25545362
A6: Call for Proposals Email #4a (Past Submitters) | C6: 109 | D6: 27 | E6: =(D6/C6) -> 0.24770642 | F6: 26 | G6: =(F6/C6) -> 0.23853211 | H6: 26 | I6: =(H6/C6) -> 0.23853211 | J6: 30 | K6: =(J6/C6) -> 0.27522936
A7: Call for Proposals Email #4b (All Prospects) | C7: 5882 | D7: 1466 | E7: =(D7/C7) -> 0.24923495 | F7: 1461 | G7: =(F7/C7) -> 0.2483849 | H7: 1462 | I7: =(H7/C7) -> 0.24855491 | J7: 1493 | K7: =(J7/C7) -> 0.25382523
A8: Call for Proposals Email #5 (All Prospects) | C8: 4142 | D8: 1051 | E8: =(D8/C8) -> 0.25374215 | F8: 1046 | G8: =(F8/C8) -> 0.25253501 | H8: 1017 | I8: =(H8/C8) -> 0.24553356 | J8: 1028 | K8: =(J8/C8) -> 0.24818928
A9: INTL Email #1 - Survey (International Attendees) | C9: 224 | D9: =54+3 -> 57 | E9: =(D9/C9) -> 0.25446429 | F9: =54+3 -> 57 | G9: =(F9/C9) -> 0.25446429 | H9: =4+55 -> 59 | I9: =(H9/C9) -> 0.26339286 | J9: =48+3 -> 51 | K9: =(J9/C9) -> 0.22767857
A10: Call for Proposals Email #6 (All Prospects) | C10: 937 | D10: =222+13 -> 235 | E10: =(D10/C10) -> 0.25080043 | F10: =8+217 -> 225 | G10: =(F10/C10) -> 0.24012807 | H10: =213+11 -> 224 | I10: =(H10/C10) -> 0.23906083 | J10: =10+243 -> 253 | K10: =(J10/C10) -> 0.27001067
A11: Call for Proposals Email #7 (All Prospects) | C11: 1043 | D11: 256 | E11: =(D11/C11) -> 0.24544583 | F11: 235 | G11: =(F11/C11) -> 0.2253116 | H11: 248 | I11: =(H11/C11) -> 0.23777565 | J11: 304 | K11: =(J11/C11) -> 0.29146692
A12: Call for Proposals Email #8 (All Prospects) | C12: 136 | D12: 23 | E12: =(D12/C12) -> 0.16911765 | F12: 14 | G12: =(F12/C12) -> 0.10294118 | H12: 22 | I12: =(H12/C12) -> 0.16176471 | J12: 77 | K12: =(J12/C12) -> 0.56617647
A13: Call for Proposals & State-of-the-Art Speakers Email #9.5 Deadline Extended (All Prospects) | C13: 684 | D13: 185 | E13: =(D13/C13) -> 0.27046784 | F13: 170 | G13: =(F13/C13) -> 0.24853801 | H13: 150 | I13: =(H13/C13) -> 0.21929825 | J13: 179 | K13: =(J13/C13) -> 0.26169591
A14: Call for Abstracts - Email #10 (All Prospects) | C14: 261 | D14: 58 | E14: =(D14/C14) -> 0.22222222 | F14: 69 | G14: =(F14/C14) -> 0.26436782 | H14: 57 | I14: =(H14/C14) -> 0.2183908 | J14: 77 | K14: =(J14/C14) -> 0.29501916
A15: Email #9 - Call for Proposals - 24 Hours Left 8/21 (All Prospects) | C15: 1092 | D15: 25 | E15: =(D15/C15) -> 0.022893773 | F15: 25 | G15: =(F15/C15) -> 0.022893773 | H15: 31 | I15: =(H15/C15) -> 0.028388278 | J15: 1011 | K15: =(J15/C15) -> 0.92582418
A16: Email #10.5 - Call for Abstracts - Past Attendees & Past Abstract Submitters (Past Abstract Submitters & Attendees) | C16: 887 | D16: 213 | E16: =(D16/C16) -> 0.24013529 | F16: 305 | G16: =(F16/C16) -> 0.34385569 | H16: 194 | I16: =(H16/C16) -> 0.21871477 | J16: 175 | K16: =(J16/C16) -> 0.19729425
A17: Save the Date Email #1 | C17: 80 | D17: 17 | E17: =(D17/C17) -> 0.2125 | F17: 18 | G17: =(F17/C17) -> 0.225 | H17: 38 | I17: =(H17/C17) -> 0.475 | J17: 7 | K17: =(J17/C17) -> 0.0875
A18: Save the Date Email #2 | C18: 151 | D18: 26 | E18: =(D18/C18) -> 0.17218543 | F18: 32 | G18: =(F18/C18) -> 0.21192053 | H18: 46 | I18: =(H18/C18) -> 0.30463576 | J18: 47 | K18: =(J18/C18) -> 0.31125828
A19: Email #11a Call for Abstracts Button Test | C19: 43 | D19: 0 | E19: =(D19/C19) -> 0 | F19: 43 | G19: =(F19/C19) -> 1 | H19: 0 | I19: =(H19/C19) -> 0 | J19: 0 | K19: =(J19/C19) -> 0
A20: Email #11b Call For Abstracts Button Test | C20: 57 | D20: 16 | E20: =(D20/C20) -> 0.28070175 | F20: 12 | G20: =(F20/C20) -> 0.21052632 | H20: 11 | I20: =(H20/C20) -> 0.19298246 | J20: 18 | K20: =(J20/C20) -> 0.31578947
A21: Email #12a Visa Focus | C21: 63 | D21: 16 | E21: =(D21/C21) -> 0.25396825 | F21: 14 | G21: =(F21/C21) -> 0.22222222 | H21: 15 | I21: =(H21/C21) -> 0.23809524 | J21: 18 | K21: =(J21/C21) -> 0.28571429
A22: Email #12b | C22: =55+50+37+53 -> 195 | D22: 55 | E22: =(D22/C22) -> 0.28205128 | F22: 50 | G22: =(F22/C22) -> 0.25641026 | H22: 37 | I22: =(H22/C22) -> 0.18974359 | J22: 53 | K22: =(J22/C22) -> 0.27179487
E23: =(D23/C23) -> #DIV/0! | G23: =(F23/C23) -> #DIV/0! | I23: =(H23/C23) -> #DIV/0! | K23: =(J23/C23) -> #DIV/0!
E24: =(D24/C24) -> #DIV/0!
A27: Average: | C27: =AVERAGE(C3:C20) -> 2100.7222 | D27: =AVERAGE(D3:D20) -> 559.16667 | E27: =AVERAGE(E3:E20) -> 0.21797065 | F27: =AVERAGE(F3:F20) -> 362.05556 | G27: =AVERAGE(G3:G20) -> 0.25442378 | H27: =AVERAGE(H3:H20) -> 554.16667 | I27: =AVERAGE(I3:I20) -> 0.22859243 | J27: =AVERAGE(J3:J20) -> 625.33333 | K27: =AVERAGE(K3:K20) -> 0.29901314

Sheet Organic Social Media (Weekly)
A1: Social Media
B2: LinkedIn (LI) | G2: Facebook (FB) | L2: Instagram (IG) | Q2: Twitter (X) | V2: Totals
A3: Notes > | B3: Total followers to start the week. | C3: Percentage change in followers over time. | D3: Every time someone sees our post, even if they just scroll past | E3: When someone actually interacts with our post, like commenting, liking, or sharing, that's an engagement. | F3: How many times we posted this week about the event | G3: Total followers to start the week. | H3: Percentage change in followers over time. | I3: Every time someone sees our post, even if they just scroll past | J3: When someone actually interacts with our post, like commenting, liking, or sharing, that's an engagement. | K3: How many times we posted this week about the event | L3: Total followers to start the week. | M3: Percentage change in followers over time. | N3: Every time someone sees our post, even if they just scroll past (view) | O3: When someone actually interacts with our post, like commenting, liking, or sharing, that's an engagement. | P3: How many times we posted this week about the event | Q3: Total followers to start the week. | R3: Percentage change in followers over time. | S3: Every time someone sees our post, even if they just scroll past | T3: When someone actually interacts with our post, like commenting, liking, or sharing, that's an engagement. | U3: How many times we posted this week about the event | V3: Followers | AB3: Follower Growth Rate | AF3: Impressions | AJ3: Engagements | AO3: Posts Per Week
A4: Week Starting | B4: LI Followers | C4: LI Follower Growth Rate | D4: LI Impressions | E4: LI Engagements | F4: LI Posts Per Week | G4: FB Followers | H4: FB Follower Growth Rate | I4: FB Impressions | J4: FB Engagements | K4: FB Posts Per Week | L4: IG Followers | M4: IG Follower Growth Rate | N4: IG Impressions | O4: IG Engagements | P4: IG Posts Per Week | Q4: X Followers | R4: X Follower Growth Rate | S4: X Impressions | T4: X Engagements | U4: X Posts Per Week | V4: LI Followers | W4: FB Followers | X4: IG Followers | Y4: X Followers | Z4: Total Followers | AB4: LI Growth Rate | AC4: FB Growth Rate | AD4: IG Growth Rate | AE4: X Growth Rate | AF4: LI Impressions | AG4: FB Impressions | AH4: IG Impressions | AI4: X Impressions | AJ4: LI Engagements | AK4: FB Engagements | AL4: IG Engagements | AM4: X Engagements | AN4: Total Engagements | AO4: LI Posts Per Week | AP4: FB Posts Per Week | AQ4: IG Posts Per Week | AR4: X Posts Per Week | AS4: Total posts per week
A5: 45831 | B5: 1490 | C5: =(B6/B5)-1 -> -0.00067114094 | D5: 807 | E5: 26 | F5: 2 | G5: 2311 | H5: =(G6/G5)-1 -> -0.00086542622 | I5: 329 | J5: 10 | K5: 2 | L5: 921 | M5: =(L6/L5)-1 -> 0.0021715527 | N5: 384 | O5: 15 | P5: 2 | Q5: 5627 | R5: =(Q6/Q5)-1 -> 0 | S5: 1141 | T5: 24 | U5: 3 | V5: =B5 -> 1490 | W5: =G5 -> 2311 | X5: =L5 -> 921 | Y5: =Q5 -> 5627 | AA5: =(Z5-Z4)/Z4 -> #VALUE! | AB5: =C5 -> -0.00067114094 | AC5: =H5 -> -0.00086542622 | AD5: =M5 -> 0.0021715527 | AE5: =R5 -> 0 | AF5: =D5 -> 807 | AG5: =I5 -> 329 | AH5: =N5 -> 384 | AI5: =S5 -> 1141 | AJ5: =E5 -> 26 | AK5: =J5 -> 10 | AL5: =O5 -> 15 | AM5: =T5 -> 24 | AN5: =SUM(AJ5:AM5) -> 75 | AO5: =F5 -> 2 | AP5: =K5 -> 2 | AQ5: =P5 -> 2 | AR5: =U5 -> 3 | AS5: =SUM(AO5:AR5) -> 9
A6: 45838 | B6: 1489 | C6: =(B6-B5)/B5 -> -0.00067114094 | D6: 179 | E6: 3 | F6: 0 | G6: 2309 | H6: =(G7/G6)-1 -> 0 | I6: 18 | J6: 0 | K6: 0 | L6: 923 | M6: =(L7/L6)-1 -> 0.0054171181 | N6: 87 | O6: 2 | P6: 0 | Q6: 5627 | R6: =(Q7/Q6)-1 -> -0.00035542918 | S6: 107 | T6: 8 | U6: 0 | V6: =B6 -> 1489 | W6: =G6 -> 2309 | X6: =L6 -> 923 | Y6: =Q6 -> 5627 | AB6: =C6 -> -0.00067114094 | AC6: =H6 -> 0 | AD6: =M6 -> 0.0054171181 | AE6: =R6 -> -0.00035542918 | AF6: =D6 -> 179 | AG6: =I6 -> 18 | AH6: =N6 -> 87 | AI6: =S6 -> 107 | AJ6: =E6 -> 3 | AK6: =J6 -> 0 | AL6: =O6 -> 2 | AM6: =T6 -> 8 | AN6: =SUM(AJ6:AM6) -> 13 | AO6: =F6 -> 0 | AP6: =K6 -> 0 | AQ6: =P6 -> 0 | AR6: =U6 -> 0 | AS6: =SUM(AO6:AR6) -> 0
A7: 45845 | B7: 1488 | C7: =(B7-B6)/B6 -> -0.00067159167 | D7: 293 | E7: 4 | F7: 1 | G7: 2309 | H7: =(G8/G7)-1 -> -0.00043308792 | I7: 94 | J7: 0 | K7: 1 | L7: 928 | M7: =(L8/L7)-1 -> -0.0021551724 | N7: 174 | O7: 7 | P7: 1 | Q7: 5625 | R7: =(Q8/Q7)-1 -> 0.0012444444 | S7: 644 | T7: 17 | U7: 1 | V7: =B7 -> 1488 | W7: =G7 -> 2309 | X7: =L7 -> 928 | Y7: =Q7 -> 5625 | AB7: =C7 -> -0.00067159167 | AC7: =H7 -> -0.00043308792 | AD7: =M7 -> -0.0021551724 | AE7: =R7 -> 0.0012444444 | AF7: =D7 -> 293 | AG7: =I7 -> 94 | AH7: =N7 -> 174 | AI7: =S7 -> 644 | AJ7: =E7 -> 4 | AK7: =J7 -> 0 | AL7: =O7 -> 7 | AM7: =T7 -> 17 | AN7: =SUM(AJ7:AM7) -> 28 | AO7: =F7 -> 1 | AP7: =K7 -> 1 | AQ7: =P7 -> 1 | AR7: =U7 -> 1 | AS7: =SUM(AO7:AR7) -> 4
A8: 45852 | B8: 1490 | C8: =(B8-B7)/B7 -> 0.001344086 | D8: 715 | E8: 12 | F8: 1 | G8: 2308 | H8: =(G9/G8)-1 -> 0 | I8: 87 | J8: 2 | K8: 1 | L8: 926 | M8: =(L9/L8)-1 -> -0.0010799136 | N8: 330 | O8: 6 | P8: 1 | Q8: 5632 | R8: =(Q9/Q8)-1 -> 0.0010653409 | S8: 440 | T8: 7 | U8: 1 | V8: =B8 -> 1490 | W8: =G8 -> 2308 | X8: =L8 -> 926 | Y8: =Q8 -> 5632 | AB8: =C8 -> 0.001344086 | AC8: =H8 -> 0 | AD8: =M8 -> -0.0010799136 | AE8: =R8 -> 0.0010653409 | AF8: =D8 -> 715 | AG8: =I8 -> 87 | AH8: =N8 -> 330 | AI8: =S8 -> 440 | AJ8: =E8 -> 12 | AK8: =J8 -> 2 | AL8: =O8 -> 6 | AM8: =T8 -> 7 | AN8: =SUM(AJ8:AM8) -> 27 | AO8: =F8 -> 1 | AP8: =K8 -> 1 | AQ8: =P8 -> 1 | AR8: =U8 -> 1 | AS8: =SUM(AO8:AR8) -> 4
A9: 45859 | B9: 1491 | C9: =(B9-B8)/B8 -> 0.00067114094 | D9: 526 | E9: 9 | F9: 2 | G9: 2308 | H9: =(G10/G9)-1 -> 0 | I9: 92 | J9: 1 | K9: 2 | L9: 925 | M9: =(L10/L9)-1 -> 0 | N9: 215 | O9: 6 | P9: 2 | Q9: 5638 | R9: =(Q10/Q9)-1 -> 0.00035473572 | S9: 428 | T9: 13 | U9: 2 | V9: =B9 -> 1491 | W9: =G9 -> 2308 | X9: =L9 -> 925 | Y9: =Q9 -> 5638 | AB9: =C9 -> 0.00067114094 | AC9: =H9 -> 0 | AD9: =M9 -> 0 | AE9: =R9 -> 0.00035473572 | AF9: =D9 -> 526 | AG9: =I9 -> 92 | AH9: =N9 -> 215 | AI9: =S9 -> 428 | AJ9: =E9 -> 9 | AK9: =J9 -> 1 | AL9: =O9 -> 6 | AM9: =T9 -> 13 | AN9: =SUM(AJ9:AM9) -> 29 | AO9: =F9 -> 2 | AP9: =K9 -> 2 | AQ9: =P9 -> 2 | AR9: =U9 -> 2 | AS9: =SUM(AO9:AR9) -> 8
A10: 45866 | B10: 1492 | C10: =(B10-B9)/B9 -> 0.00067069081 | D10: 519 | E10: 12 | F10: 1 | G10: 2308 | H10: =(G10-G9)/G9 -> 0 | I10: 81 | J10: 2 | K10: 1 | L10: 925 | M10: =(L10-L9)/L9 -> 0 | N10: 730 | O10: 14 | P10: 2 | Q10: 5640 | R10: =(Q11/Q10)-1 -> 0.00070921986 | S10: 435 | T10: 15 | U10: 1 | V10: =B10 -> 1492 | W10: =G10 -> 2308 | X10: =L10 -> 925 | Y10: =Q10 -> 5640 | AB10: =C10 -> 0.00067069081 | AC10: =H10 -> 0 | AD10: =M10 -> 0 | AE10: =R10 -> 0.00070921986 | AF10: =D10 -> 519 | AG10: =I10 -> 81 | AH10: =N10 -> 730 | AI10: =S10 -> 435 | AJ10: =E10 -> 12 | AK10: =J10 -> 2 | AL10: =O10 -> 14 | AM10: =T10 -> 15 | AN10: =SUM(AJ10:AM10) -> 43 | AO10: =F10 -> 1 | AP10: =K10 -> 1 | AQ10: =P10 -> 2 | AR10: =U10 -> 1 | AS10: =SUM(AO10:AR10) -> 5
A11: 45873 | B11: 1498 | C11: =(B11-B10)/B10 -> 0.0040214477 | D11: 812 | E11: 71 | F11: 3 | G11: 2307 | H11: =(G11-G10)/G10 -> -0.00043327556 | I11: 277 | J11: 2 | K11: 3 | L11: 935 | M11: =(L11-L10)/L10 -> 0.010810811 | N11: 1405 | O11: 10 | P11: 1 | Q11: 5644 | R11: =(Q11-Q10)/Q10 -> 0.00070921986 | S11: 1058 | T11: 109 | U11: 2 | V11: =B11 -> 1498 | W11: =G11 -> 2307 | X11: =L11 -> 935 | Y11: =Q11 -> 5644 | AB11: =C11 -> 0.0040214477 | AC11: =H11 -> -0.00043327556 | AD11: =M11 -> 0.010810811 | AE11: =R11 -> 0.00070921986 | AF11: =D11 -> 812 | AG11: =I11 -> 277 | AH11: =N11 -> 1405 | AI11: =S11 -> 1058 | AJ11: =E11 -> 71 | AK11: =J11 -> 2 | AL11: =O11 -> 10 | AM11: =T11 -> 109 | AN11: =SUM(AJ11:AM11) -> 192 | AO11: =F11 -> 3 | AP11: =K11 -> 3 | AQ11: =P11 -> 1 | AR11: =U11 -> 2 | AS11: =SUM(AO11:AR11) -> 9
A12: 45880 | B12: 1502 | C12: =(B12-B11)/B11 -> 0.002670227 | D12: 347 | E12: 12 | F12: 1 | G12: 2309 | H12: =(G12-G11)/G11 -> 0.00086692674 | I12: 178 | J12: 8 | K12: 1 | L12: 943 | M12: =(L12-L11)/L11 -> 0.0085561497 | N12: 987 | O12: 23 | P12: 4 | Q12: 5647 | R12: =(Q12-Q11)/Q11 -> 0.00053153792 | S12: 820 | T12: 18 | U12: 1 | V12: =B12 -> 1502 | W12: =G12 -> 2309 | X12: =L12 -> 943 | Y12: =Q12 -> 5647 | AB12: =C12 -> 0.002670227 | AC12: =H12 -> 0.00086692674 | AD12: =M12 -> 0.0085561497 | AE12: =R12 -> 0.00053153792 | AF12: =D12 -> 347 | AG12: =I12 -> 178 | AH12: =N12 -> 987 | AI12: =S12 -> 820 | AJ12: =E12 -> 12 | AK12: =J12 -> 8 | AL12: =O12 -> 23 | AM12: =T12 -> 18 | AN12: =SUM(AJ12:AM12) -> 61 | AO12: =F12 -> 1 | AP12: =K12 -> 1 | AQ12: =P12 -> 4 | AR12: =U12 -> 1 | AS12: =SUM(AO12:AR12) -> 7
A13: 45887 | B13: 1501 | C13: =(B13-B12)/B12 -> -0.00066577896 | D13: 368 | E13: 22 | F13: 2 | G13: 2309 | H13: =(G13-G12)/G12 -> 0 | I13: 201 | J13: 3 | K13: 2 | L13: 941 | M13: =(L13-L12)/L12 -> -0.0021208908 | N13: 576 | O13: 7 | P13: 2 | Q13: 5655 | R13: =(Q13-Q12)/Q12 -> 0.0014166814 | S13: 806 | T13: 37 | U13: 2 | V13: =B13 -> 1501 | W13: =G13 -> 2309 | X13: =L13 -> 941 | Y13: =Q13 -> 5655 | AB13: =C13 -> -0.00066577896 | AC13: =H13 -> 0 | AD13: =M13 -> -0.0021208908 | AE13: =R13 -> 0.0014166814 | AF13: =D13 -> 368 | AG13: =I13 -> 201 | AH13: =N13 -> 576 | AI13: =S13 -> 806 | AJ13: =E13 -> 22 | AK13: =J13 -> 3 | AL13: =O13 -> 7 | AM13: =T13 -> 37 | AN13: =SUM(AJ13:AM13) -> 69 | AO13: =F13 -> 2 | AP13: =K13 -> 2 | AQ13: =P13 -> 2 | AR13: =U13 -> 2 | AS13: =SUM(AO13:AR13) -> 8
A14: 45894 | B14: 1506 | C14: =(B14-B13)/B13 -> 0.0033311126 | D14: 209 | E14: 7 | F14: 1 | G14: 2307 | H14: =(G14-G13)/G13 -> -0.00086617583 | I14: 79 | J14: 4 | K14: 1 | L14: 941 | M14: =(L14-L13)/L13 -> 0 | N14: 170 | O14: 2 | P14: 1 | Q14: 5665 | R14: =(Q14-Q13)/Q13 -> 0.0017683466 | S14: 261 | T14: 2 | U14: 1 | V14: =B14 -> 1506 | W14: =G14 -> 2307 | X14: =L14 -> 941 | Y14: =Q14 -> 5665 | AB14: =C14 -> 0.0033311126 | AC14: =H14 -> -0.00086617583 | AD14: =M14 -> 0 | AE14: =R14 -> 0.0017683466 | AF14: =D14 -> 209 | AG14: =I14 -> 79 | AH14: =N14 -> 170 | AI14: =S14 -> 261 | AJ14: =E14 -> 7 | AK14: =J14 -> 4 | AL14: =O14 -> 2 | AM14: =T14 -> 2 | AN14: =SUM(AJ14:AM14) -> 15 | AO14: =F14 -> 1 | AP14: =K14 -> 1 | AQ14: =P14 -> 1 | AR14: =U14 -> 1 | AS14: =SUM(AO14:AR14) -> 4
A15: 45901 | B15: 1508 | C15: =(B15-B14)/B14 -> 0.0013280212 | D15: 134 | E15: 3 | F15: 0 | G15: 2309 | H15: =(G15-G14)/G14 -> 0.00086692674 | I15: 31 | J15: 0 | K15: 0 | L15: 940 | M15: =(L15-L14)/L14 -> -0.0010626993 | N15: 142 | O15: 0 | P15: 0 | Q15: 5666 | R15: =(Q15-Q14)/Q14 -> 0.00017652251 | S15: 297 | T15: 7 | U15: 0 | V15: =B15 -> 1508 | W15: =G15 -> 2309 | X15: =L15 -> 940 | Y15: =Q15 -> 5666 | AB15: =C15 -> 0.0013280212 | AC15: =H15 -> 0.00086692674 | AD15: =M15 -> -0.0010626993 | AE15: =R15 -> 0.00017652251 | AF15: =D15 -> 134 | AG15: =I15 -> 31 | AH15: =N15 -> 142 | AI15: =S15 -> 297 | AJ15: =E15 -> 3 | AK15: =J15 -> 0 | AL15: =O15 -> 0 | AM15: =T15 -> 7 | AN15: =SUM(AJ15:AM15) -> 10 | AO15: =F15 -> 0 | AP15: =K15 -> 0 | AQ15: =P15 -> 0 | AR15: =U15 -> 0 | AS15: =SUM(AO15:AR15) -> 0
A16: 45908 | B16: 1509 | C16: =(B16-B15)/B15 -> 0.00066312997 | D16: 129 | E16: 3 | F16: 1 | G16: 2311 | H16: =(G16-G15)/G15 -> 0.00086617583 | I16: 92 | J16: 3 | K16: 1 | L16: 940 | M16: =(L16-L15)/L15 -> 0 | N16: 411 | O16: 2 | P16: 1 | Q16: 5674 | R16: =(Q16-Q15)/Q15 -> 0.0014119308 | S16: 1271 | T16: 28 | U16: 1 | V16: =B16 -> 1509 | W16: =G16 -> 2311 | X16: =L16 -> 940 | Y16: =Q16 -> 5674 | Z16: =SUM(V16:Y16) -> 10434 | AA16: =(Z16-Z15)/Z15 -> #DIV/0! | AB16: =C16 -> 0.00066312997 | AC16: =H16 -> 0.00086617583 | AD16: =M16 -> 0 | AE16: =R16 -> 0.0014119308 | AF16: =D16 -> 129 | AG16: =I16 -> 92 | AH16: =N16 -> 411 | AI16: =S16 -> 1271 | AJ16: =E16 -> 3 | AK16: =J16 -> 3 | AL16: =O16 -> 2 | AM16: =T16 -> 28 | AN16: =SUM(AJ16:AM16) -> 36 | AO16: =F16 -> 1 | AP16: =K16 -> 1 | AQ16: =P16 -> 1 | AR16: =U16 -> 1 | AS16: =SUM(AO16:AR16) -> 4
A17: 45915 | B17: 1510 | C17: =(B17-B16)/B16 -> 0.00066269052 | D17: 277 | E17: 8 | F17: 1 | G17: 2310 | H17: =(G17-G16)/G16 -> -0.00043271311 | I17: 65 | J17: 2 | K17: 1 | L17: 940 | M17: =(L17-L16)/L16 -> 0 | N17: 513 | O17: 5 | P17: 1 | Q17: 5677 | R17: =(Q17-Q16)/Q16 -> 0.00052872753 | S17: 326 | T17: 6 | U17: 1 | V17: =B17 -> 1510 | W17: =G17 -> 2310 | X17: =L17 -> 940 | Y17: =Q17 -> 5677 | Z17: =SUM(V17:Y17) -> 10437 | AA17: =(Z17-Z16)/Z16 -> 0.00028752156 | AB17: =C17 -> 0.00066269052 | AC17: =H17 -> -0.00043271311 | AD17: =M17 -> 0 | AE17: =R17 -> 0.00052872753 | AF17: =D17 -> 277 | AG17: =I17 -> 65 | AH17: =N17 -> 513 | AI17: =S17 -> 326 | AJ17: =E17 -> 8 | AK17: =J17 -> 2 | AL17: =O17 -> 5 | AM17: =T17 -> 6 | AN17: =SUM(AJ17:AM17) -> 21 | AO17: =F17 -> 1 | AP17: =K17 -> 1 | AQ17: =P17 -> 1 | AR17: =U17 -> 1 | AS17: =SUM(AO17:AR17) -> 4
A18: 45922 | B18: 1512 | C18: =(B18-B17)/B17 -> 0.0013245033 | D18: 228 | E18: 5 | F18: 1 | G18: 2313 | H18: =(G18-G17)/G17 -> 0.0012987013 | I18: 44 | J18: 2 | K18: 1 | L18: 941 | M18: =(L18-L17)/L17 -> 0.0010638298 | N18: 242 | O18: 4 | P18: 1 | Q18: 5672 | R18: =(Q18-Q17)/Q17 -> -0.00088074687 | S18: 563 | T18: 17 | U18: 1 | V18: =B18 -> 1512 | W18: =G18 -> 2313 | X18: =L18 -> 941 | Y18: =Q18 -> 5672 | Z18: e | AA18: =(Z18-Z17)/Z17 -> #VALUE! | AB18: =C18 -> 0.0013245033 | AC18: =H18 -> 0.0012987013 | AD18: =M18 -> 0.0010638298 | AE18: =R18 -> -0.00088074687 | AF18: =D18 -> 228 | AG18: =I18 -> 44 | AH18: =N18 -> 242 | AI18: =S18 -> 563 | AJ18: =E18 -> 5 | AK18: =J18 -> 2 | AL18: =O18 -> 4 | AM18: =T18 -> 17 | AN18: =SUM(AJ18:AM18) -> 28 | AO18: =F18 -> 1 | AP18: =K18 -> 1 | AQ18: =P18 -> 1 | AR18: =U18 -> 1 | AS18: =SUM(AO18:AR18) -> 4
A19: 45929 | B19: 1517 | C19: =(B19-B18)/B18 -> 0.0033068783 | D19: 103 | E19: 0 | F19: 0 | G19: 2313 | H19: =(G19-G18)/G18 -> 0 | I19: 2 | J19: 1 | K19: 0 | L19: 942 | M19: =(L19-L18)/L18 -> 0.0010626993 | N19: 853 | O19: 0 | P19: 0 | Q19: 5682 | R19: =(Q19-Q18)/Q18 -> 0.0017630465 | S19: 126 | T19: 5 | U19: 0 | V19: =B19 -> 1517 | W19: =G19 -> 2313 | X19: =L19 -> 942 | Y19: =Q19 -> 5682 | Z19: =SUM(V19:Y19) -> 10454 | AA19: =(Z19-Z18)/Z18 -> #VALUE! | AB19: =C19 -> 0.0033068783 | AC19: =H19 -> 0 | AD19: =M19 -> 0.0010626993 | AE19: =R19 -> 0.0017630465 | AF19: =D19 -> 103 | AG19: =I19 -> 2 | AH19: =N19 -> 853 | AI19: =S19 -> 126 | AJ19: =E19 -> 0 | AK19: =J19 -> 1 | AL19: =O19 -> 0 | AM19: =T19 -> 5 | AN19: =SUM(AJ19:AM19) -> 6 | AO19: =F19 -> 0 | AP19: =K19 -> 0 | AQ19: =P19 -> 0 | AR19: =U19 -> 0 | AS19: =SUM(AO19:AR19) -> 0
A20: 45936 | B20: 1518 | C20: =(B20-B19)/B19 -> 0.00065919578 | D20: 223 | E20: 8 | F20: 1 | G20: 2313 | H20: =(G20-G19)/G19 -> 0 | I20: 38 | J20: 2 | K20: 1 | L20: 943 | M20: =(L20-L19)/L19 -> 0.0010615711 | N20: 542 | O20: 7 | P20: 1 | Q20: 5680 | R20: =(Q20-Q19)/Q19 -> -0.00035198874 | S20: 354 | T20: 18 | U20: 1 | V20: =B20 -> 1518 | W20: =G20 -> 2313 | X20: =L20 -> 943 | Y20: =Q20 -> 5680 | Z20: =SUM(V20:Y20) -> 10454 | AA20: =(Z20-Z19)/Z19 -> 0 | AB20: =C20 -> 0.00065919578 | AC20: =H20 -> 0 | AD20: =M20 -> 0.0010615711 | AE20: =R20 -> -0.00035198874 | AF20: =D20 -> 223 | AG20: =I20 -> 38 | AH20: =N20 -> 542 | AI20: =S20 -> 354 | AJ20: =E20 -> 8 | AK20: =J20 -> 2 | AL20: =O20 -> 7 | AM20: =T20 -> 18 | AN20: =SUM(AJ20:AM20) -> 35 | AO20: =F20 -> 1 | AP20: =K20 -> 1 | AQ20: =P20 -> 1 | AR20: =U20 -> 1 | AS20: =SUM(AO20:AR20) -> 4
A21: 45943 | B21: 1519 | C21: =(B21-B20)/B20 -> 0.00065876153 | D21: 402 | E21: 7 | F21: 1 | G21: 2311 | H21: =(G21-G20)/G20 -> -0.00086467791 | I21: 82 | J21: 3 | K21: 1 | L21: 951 | M21: =(L21-L20)/L20 -> 0.0084835631 | N21: 1273 | O21: 15 | P21: 1 | Q21: 5678 | R21: =(Q21-Q20)/Q20 -> -0.00035211268 | S21: 787 | T21: 21 | U21: 1 | V21: =B21 -> 1519 | W21: =G21 -> 2311 | X21: =L21 -> 951 | Y21: =Q21 -> 5678 | Z21: =SUM(V21:Y21) -> 10459 | AA21: =(Z21-Z20)/Z20 -> 0.00047828582 | AB21: =C21 -> 0.00065876153 | AC21: =H21 -> -0.00086467791 | AD21: =M21 -> 0.0084835631 | AE21: =R21 -> -0.00035211268 | AF21: =D21 -> 402 | AG21: =I21 -> 82 | AH21: =N21 -> 1273 | AI21: =S21 -> 787 | AJ21: =E21 -> 7 | AK21: =J21 -> 3 | AL21: =O21 -> 15 | AM21: =T21 -> 21 | AN21: =SUM(AJ21:AM21) -> 46 | AO21: =F21 -> 1 | AP21: =K21 -> 1 | AQ21: =P21 -> 1 | AR21: =U21 -> 1 | AS21: =SUM(AO21:AR21) -> 4
A22: 45950 | B22: 1520 | C22: =(B22-B21)/B21 -> 0.00065832785 | D22: 209 | E22: 10 | F22: 0 | G22: 2310 | H22: =(G22-G21)/G21 -> -0.00043271311 | I22: 19 | J22: 1 | K22: 0 | L22: 956 | M22: =(L22-L21)/L21 -> 0.0052576236 | N22: 662 | O22: 1 | P22: 0 | Q22: 5679 | R22: =(Q22-Q21)/Q21 -> 0.00017611835 | S22: 97 | T22: 4 | U22: 0 | V22: =B22 -> 1520 | W22: =G22 -> 2310 | X22: =L22 -> 956 | Y22: =Q22 -> 5679 | Z22: =SUM(V22:Y22) -> 10465 | AA22: =(Z22-Z21)/Z21 -> 0.00057366861 | AB22: =C22 -> 0.00065832785 | AC22: =H22 -> -0.00043271311 | AD22: =M22 -> 0.0052576236 | AE22: =R22 -> 0.00017611835 | AF22: =D22 -> 209 | AG22: =I22 -> 19 | AH22: =N22 -> 662 | AI22: =S22 -> 97 | AJ22: =E22 -> 10 | AK22: =J22 -> 1 | AL22: =O22 -> 1 | AM22: =T22 -> 4 | AN22: =SUM(AJ22:AM22) -> 16 | AO22: =F22 -> 0 | AP22: =K22 -> 0 | AQ22: =P22 -> 0 | AR22: =U22 -> 0 | AS22: =SUM(AO22:AR22) -> 0
A23: 45957 | B23: 1522 | C23: =(B23-B22)/B22 -> 0.0013157895 | D23: 343 | E23: 12 | F23: 2 | G23: 2312 | H23: =(G23-G22)/G22 -> 0.00086580087 | I23: 80 | J23: 7 | K23: 2 | L23: 958 | M23: =(L23-L22)/L22 -> 0.0020920502 | N23: 896 | O23: 6 | P23: 2 | Q23: 5678 | R23: =(Q23-Q22)/Q22 -> -0.00017608734 | S23: 447 | T23: 9 | U23: 2 | V23: =B23 -> 1522 | W23: =G23 -> 2312 | X23: =L23 -> 958 | Y23: =Q23 -> 5678 | Z23: =SUM(V23:Y23) -> 10470 | AA23: =(Z23-Z22)/Z22 -> 0.00047778309 | AB23: =C23 -> 0.0013157895 | AC23: =H23 -> 0.00086580087 | AD23: =M23 -> 0.0020920502 | AE23: =R23 -> -0.00017608734 | AF23: =D23 -> 343 | AG23: =I23 -> 80 | AH23: =N23 -> 896 | AI23: =S23 -> 447 | AJ23: =E23 -> 12 | AK23: =J23 -> 7 | AL23: =O23 -> 6 | AM23: =T23 -> 9 | AN23: =SUM(AJ23:AM23) -> 34 | AO23: =F23 -> 2 | AP23: =K23 -> 2 | AQ23: =P23 -> 2 | AR23: =U23 -> 2 | AS23: =SUM(AO23:AR23) -> 8
A24: 45964 | B24: 1526 | C24: =(B24-B23)/B23 -> 0.0026281209 | D24: 379 | E24: 6 | F24: 1 | G24: 2313 | H24: =(G24-G23)/G23 -> 0.00043252595 | I24: 35 | J24: 3 | K24: 1 | L24: 962 | M24: =(L24-L23)/L23 -> 0.0041753653 | N24: 775 | O24: 0 | P24: 1 | Q24: 5681 | R24: =(Q24-Q23)/Q23 -> 0.00052835505 | S24: 534 | T24: 9 | U24: 1 | V24: =B24 -> 1526 | W24: =G24 -> 2313 | X24: =L24 -> 962 | Y24: =Q24 -> 5681 | Z24: =SUM(V24:Y24) -> 10482 | AA24: =(Z24-Z23)/Z23 -> 0.0011461318 | AB24: =C24 -> 0.0026281209 | AC24: =H24 -> 0.00043252595 | AD24: =M24 -> 0.0041753653 | AE24: =R24 -> 0.00052835505 | AF24: =D24 -> 379 | AG24: =I24 -> 35 | AH24: =N24 -> 775 | AI24: =S24 -> 534 | AJ24: =E24 -> 6 | AK24: =J24 -> 3 | AL24: =O24 -> 0 | AM24: =T24 -> 9 | AN24: =SUM(AJ24:AM24) -> 18 | AO24: =F24 -> 1 | AP24: =K24 -> 1 | AQ24: =P24 -> 1 | AR24: =U24 -> 1 | AS24: =SUM(AO24:AR24) -> 4
A25: 45971 | B25: 1529 | C25: =(B25-B24)/B24 -> 0.001965924 | D25: 544 | E25: 7 | F25: 2 | G25: 2311 | H25: =(G25-G24)/G24 -> -0.00086467791 | I25: 102 | J25: 1 | K25: 2 | L25: 973 | M25: =(L25-L24)/L24 -> 0.011434511 | N25: 2079 | O25: 15 | P25: 2 | Q25: 5682 | R25: =(Q25-Q24)/Q24 -> 0.00017602535 | S25: 747 | T25: 25 | U25: 2 | V25: =B25 -> 1529 | W25: =G25 -> 2311 | X25: =L25 -> 973 | Y25: =Q25 -> 5682 | Z25: =SUM(V25:Y25) -> 10495 | AA25: =(Z25-Z24)/Z24 -> 0.0012402213 | AB25: =C25 -> 0.001965924 | AC25: =H25 -> -0.00086467791 | AD25: =M25 -> 0.011434511 | AE25: =R25 -> 0.00017602535 | AF25: =D25 -> 544 | AG25: =I25 -> 102 | AH25: =N25 -> 2079 | AI25: =S25 -> 747 | AJ25: =E25 -> 7 | AK25: =J25 -> 1 | AL25: =O25 -> 15 | AM25: =T25 -> 25 | AN25: =SUM(AJ25:AM25) -> 48 | AO25: =F25 -> 2 | AP25: =K25 -> 2 | AQ25: =P25 -> 2 | AR25: =U25 -> 2 | AS25: =SUM(AO25:AR25) -> 8
A26: 45978 | B26: 1533 | C26: =(B26-B25)/B25 -> 0.0026160889 | D26: 856 | E26: 18 | F26: 1 | G26: 2309 | H26: =(G26-G25)/G25 -> -0.00086542622 | I26: 82 | J26: 0 | K26: 1 | L26: 973 | M26: =(L26-L25)/L25 -> 0 | N26: 420 | O26: 2 | P26: 1 | Q26: 5678 | R26: =(Q26-Q25)/Q25 -> -0.00070397747 | S26: 333 | T26: 8 | U26: 1 | V26: =B26 -> 1533 | W26: =G26 -> 2309 | X26: =L26 -> 973 | Y26: =Q26 -> 5678 | Z26: =SUM(V26:Y26) -> 10493 | AA26: =(Z26-Z25)/Z25 -> -0.00019056694 | AB26: =C26 -> 0.0026160889 | AC26: =H26 -> -0.00086542622 | AD26: =M26 -> 0 | AE26: =R26 -> -0.00070397747 | AF26: =D26 -> 856 | AG26: =I26 -> 82 | AH26: =N26 -> 420 | AI26: =S26 -> 333 | AJ26: =E26 -> 18 | AK26: =J26 -> 0 | AL26: =O26 -> 2 | AM26: =T26 -> 8 | AN26: =SUM(AJ26:AM26) -> 28 | AO26: =F26 -> 1 | AP26: =K26 -> 1 | AQ26: =P26 -> 1 | AR26: =U26 -> 1 | AS26: =SUM(AO26:AR26) -> 4
A27: 45985 | B27: 1538 | C27: =(B27-B26)/B26 -> 0.0032615786 | D27: 477 | E27: 13 | F27: 1 | G27: 2309 | H27: =(G27-G26)/G26 -> 0 | I27: 68 | J27: 0 | K27: 1 | L27: 972 | M27: =(L27-L26)/L26 -> -0.0010277492 | N27: 770 | O27: 7 | P27: 1 | Q27: 5675 | R27: =(Q27-Q26)/Q26 -> -0.00052835505 | S27: 162 | T27: 4 | U27: 1 | V27: =B27 -> 1538 | W27: =G27 -> 2309 | X27: =L27 -> 972 | Y27: =Q27 -> 5675 | Z27: =SUM(V27:Y27) -> 10494 | AA27: =(Z27-Z26)/Z26 -> 9.530163e-05 | AB27: =C27 -> 0.0032615786 | AC27: =H27 -> 0 | AD27: =M27 -> -0.0010277492 | AE27: =R27 -> -0.00052835505 | AF27: =D27 -> 477 | AG27: =I27 -> 68 | AH27: =N27 -> 770 | AI27: =S27 -> 162 | AJ27: =E27 -> 13 | AK27: =J27 -> 0 | AL27: =O27 -> 7 | AM27: =T27 -> 4 | AN27: =SUM(AJ27:AM27) -> 24 | AO27: =F27 -> 1 | AP27: =K27 -> 1 | AQ27: =P27 -> 1 | AR27: =U27 -> 1 | AS27: =SUM(AO27:AR27) -> 4
A28: 45992 | B28: 1545 | C28: =(B28-B27)/B27 -> 0.0045513654 | D28: 340 | E28: 16 | F28: 1 | G28: 2309 | H28: =(G28-G27)/G27 -> 0 | I28: 206 | J28: 5 | K28: 1 | L28: 973 | M28: =(L28-L27)/L27 -> 0.0010288066 | N28: 768 | O28: 12 | P28: 1 | Q28: 5675 | R28: =(Q28-Q27)/Q27 -> 0 | S28: 344 | T28: 15 | U28: 1 | V28: =B28 -> 1545 | W28: =G28 -> 2309 | X28: =L28 -> 973 | Y28: =Q28 -> 5675 | Z28: =SUM(V28:Y28) -> 10502 | AA28: =(Z28-Z27)/Z27 -> 0.00076234038 | AB28: =C28 -> 0.0045513654 | AC28: =H28 -> 0 | AD28: =M28 -> 0.0010288066 | AE28: =R28 -> 0 | AF28: =D28 -> 340 | AG28: =I28 -> 206 | AH28: =N28 -> 768 | AI28: =S28 -> 344 | AJ28: =E28 -> 16 | AK28: =J28 -> 5 | AL28: =O28 -> 12 | AM28: =T28 -> 15 | AN28: =SUM(AJ28:AM28) -> 48 | AO28: =F28 -> 1 | AP28: =K28 -> 1 | AQ28: =P28 -> 1 | AR28: =U28 -> 1 | AS28: =SUM(AO28:AR28) -> 4
A29: 45999 | B29: 1551 | C29: =(B29-B28)/B28 -> 0.0038834951 | D29: 480 | E29: 22 | F29: 1 | G29: 2308 | H29: =(G29-G28)/G28 -> -0.00043308792 | I29: 63 | J29: 3 | K29: 1 | L29: 975 | M29: =(L29-L28)/L28 -> 0.0020554985 | N29: 366 | O29: 11 | P29: 1 | Q29: 5677 | R29: =(Q29-Q28)/Q28 -> 0.00035242291 | S29: 242 | T29: 12 | U29: 1 | V29: =B29 -> 1551 | W29: =G29 -> 2308 | X29: =L29 -> 975 | Y29: =Q29 -> 5677 | Z29: =SUM(V29:Y29) -> 10511 | AA29: =(Z29-Z28)/Z28 -> 0.00085697962 | AB29: =C29 -> 0.0038834951 | AC29: =H29 -> -0.00043308792 | AD29: =M29 -> 0.0020554985 | AE29: =R29 -> 0.00035242291 | AF29: =D29 -> 480 | AG29: =I29 -> 63 | AH29: =N29 -> 366 | AI29: =S29 -> 242 | AJ29: =E29 -> 22 | AK29: =J29 -> 3 | AL29: =O29 -> 11 | AM29: =T29 -> 12 | AN29: =SUM(AJ29:AM29) -> 48 | AO29: =F29 -> 1 | AP29: =K29 -> 1 | AQ29: =P29 -> 1 | AR29: =U29 -> 1 | AS29: =SUM(AO29:AR29) -> 4
A30: 46006 | B30: 1558 | C30: =(B30-B29)/B29 -> 0.0045132173 | D30: 420 | E30: 17 | F30: 1 | G30: 2307 | H30: =(G30-G29)/G29 -> -0.00043327556 | I30: 68 | J30: 2 | K30: 1 | L30: 976 | M30: =(L30-L29)/L29 -> 0.001025641 | N30: 337 | O30: 3 | P30: 1 | Q30: 5681 | R30: =(Q30-Q29)/Q29 -> 0.0007045975 | S30: 298 | T30: 9 | U30: 1 | V30: =B30 -> 1558 | W30: =G30 -> 2307 | X30: =L30 -> 976 | Y30: =Q30 -> 5681 | Z30: =SUM(V30:Y30) -> 10522 | AA30: =(Z30-Z29)/Z29 -> 0.0010465227 | AB30: =C30 -> 0.0045132173 | AC30: =H30 -> -0.00043327556 | AD30: =M30 -> 0.001025641 | AE30: =R30 -> 0.0007045975 | AF30: =D30 -> 420 | AG30: =I30 -> 68 | AH30: =N30 -> 337 | AI30: =S30 -> 298 | AJ30: =E30 -> 17 | AK30: =J30 -> 2 | AL30: =O30 -> 3 | AM30: =T30 -> 9 | AN30: =SUM(AJ30:AM30) -> 31 | AO30: =F30 -> 1 | AP30: =K30 -> 1 | AQ30: =P30 -> 1 | AR30: =U30 -> 1 | AS30: =SUM(AO30:AR30) -> 4
A31: 46013 | B31: 1563 | C31: =(B31-B30)/B30 -> 0.0032092426 | D31: 472 | E31: 10 | F31: 0 | G31: 2305 | H31: =(G31-G30)/G30 -> -0.00086692674 | I31: 20 | J31: 0 | K31: 0 | L31: 981 | M31: =(L31-L30)/L30 -> 0.0051229508 | N31: 496 | O31: 6 | P31: 0 | Q31: 5679 | R31: =(Q31-Q30)/Q30 -> -0.0003520507 | S31: 115 | T31: 0 | U31: 0 | V31: =B31 -> 1563 | W31: =G31 -> 2305 | X31: =L31 -> 981 | Y31: =Q31 -> 5679 | Z31: =SUM(V31:Y31) -> 10528 | AA31: =(Z31-Z30)/Z30 -> 0.0005702338 | AB31: =C31 -> 0.0032092426 | AC31: =H31 -> -0.00086692674 | AD31: =M31 -> 0.0051229508 | AE31: =R31 -> -0.0003520507 | AF31: =D31 -> 472 | AG31: =I31 -> 20 | AH31: =N31 -> 496 | AI31: =S31 -> 115 | AJ31: =E31 -> 10 | AK31: =J31 -> 0 | AL31: =N31 -> 496 | AM31: =T31 -> 0 | AN31: =SUM(AJ31:AM31) -> 506 | AO31: =F31 -> 0 | AP31: =K31 -> 0 | AQ31: =P31 -> 0 | AR31: =U31 -> 0 | AS31: =SUM(AO31:AR31) -> 0
A32: 46020 | B32: 1567 | C32: =(B32-B31)/B31 -> 0.0025591811 | D32: 294 | E32: 6 | F32: 0 | G32: 2307 | H32: =(G32-G31)/G31 -> 0.00086767896 | I32: 11 | J32: 0 | K32: 0 | L32: 981 | M32: =(L32-L31)/L31 -> 0 | N32: 78 | O32: 0 | P32: 0 | Q32: 5680 | R32: =(Q32-Q31)/Q31 -> 0.00017608734 | S32: 34 | T32: 3 | U32: 0 | V32: =B32 -> 1567 | W32: =G32 -> 2307 | X32: =L32 -> 981 | Y32: =Q32 -> 5680 | Z32: =SUM(V32:Y32) -> 10535 | AA32: =(Z32-Z31)/Z31 -> 0.00066489362 | AB32: =C32 -> 0.0025591811 | AC32: =H32 -> 0.00086767896 | AD32: =M32 -> 0 | AE32: =R32 -> 0.00017608734 | AF32: =D32 -> 294 | AG32: =I32 -> 11 | AH32: =N32 -> 78 | AI32: =S32 -> 34 | AJ32: =E32 -> 6 | AK32: =J32 -> 0 | AL32: =O32 -> 0 | AM32: =T32 -> 3 | AN32: =SUM(AJ32:AM32) -> 9 | AO32: =F32 -> 0 | AP32: =K32 -> 0 | AQ32: =P33 -> 0 | AR32: =U32 -> 0 | AS32: =SUM(AO32:AR32) -> 0
A33: 46027 | B33: 1568 | C33: =(B33-B32)/B32 -> 0.00063816209 | D33: 356 | E33: 6 | F33: 0 | G33: 2308 | H33: =(G33-G32)/G32 -> 0.00043346337 | I33: 39 | J33: 0 | K33: 0 | L33: 982 | M33: =(L33-L32)/L32 -> 0.001019368 | N33: 63 | O33: 1 | P33: 0 | Q33: 5678 | R33: =(Q33-Q32)/Q32 -> -0.00035211268 | S33: 69 | T33: 4 | U33: 0 | V33: =B33 -> 1568 | W33: =G33 -> 2308 | X33: =L33 -> 982 | Y33: =Q33 -> 5678 | Z33: =SUM(V33:Y33) -> 10536 | AA33: =(Z33-Z32)/Z32 -> 9.492169e-05 | AB33: =C33 -> 0.00063816209 | AC33: =H33 -> 0.00043346337 | AD33: =M33 -> 0.001019368 | AE33: =R33 -> -0.00035211268 | AF33: =D33 -> 356 | AG33: =I33 -> 39 | AH33: =N33 -> 63 | AI33: =S33 -> 69 | AJ33: =E33 -> 6 | AK33: =J33 -> 0 | AL33: =O33 -> 1 | AM33: =T33 -> 4 | AN33: =SUM(AJ33:AM33) -> 11 | AO33: =F33 -> 0 | AP33: =K33 -> 0 | AQ33: =#REF! -> #REF! | AR33: =U33 -> 0 | AS33: =SUM(AO33:AR33) -> #REF!
A34: 46034 | B34: 1568 | C34: =(B34-B33)/B33 -> 0 | D34: 348 | E34: 8 | F34: 1 | G34: 2309 | H34: =(G34-G33)/G33 -> 0.00043327556 | I34: 100 | J34: 2 | K34: 1 | L34: 983 | M34: =(L34-L33)/L33 -> 0.0010183299 | N34: 313 | O34: 3 | P34: 1 | Q34: 5678 | R34: =(Q34-Q33)/Q33 -> 0 | S34: 301 | T34: 7 | U34: 1 | V34: =B34 -> 1568 | W34: =G34 -> 2309 | X34: =L34 -> 983 | Y34: =Q34 -> 5678 | Z34: =SUM(V34:Y34) -> 10538 | AA34: =(Z34-Z33)/Z33 -> 0.00018982536 | AB34: =C34 -> 0 | AC34: =H34 -> 0.00043327556 | AD34: =M34 -> 0.0010183299 | AE34: =R34 -> 0 | AF34: =D34 -> 348 | AG34: =I34 -> 100 | AH34: =N34 -> 313 | AI34: =S34 -> 301 | AJ34: =E34 -> 8 | AK34: =J34 -> 2 | AL34: =O34 -> 3 | AM34: =T34 -> 7 | AN34: =SUM(AJ34:AM34) -> 20 | AO34: =F34 -> 1 | AP34: =K34 -> 1 | AQ34: =P34 -> 1 | AR34: =U34 -> 1 | AS34: =SUM(AO34:AR34) -> 4
A35: 46041 | B35: 1568 | C35: =(B35-B34)/B34 -> 0 | D35: 100 | E35: 1 | F35: 0 | G35: 2309 | H35: =(G35-G34)/G34 -> 0 | I35: 21 | J35: 0 | K35: 0 | L35: 983 | M35: =(L35-L34)/L34 -> 0 | N35: 92 | O35: 2 | P35: 0 | Q35: 5681 | R35: =(Q35-Q34)/Q34 -> 0.00052835505 | S35: 82 | T35: 0 | U35: 0 | V35: =B35 -> 1568 | W35: =G35 -> 2309 | X35: =L35 -> 983 | Y35: =Q35 -> 5681 | Z35: =SUM(V35:Y35) -> 10541 | AA35: =(Z35-Z34)/Z34 -> 0.000284684 | AB35: =C35 -> 0 | AC35: =H35 -> 0 | AD35: =M35 -> 0 | AE35: =R35 -> 0.00052835505 | AF35: =D35 -> 100 | AG35: =I35 -> 21 | AH35: =N35 -> 92 | AI35: =S35 -> 82 | AJ35: =E35 -> 1 | AK35: =J35 -> 0 | AL35: =O35 -> 2 | AM35: =T35 -> 0 | AN35: =SUM(AJ35:AM35) -> 3 | AO35: =F35 -> 0 | AP35: =K35 -> 0 | AQ35: =P35 -> 0 | AR35: =U35 -> 0 | AS35: =SUM(AO35:AR35) -> 0
A36: 46048 | B36: 1575 | C36: =(B36-B35)/B35 -> 0.0044642857 | D36: 292 | E36: 17 | F36: 1 | G36: 2315 | H36: =(G36-G35)/G35 -> 0.0025985275 | I36: 261 | J36: 2 | K36: 1 | L36: 987 | M36: =(L36-L35)/L35 -> 0.004069176 | N36: 325 | O36: 3 | P36: 1 | Q36: 5684 | R36: =(Q36-Q35)/Q35 -> 0.00052807604 | S36: 544 | T36: 32 | U36: 1 | V36: =B36 -> 1575 | W36: =G36 -> 2315 | X36: =L36 -> 987 | Y36: =Q36 -> 5684 | Z36: =SUM(V36:Y36) -> 10561 | AA36: =(Z36-Z35)/Z35 -> 0.0018973532 | AB36: =C36 -> 0.0044642857 | AC36: =H36 -> 0.0025985275 | AD36: =M36 -> 0.004069176 | AE36: =R36 -> 0.00052807604 | AF36: =D36 -> 292 | AG36: =I36 -> 261 | AH36: =N36 -> 325 | AI36: =S36 -> 544 | AJ36: =E36 -> 17 | AK36: =J36 -> 2 | AL36: =O36 -> 3 | AM36: =T36 -> 32 | AN36: =SUM(AJ36:AM36) -> 54 | AO36: =F36 -> 1 | AP36: =K36 -> 1 | AQ36: =P36 -> 1 | AR36: =U36 -> 1 | AS36: =SUM(AO36:AR36) -> 4
A37: 46055 | B37: 1582 | C37: =(B37-B36)/B36 -> 0.0044444444 | D37: 901 | E37: 44 | F37: 2 | G37: 2319 | H37: =(G37-G36)/G36 -> 0.0017278618 | I37: 275 | J37: 3 | K37: 2 | L37: 992 | M37: =(L37-L36)/L36 -> 0.0050658561 | N37: 1095 | O37: 10 | P37: 2 | Q37: 5686 | R37: =(Q37-Q36)/Q36 -> 0.00035186488 | S37: 634 | T37: 21 | U37: 2 | V37: =B37 -> 1582 | W37: =G37 -> 2319 | X37: =L37 -> 992 | Y37: =Q37 -> 5686 | Z37: =SUM(V37:Y37) -> 10579 | AA37: =(Z37-Z36)/Z36 -> 0.0017043841 | AB37: =C37 -> 0.0044444444 | AC37: =H37 -> 0.0017278618 | AD37: =M37 -> 0.0050658561 | AE37: =R37 -> 0.00035186488 | AF37: =D37 -> 901 | AG37: =I37 -> 275 | AH37: =N37 -> 1095 | AI37: =S37 -> 634 | AJ37: =E37 -> 44 | AK37: =J37 -> 3 | AL37: =O37 -> 10 | AM37: =T37 -> 21 | AN37: =SUM(AJ37:AM37) -> 78 | AO37: =F37 -> 2 | AP37: =K37 -> 2 | AQ37: =P37 -> 2 | AR37: =U37 -> 2 | AS37: =SUM(AO37:AR37) -> 8
A38: 46062 | B38: 1589 | C38: =(B38-B37)/B37 -> 0.0044247788 | D38: 453 | E38: 8 | F38: 1 | G38: 2326 | H38: =(G38-G37)/G37 -> 0.0030185425 | I38: 419 | J38: 6 | K38: 1 | L38: 1008 | M38: =(L38-L37)/L37 -> 0.016129032 | N38: 855 | O38: 14 | P38: 1 | Q38: 5692 | R38: =(Q38-Q37)/Q37 -> 0.0010552234 | S38: 564 | T38: 31 | U38: 1 | V38: =B38 -> 1589 | W38: =G38 -> 2326 | X38: =L38 -> 1008 | Y38: =Q38 -> 5692 | Z38: =SUM(V38:Y38) -> 10615 | AA38: =(Z38-Z37)/Z37 -> 0.0034029681 | AB38: =C38 -> 0.0044247788 | AC38: =H38 -> 0.0030185425 | AD38: =M38 -> 0.016129032 | AE38: =R38 -> 0.0010552234 | AF38: =D38 -> 453 | AG38: =I38 -> 419 | AH38: =N38 -> 855 | AI38: =S38 -> 564 | AJ38: =E38 -> 8 | AK38: =J38 -> 6 | AL38: =O38 -> 14 | AM38: =T38 -> 31 | AN38: =SUM(AJ38:AM38) -> 59 | AO38: =F38 -> 1 | AP38: =K38 -> 1 | AQ38: =P38 -> 1 | AR38: =U38 -> 1 | AS38: =SUM(AO38:AR38) -> 4
A39: 46069 | B39: 1589 | C39: =(B39-B38)/B38 -> 0 | D39: 393 | E39: 14 | F39: 0 | G39: 2331 | H39: =(G39-G38)/G38 -> 0.0021496131 | I39: 304 | J39: 3 | K39: 0 | L39: 1008 | M39: =(L39-L38)/L38 -> 0 | N39: 358 | O39: 5 | P39: 0 | Q39: 5699 | R39: =(Q39-Q38)/Q38 -> 0.0012297962 | S39: 258 | T39: 14 | U39: 0 | V39: =B39 -> 1589 | W39: =G39 -> 2331 | X39: =L39 -> 1008 | Y39: =Q39 -> 5699 | Z39: =SUM(V39:Y39) -> 10627 | AA39: =(Z39-Z38)/Z38 -> 0.0011304757 | AB39: =C39 -> 0 | AC39: =H39 -> 0.0021496131 | AD39: =M39 -> 0 | AE39: =R39 -> 0.0012297962 | AF39: =D39 -> 393 | AG39: =I39 -> 304 | AH39: =N39 -> 358 | AI39: =S39 -> 258 | AJ39: =E39 -> 14 | AK39: =J39 -> 3 | AL39: =O39 -> 5 | AM39: =T39 -> 14 | AN39: =SUM(AJ39:AM39) -> 36 | AO39: =F39 -> 0 | AP39: =K39 -> 0 | AQ39: =P39 -> 0 | AR39: =U39 -> 0 | AS39: =SUM(AO39:AR39) -> 0
A40: 46076 | B40: 1596 | C40: =(B40-B39)/B39 -> 0.0044052863 | D40: 285 | E40: 79 | F40: 1 | G40: 2343 | H40: =(G40-G39)/G39 -> 0.0051480051 | I40: 263 | J40: 4 | K40: 1 | L40: 1017 | M40: =(L40-L39)/L39 -> 0.0089285714 | N40: 504 | O40: 6 | P40: 1 | Q40: 5703 | R40: =(Q40-Q39)/Q39 -> 0.00070187752 | S40: 259 | T40: 20 | U40: 1 | V40: =B40 -> 1596 | W40: =G40 -> 2343 | X40: =L40 -> 1017 | Y40: =Q40 -> 5703 | Z40: =SUM(V40:Y40) -> 10659 | AA40: =(Z40-Z39)/Z39 -> 0.0030111979 | AB40: =C40 -> 0.0044052863 | AC40: =H40 -> 0.0051480051 | AD40: =M40 -> 0.0089285714 | AE40: =R40 -> 0.00070187752 | AF40: =D40 -> 285 | AG40: =I40 -> 263 | AH40: =N40 -> 504 | AI40: =S40 -> 259 | AJ40: =E40 -> 79 | AK40: =J40 -> 4 | AL40: =O40 -> 6 | AM40: =T40 -> 20 | AN40: =SUM(AJ40:AM40) -> 109 | AO40: =F40 -> 1 | AP40: =K40 -> 1 | AQ40: =P40 -> 1 | AR40: =U40 -> 1 | AS40: =SUM(AO40:AR40) -> 4
A41: 46083 | B41: 1605 | C41: =(B41-B40)/B40 -> 0.0056390977 | D41: 429 | E41: 62 | F41: 2 | G41: 2352 | H41: =(G41-G40)/G40 -> 0.0038412292 | I41: 1004 | J41: 8 | K41: 2 | L41: 1031 | M41: =(L41-L40)/L40 -> 0.013765978 | N41: 1087 | O41: 11 | P41: 2 | Q41: 5701 | R41: =(Q41-Q40)/Q40 -> -0.00035069262 | S41: 599 | T41: 26 | U41: 2 | V41: =B41 -> 1605 | W41: =G41 -> 2352 | X41: =L41 -> 1031 | Y41: =Q41 -> 5701 | Z41: =SUM(V41:Y41) -> 10689 | AA41: =(Z41-Z40)/Z40 -> 0.0028145229 | AB41: =C41 -> 0.0056390977 | AC41: =H41 -> 0.0038412292 | AD41: =M41 -> 0.013765978 | AE41: =R41 -> -0.00035069262 | AF41: =D41 -> 429 | AG41: =I41 -> 1004 | AH41: =N41 -> 1087 | AI41: =S41 -> 599 | AJ41: =E41 -> 62 | AK41: =J41 -> 8 | AL41: =O41 -> 11 | AM41: =T41 -> 26 | AN41: =SUM(AJ41:AM41) -> 107 | AO41: =F41 -> 2 | AP41: =K41 -> 2 | AQ41: =P41 -> 2 | AR41: =U41 -> 2 | AS41: =SUM(AO41:AR41) -> 8
A42: 46090 | B42: 1609 | C42: =(B42-B41)/B41 -> 0.0024922118 | D42: 396 | E42: 34 | F42: 2 | G42: 2359 | H42: =(G42-G41)/G41 -> 0.0029761905 | I42: 213 | J42: 2 | K42: 2 | L42: 1045 | M42: =(L42-L41)/L41 -> 0.013579049 | N42: 457 | O42: 19 | P42: 2 | Q42: 5700 | R42: =(Q42-Q41)/Q41 -> -0.00017540782 | S42: 443 | T42: 11 | U42: 2 | V42: =B42 -> 1609 | W42: =G42 -> 2359 | X42: =L42 -> 1045 | Y42: =Q42 -> 5700 | Z42: =SUM(V42:Y42) -> 10713 | AB42: =C42 -> 0.0024922118 | AC42: =H42 -> 0.0029761905 | AD42: =M42 -> 0.013579049 | AE42: =R42 -> -0.00017540782 | AF42: =D42 -> 396 | AG42: =I42 -> 213 | AH42: =N42 -> 457 | AI42: =S42 -> 443 | AJ42: =E42 -> 34 | AK42: =J42 -> 2 | AL42: =O42 -> 19 | AM42: =T42 -> 11 | AN42: =SUM(AJ42:AM42) -> 66 | AO42: =F42 -> 2 | AP42: =K42 -> 2 | AQ42: =P42 -> 2 | AR42: =U42 -> 2 | AS42: =SUM(AO42:AR42) -> 8
A43: 46097 | B43: 1617 | C43: =(B43-B42)/B42 -> 0.0049720323 | D43: 373 | E43: 9 | F43: 0 | G43: 2361 | H43: =(G43-G42)/G42 -> 0.00084781687 | I43: 139 | J43: 0 | K43: 0 | L43: 1051 | M43: =(L43-L42)/L42 -> 0.0057416268 | N43: 101 | O43: 5 | P43: 0 | Q43: 5705 | R43: =(Q43-Q42)/Q42 -> 0.00087719298 | S43: 443 | T43: 6 | U43: 0 | V43: =B43 -> 1617 | W43: =G43 -> 2361 | X43: =L43 -> 1051 | Y43: =Q43 -> 5705 | Z43: =SUM(V43:Y43) -> 10734 | AB43: =C43 -> 0.0049720323 | AC43: =H43 -> 0.00084781687 | AD43: =M43 -> 0.0057416268 | AE43: =R43 -> 0.00087719298 | AF43: =D43 -> 373 | AG43: =I43 -> 139 | AH43: =N43 -> 101 | AI43: =S43 -> 443 | AJ43: =E43 -> 9 | AK43: =J43 -> 0 | AL43: =O43 -> 5 | AM43: =T43 -> 6 | AN43: =SUM(AJ43:AM43) -> 20 | AO43: =F43 -> 0 | AP43: =K43 -> 0 | AQ43: =P43 -> 0 | AR43: =U43 -> 0 | AS43: =SUM(AO43:AR43) -> 0
A44: 46104 | B44: 1623 | C44: =(B44-B43)/B43 -> 0.0037105751 | D44: 249 | E44: 18 | F44: 1 | G44: 2365 | H44: =(G44-G43)/G43 -> 0.0016941974 | I44: 299 | J44: 3 | K44: 1 | L44: 1062 | M44: =(L44-L43)/L43 -> 0.010466223 | N44: 169 | O44: 2 | P44: 1 | Q44: 5704 | R44: =(Q44-Q43)/Q43 -> -0.00017528484 | S44: 170 | T44: 14 | U44: 1 | V44: =B44 -> 1623 | W44: =G44 -> 2365 | X44: =L44 -> 1062 | Y44: =Q44 -> 5704 | Z44: =SUM(V44:Y44) -> 10754 | AB44: =C44 -> 0.0037105751 | AC44: =H44 -> 0.0016941974 | AD44: =M44 -> 0.010466223 | AE44: =R44 -> -0.00017528484 | AF44: =D44 -> 249 | AG44: =I44 -> 299 | AH44: =N44 -> 169 | AI44: =S44 -> 170 | AJ44: =E44 -> 18 | AK44: =J44 -> 3 | AL44: =O44 -> 2 | AM44: =T44 -> 14 | AN44: =SUM(AJ44:AM44) -> 37 | AO44: =F44 -> 1 | AP44: =K44 -> 1 | AQ44: =P44 -> 1 | AR44: =U44 -> 1 | AS44: =SUM(AO44:AR44) -> 4
A45: 46111 | B45: 1626 | C45: =(B45-B44)/B44 -> 0.0018484288 | D45: 278 | E45: 7 | F45: 1 | G45: 2368 | H45: =(G45-G44)/G44 -> 0.0012684989 | I45: 58 | J45: 5 | K45: 1 | L45: 1076 | M45: =(L45-L44)/L44 -> 0.013182674 | N45: 355 | O45: 3 | P45: 1 | Q45: 5703 | R45: =(Q45-Q44)/Q44 -> -0.00017531557 | S45: 161 | T45: 4 | U45: 1 | V45: =B45 -> 1626 | W45: =G45 -> 2368 | X45: =L45 -> 1076 | Y45: =Q45 -> 5703 | Z45: =SUM(V45:Y45) -> 10773 | AB45: =C45 -> 0.0018484288 | AC45: =H45 -> 0.0012684989 | AD45: =M45 -> 0.013182674 | AE45: =R45 -> -0.00017531557 | AF45: =D45 -> 278 | AG45: =I45 -> 58 | AH45: =N45 -> 355 | AI45: =S45 -> 161 | AJ45: =E45 -> 7 | AK45: =J45 -> 5 | AL45: =O45 -> 3 | AM45: =T45 -> 4 | AN45: =SUM(AJ45:AM45) -> 19 | AO45: =F45 -> 1 | AP45: =K45 -> 1 | AQ45: =P45 -> 1 | AR45: =U45 -> 1 | AS45: =SUM(AO45:AR45) -> 4
A46: 46118 | B46: 1631 | C46: =(B46-B45)/B45 -> 0.0030750308 | D46: 494 | E46: 93 | F46: 1 | G46: 2374 | H46: =(G46-G45)/G45 -> 0.0025337838 | I46: 366 | J46: 3 | K46: 1 | L46: 1087 | M46: =(L46-L45)/L45 -> 0.010223048 | N46: 297 | O46: 3 | P46: 1 | Q46: 5704 | R46: =(Q46-Q45)/Q45 -> 0.00017534631 | S46: 865 | T46: 50 | U46: 1 | V46: =B46 -> 1631 | W46: =G46 -> 2374 | X46: =L46 -> 1087 | Y46: =Q46 -> 5704 | Z46: =SUM(V46:Y46) -> 10796 | AB46: =C46 -> 0.0030750308 | AC46: =H46 -> 0.0025337838 | AD46: =M46 -> 0.010223048 | AE46: =R46 -> 0.00017534631 | AF46: =D46 -> 494 | AG46: =I46 -> 366 | AH46: =N46 -> 297 | AI46: =S46 -> 865 | AJ46: =E46 -> 93 | AK46: =J46 -> 3 | AL46: =O46 -> 3 | AM46: =T46 -> 50 | AN46: =SUM(AJ46:AM46) -> 149 | AO46: =F46 -> 1 | AP46: =K46 -> 1 | AQ46: =P46 -> 1 | AR46: =U46 -> 1 | AS46: =SUM(AO46:AR46) -> 4
A47: 46125 | B47: 1654 | C47: =(B47-B46)/B46 -> 0.014101778 | D47: 2221 | E47: 181 | F47: 2 | G47: 2381 | H47: =(G47-G46)/G46 -> 0.0029486099 | I47: 458 | J47: 11 | K47: 2 | L47: 1095 | M47: =(L47-L46)/L46 -> 0.0073597056 | N47: 480 | O47: 11 | P47: 2 | Q47: 5709 | R47: =(Q47-Q46)/Q46 -> 0.00087657784 | S47: 1507 | T47: 63 | U47: 2 | V47: =B47 -> 1654 | W47: =G47 -> 2381 | X47: =L47 -> 1095 | Y47: =Q47 -> 5709 | Z47: =SUM(V47:Y47) -> 10839 | AB47: =C47 -> 0.014101778 | AC47: =H47 -> 0.0029486099 | AD47: =M47 -> 0.0073597056 | AE47: =R47 -> 0.00087657784 | AF47: =D47 -> 2221 | AG47: =I47 -> 458 | AH47: =N47 -> 480 | AI47: =S47 -> 1507 | AJ47: =E47 -> 181 | AK47: =J47 -> 11 | AL47: =O47 -> 11 | AM47: =T47 -> 63 | AN47: =SUM(AJ47:AM47) -> 266 | AO47: =F47 -> 2 | AP47: =K47 -> 2 | AQ47: =P47 -> 2 | AR47: =U47 -> 2 | AS47: =SUM(AO47:AR47) -> 8
A48: 46132 | B48: 1670 | C48: =(B48-B47)/B47 -> 0.0096735187 | D48: 1425 | E48: 81 | F48: 2 | G48: 2383 | H48: =(G48-G47)/G47 -> 0.0008399832 | I48: 144 | J48: 2 | K48: 2 | L48: 1102 | M48: =(L48-L47)/L47 -> 0.0063926941 | N48: 526 | O48: 8 | P48: 2 | Q48: 5709 | R48: =(Q48-Q47)/Q47 -> 0 | S48: 777 | T48: 47 | U48: 2 | V48: =B48 -> 1670 | W48: =G48 -> 2383 | X48: =L48 -> 1102 | Y48: =Q48 -> 5709 | Z48: =SUM(V48:Y48) -> 10864 | AB48: =C48 -> 0.0096735187 | AC48: =H48 -> 0.0008399832 | AD48: =M48 -> 0.0063926941 | AE48: =R48 -> 0 | AF48: =D48 -> 1425 | AG48: =I48 -> 144 | AH48: =N48 -> 526 | AI48: =S48 -> 777 | AJ48: =E48 -> 81 | AK48: =J48 -> 2 | AL48: =O48 -> 8 | AM48: =T48 -> 47 | AN48: =SUM(AJ48:AM48) -> 138 | AO48: =F48 -> 2 | AP48: =K48 -> 2 | AQ48: =P48 -> 2 | AR48: =U48 -> 2 | AS48: =SUM(AO48:AR48) -> 8
A49: 46139 | B49: 1684 | C49: =(B49-B48)/B48 -> 0.0083832335 | D49: 1125 | E49: 40 | F49: 1 | G49: 2392 | H49: =(G49-G48)/G48 -> 0.003776752 | I49: 167 | J49: 5 | K49: 1 | L49: 1102 | M49: =(L49-L48)/L48 -> 0 | N49: 273 | O49: 7 | P49: 1 | Q49: 5711 | R49: =(Q49-Q48)/Q48 -> 0.00035032405 | S49: 185 | T49: 6 | U49: 1 | V49: =B49 -> 1684 | W49: =G49 -> 2392 | X49: =L49 -> 1102 | Y49: =Q49 -> 5711 | Z49: =SUM(V49:Y49) -> 10889 | AB49: =C49 -> 0.0083832335 | AC49: =H49 -> 0.003776752 | AD49: =M49 -> 0 | AE49: =R49 -> 0.00035032405 | AF49: =D49 -> 1125 | AG49: =I49 -> 167 | AH49: =N49 -> 273 | AI49: =S49 -> 185 | AJ49: =E49 -> 40 | AK49: =J49 -> 5 | AL49: =O49 -> 7 | AM49: =T49 -> 6 | AN49: =SUM(AJ49:AM49) -> 58 | AO49: =F49 -> 1 | AP49: =K49 -> 1 | AQ49: =P49 -> 1 | AR49: =U49 -> 1 | AS49: =SUM(AO49:AR49) -> 4
A50: 46146 | B50: 1692 | C50: =(B50-B49)/B49 -> 0.0047505938 | D50: 1390 | E50: 67 | F50: 2 | G50: 2396 | H50: =(G50-G49)/G49 -> 0.0016722408 | I50: 561 | J50: 5 | K50: 2 | L50: 1107 | M50: =(L50-L49)/L49 -> 0.0045372051 | N50: 457 | O50: 13 | P50: 2 | Q50: 5713 | R50: =(Q50-Q49)/Q49 -> 0.00035020137 | S50: 21 | T50: 0 | U50: 2 | V50: =B50 -> 1692 | W50: =G50 -> 2396 | X50: =L50 -> 1107 | Y50: =Q50 -> 5713 | Z50: =SUM(V50:Y50) -> 10908 | AB50: =C50 -> 0.0047505938 | AC50: =H50 -> 0.0016722408 | AD50: =M50 -> 0.0045372051 | AE50: =R50 -> 0.00035020137 | AF50: =D50 -> 1390 | AG50: =I50 -> 561 | AH50: =N50 -> 457 | AI50: =S50 -> 21 | AJ50: =E50 -> 67 | AK50: =J50 -> 5 | AL50: =O50 -> 13 | AM50: =T50 -> 0 | AN50: =SUM(AJ50:AM50) -> 85 | AO50: =F50 -> 2 | AP50: =K50 -> 2 | AQ50: =P50 -> 2 | AR50: =U50 -> 2 | AS50: =SUM(AO50:AR50) -> 8
A51: 46153 | B51: 1703 | C51: =(B51-B50)/B50 -> 0.006501182 | D51: 1176 | E51: 42 | F51: 2 | G51: 2404 | H51: =(G51-G50)/G50 -> 0.0033388982 | I51: 631 | J51: 17 | K51: 2 | L51: 1112 | M51: =(L51-L50)/L50 -> 0.0045167118 | N51: 867 | O51: 15 | P51: 2 | Q51: 5715 | R51: =(Q51-Q50)/Q50 -> 0.00035007877 | S51: 1377 | T51: 28 | U51: 2 | V51: =B51 -> 1703 | W51: =G51 -> 2404 | X51: =L51 -> 1112 | Y51: =Q51 -> 5715 | Z51: =SUM(V51:Y51) -> 10934 | AB51: =C51 -> 0.006501182 | AC51: =H51 -> 0.0033388982 | AD51: =M51 -> 0.0045167118 | AE51: =R51 -> 0.00035007877 | AF51: =D51 -> 1176 | AG51: =I51 -> 631 | AH51: =N51 -> 867 | AI51: =S51 -> 1377 | AJ51: =E51 -> 42 | AK51: =J51 -> 17 | AL51: =O51 -> 15 | AM51: =T51 -> 28 | AN51: =SUM(AJ51:AM51) -> 102 | AO51: =F51 -> 2 | AP51: =K51 -> 2 | AQ51: =P51 -> 2 | AR51: =U51 -> 2 | AS51: =SUM(AO51:AR51) -> 8
A52: 46160 | B52: 1718 | C52: =(B52-B51)/B51 -> 0.0088079859 | D52: 1514 | E52: 53 | F52: 1 | G52: 2415 | H52: =(G52-G51)/G51 -> 0.0045757072 | I52: 353 | J52: 4 | K52: 1 | L52: 1121 | M52: =(L52-L51)/L51 -> 0.0080935252 | N52: 773 | O52: 6 | P52: 1 | Q52: 5717 | R52: =(Q52-Q51)/Q51 -> 0.00034995626 | S52: 604 | T52: 10 | U52: 1 | V52: =B52 -> 1718 | W52: =G52 -> 2415 | X52: =L52 -> 1121 | Y52: =Q52 -> 5717 | Z52: =SUM(V52:Y52) -> 10971 | AB52: =C52 -> 0.0088079859 | AC52: =H52 -> 0.0045757072 | AD52: =M52 -> 0.0080935252 | AE52: =R52 -> 0.00034995626 | AF52: =D52 -> 1514 | AG52: =I52 -> 353 | AH52: =N52 -> 773 | AI52: =S52 -> 604 | AJ52: =E52 -> 53 | AK52: =J52 -> 4 | AL52: =O52 -> 6 | AM52: =T52 -> 10 | AN52: =SUM(AJ52:AM52) -> 73 | AO52: =F52 -> 1 | AP52: =K52 -> 1 | AQ52: =P52 -> 1 | AR52: =U52 -> 1 | AS52: =SUM(AO52:AR52) -> 4
A53: 46167 | B53: 1726 | C53: =(B53-B52)/B52 -> 0.0046565774 | D53: 526 | E53: 11 | F53: 0 | G53: 2422 | H53: =(G53-G52)/G52 -> 0.0028985507 | I53: 133 | J53: 2 | K53: 0 | L53: 1126 | M53: =(L53-L52)/L52 -> 0.0044603033 | N53: 63 | O53: 1 | P53: 0 | Q53: 5717 | R53: =(Q53-Q52)/Q52 -> 0 | S53: 111 | T53: 5 | U53: 0 | V53: =B53 -> 1726 | W53: =G53 -> 2422 | X53: =L53 -> 1126 | Y53: =Q53 -> 5717 | Z53: =SUM(V53:Y53) -> 10991 | AB53: =C53 -> 0.0046565774 | AC53: =H53 -> 0.0028985507 | AD53: =M53 -> 0.0044603033 | AE53: =R53 -> 0 | AF53: =D53 -> 526 | AG53: =I53 -> 133 | AH53: =N53 -> 63 | AI53: =S53 -> 111 | AJ53: =E53 -> 11 | AK53: =J53 -> 2 | AL53: =O53 -> 1 | AM53: =T53 -> 5 | AN53: =SUM(AJ53:AM53) -> 19 | AO53: =F53 -> 0 | AP53: =K53 -> 0 | AQ53: =P53 -> 0 | AR53: =U53 -> 0 | AS53: =SUM(AO53:AR53) -> 0
A54: 46174 | B54: 1751 | C54: =(B54-B53)/B53 -> 0.014484357 | D54: 1213 | E54: 59 | F54: 3 | G54: 2426 | H54: =(G54-G53)/G53 -> 0.0016515277 | I54: 296 | J54: 12 | K54: 3 | L54: 1139 | M54: =(L54-L53)/L53 -> 0.011545293 | N54: 855 | O54: 9 | P54: 3 | Q54: 1247 | R54: =(Q54-Q53)/Q53 -> -0.78187861 | S54: 1247 | T54: 78 | U54: 3 | V54: =B54 -> 1751 | W54: =G54 -> 2426 | X54: =L54 -> 1139 | Y54: =Q54 -> 1247 | Z54: =SUM(V54:Y54) -> 6563 | AB54: =C54 -> 0.014484357 | AC54: =H54 -> 0.0016515277 | AD54: =M54 -> 0.011545293 | AE54: =R54 -> -0.78187861 | AF54: =D54 -> 1213 | AG54: =I54 -> 296 | AH54: =N54 -> 855 | AI54: =S54 -> 1247 | AJ54: =E54 -> 59 | AK54: =J54 -> 12 | AL54: =O54 -> 9 | AM54: =T54 -> 78 | AN54: =SUM(AJ54:AM54) -> 158 | AO54: =F54 -> 3 | AP54: =K54 -> 3 | AQ54: =P54 -> 3 | AR54: =U54 -> 3 | AS54: =SUM(AO54:AR54) -> 12
A55: 46181 | C55: =(B55-B54)/B54 -> -1 | H55: =(G55-G54)/G54 -> -1 | M55: =(L55-L54)/L54 -> -1 | R55: =(Q55-Q54)/Q54 -> -1 | V55: =B55 -> 0 | W55: =G55 -> 0 | X55: =L55 -> 0 | Y55: =Q55 -> 0 | Z55: =SUM(V55:Y55) -> 0 | AB55: =C55 -> -1 | AC55: =H55 -> -1 | AD55: =M55 -> -1 | AE55: =R55 -> -1 | AF55: =D55 -> 0 | AG55: =I55 -> 0 | AH55: =N55 -> 0 | AI55: =S55 -> 0 | AJ55: =E55 -> 0 | AK55: =J55 -> 0 | AL55: =O55 -> 0 | AM55: =T55 -> 0 | AN55: =SUM(AJ55:AM55) -> 0 | AO55: =F55 -> 0 | AP55: =K55 -> 0 | AQ55: =P55 -> 0 | AR55: =U55 -> 0 | AS55: =SUM(AO55:AR55) -> 0
A56: 46188 | C56: =(B56-B55)/B55 -> #DIV/0! | H56: =(G56-G55)/G55 -> #DIV/0! | M56: =(L56-L55)/L55 -> #DIV/0! | R56: =(Q56-Q55)/Q55 -> #DIV/0! | V56: =B56 -> 0 | W56: =G56 -> 0 | X56: =L56 -> 0 | Y56: =Q56 -> 0 | Z56: =SUM(V56:Y56) -> 0 | AB56: =C56 -> #DIV/0! | AC56: =H56 -> #DIV/0! | AD56: =M56 -> #DIV/0! | AE56: =R56 -> #DIV/0! | AF56: =D56 -> 0 | AG56: =I56 -> 0 | AH56: =N56 -> 0 | AI56: =S56 -> 0 | AJ56: =E56 -> 0 | AK56: =J56 -> 0 | AL56: =O56 -> 0 | AM56: =T56 -> 0 | AN56: =SUM(AJ56:AM56) -> 0 | AO56: =F56 -> 0 | AP56: =K56 -> 0 | AQ56: =P57 -> 0 | AR56: =U56 -> 0 | AS56: =SUM(AO56:AR56) -> 0
A57: 46195 | C57: =(B57-B56)/B56 -> #DIV/0! | H57: =(G57-G56)/G56 -> #DIV/0! | M57: =(L57-L56)/L56 -> #DIV/0! | R57: =(Q57-Q56)/Q56 -> #DIV/0! | V57: =B57 -> 0 | W57: =G57 -> 0 | X57: =L57 -> 0 | Y57: =Q57 -> 0 | Z57: =SUM(V57:Y57) -> 0 | AB57: =C57 -> #DIV/0! | AC57: =H57 -> #DIV/0! | AD57: =M57 -> #DIV/0! | AE57: =R57 -> #DIV/0! | AF57: =D57 -> 0 | AG57: =I57 -> 0 | AH57: =N57 -> 0 | AI57: =S57 -> 0 | AJ57: =E57 -> 0 | AK57: =J57 -> 0 | AL57: =O57 -> 0 | AM57: =T57 -> 0 | AN57: =SUM(AJ57:AM57) -> 0 | AO57: =F57 -> 0 | AP57: =K57 -> 0 | AQ57: =#REF! -> #REF! | AR57: =U57 -> 0 | AS57: =SUM(AO57:AR57) -> #REF!
A58: 46202 | C58: =(B58-B57)/B57 -> #DIV/0! | H58: =(G58-G57)/G57 -> #DIV/0! | M58: =(L58-L57)/L57 -> #DIV/0! | R58: =(Q58-Q57)/Q57 -> #DIV/0! | V58: =B58 -> 0 | W58: =G58 -> 0 | X58: =L58 -> 0 | Y58: =Q58 -> 0 | Z58: =SUM(V58:Y58) -> 0 | AB58: =C58 -> #DIV/0! | AC58: =H58 -> #DIV/0! | AD58: =M58 -> #DIV/0! | AE58: =R58 -> #DIV/0! | AF58: =D58 -> 0 | AG58: =I58 -> 0 | AH58: =N58 -> 0 | AI58: =S58 -> 0 | AJ58: =E58 -> 0 | AK58: =J58 -> 0 | AL58: =O58 -> 0 | AM58: =T58 -> 0 | AN58: =SUM(AJ58:AM58) -> 0 | AO58: =F58 -> 0 | AP58: =K58 -> 0 | AQ58: =#REF! -> #REF! | AR58: =U58 -> 0 | AS58: =SUM(AO58:AR58) -> #REF!
A59: 46209 | C59: =(B59-B58)/B58 -> #DIV/0! | H59: =(G59-G58)/G58 -> #DIV/0! | M59: =(L59-L58)/L58 -> #DIV/0! | R59: =(Q59-Q58)/Q58 -> #DIV/0! | V59: =B59 -> 0 | W59: =G59 -> 0 | X59: =L59 -> 0 | Y59: =Q59 -> 0 | Z59: =SUM(V59:Y59) -> 0 | AB59: =C59 -> #DIV/0! | AC59: =H59 -> #DIV/0! | AD59: =M59 -> #DIV/0! | AE59: =R59 -> #DIV/0! | AF59: =D59 -> 0 | AG59: =I59 -> 0 | AH59: =N59 -> 0 | AI59: =S59 -> 0 | AJ59: =E59 -> 0 | AK59: =J59 -> 0 | AL59: =O59 -> 0 | AM59: =T59 -> 0 | AN59: =SUM(AJ59:AM59) -> 0 | AO59: =F59 -> 0 | AP59: =K59 -> 0 | AQ59: =#REF! -> #REF! | AR59: =U59 -> 0 | AS59: =SUM(AO59:AR59) -> #REF!
Z60: =SUM(V60:Y60) -> 0 | AH60: =N60 -> 0 | AI60: =S60 -> 0 | AJ60: =E60 -> 0 | AK60: =J60 -> 0 | AL60: =O60 -> 0 | AM60: =T60 -> 0 | AN60: =SUM(AJ60:AM60) -> 0 | AO60: =F60 -> 0 | AP60: =K60 -> 0 | AQ60: =P60 -> 0 | AR60: =U60 -> 0 | AS60: =SUM(AO60:AR60) -> 0
Z61: =SUM(V61:Y61) -> 0 | AH61: =N61 -> 0 | AI61: =S61 -> 0 | AJ61: =E61 -> 0 | AK61: =J61 -> 0 | AL61: =O61 -> 0 | AM61: =T61 -> 0 | AN61: =SUM(AJ61:AM61) -> 0 | AO61: =F61 -> 0 | AP61: =K61 -> 0 | AQ61: =P61 -> 0 | AR61: =U61 -> 0 | AS61: =SUM(AO61:AR61) -> 0
Z62: =SUM(V62:Y62) -> 0 | AH62: =N62 -> 0 | AI62: =S62 -> 0 | AJ62: =E62 -> 0 | AK62: =J62 -> 0 | AL62: =O62 -> 0 | AM62: =T62 -> 0 | AN62: =SUM(AJ62:AM62) -> 0 | AO62: =F62 -> 0 | AP62: =K62 -> 0 | AQ62: =P62 -> 0 | AR62: =U62 -> 0 | AS62: =SUM(AO62:AR62) -> 0
Z63: =SUM(V63:Y63) -> 0 | AH63: =N63 -> 0 | AI63: =S63 -> 0 | AJ63: =E63 -> 0 | AK63: =J63 -> 0 | AL63: =O63 -> 0 | AM63: =T63 -> 0 | AN63: =SUM(AJ63:AM63) -> 0 | AO63: =F63 -> 0 | AP63: =K63 -> 0 | AQ63: =P63 -> 0 | AR63: =U63 -> 0 | AS63: =SUM(AO63:AR63) -> 0
Z64: =SUM(V64:Y64) -> 0 | AH64: =N64 -> 0 | AI64: =S64 -> 0 | AJ64: =E64 -> 0 | AK64: =J64 -> 0 | AL64: =O64 -> 0 | AM64: =T64 -> 0 | AN64: =SUM(AJ64:AM64) -> 0 | AO64: =F64 -> 0 | AP64: =K64 -> 0 | AQ64: =P64 -> 0 | AR64: =U64 -> 0 | AS64: =SUM(AO64:AR64) -> 0
Z65: =SUM(V65:Y65) -> 0 | AH65: =N65 -> 0 | AI65: =S65 -> 0 | AJ65: =E65 -> 0 | AK65: =J65 -> 0 | AL65: =O65 -> 0 | AM65: =T65 -> 0 | AN65: =SUM(AJ65:AM65) -> 0 | AO65: =F65 -> 0 | AP65: =K65 -> 0 | AQ65: =P65 -> 0 | AR65: =U65 -> 0 | AS65: =SUM(AO65:AR65) -> 0
Z66: =SUM(V66:Y66) -> 0 | AH66: =N66 -> 0 | AI66: =S66 -> 0 | AJ66: =E66 -> 0 | AK66: =J66 -> 0 | AL66: =O66 -> 0 | AM66: =T66 -> 0 | AN66: =SUM(AJ66:AM66) -> 0 | AO66: =F66 -> 0 | AP66: =K66 -> 0 | AQ66: =P66 -> 0 | AR66: =U66 -> 0 | AS66: =SUM(AO66:AR66) -> 0
Z67: =SUM(V67:Y67) -> 0 | AH67: =N67 -> 0 | AI67: =S67 -> 0 | AJ67: =E67 -> 0 | AK67: =J67 -> 0 | AL67: =O67 -> 0 | AM67: =T67 -> 0 | AN67: =SUM(AJ67:AM67) -> 0 | AO67: =F67 -> 0 | AP67: =K67 -> 0 | AQ67: =P67 -> 0 | AR67: =U67 -> 0 | AS67: =SUM(AO67:AR67) -> 0
Z68: =SUM(V68:Y68) -> 0 | AH68: =N68 -> 0 | AI68: =S68 -> 0 | AJ68: =E68 -> 0 | AK68: =J68 -> 0 | AL68: =O68 -> 0 | AM68: =T68 -> 0 | AN68: =SUM(AJ68:AM68) -> 0 | AO68: =F68 -> 0 | AP68: =K68 -> 0 | AQ68: =P68 -> 0 | AR68: =U68 -> 0 | AS68: =SUM(AO68:AR68) -> 0
Z69: =SUM(V69:Y69) -> 0 | AH69: =N69 -> 0 | AI69: =S69 -> 0 | AJ69: =E69 -> 0 | AK69: =J69 -> 0 | AL69: =O69 -> 0 | AM69: =T69 -> 0 | AN69: =SUM(AJ69:AM69) -> 0 | AO69: =F69 -> 0 | AP69: =K69 -> 0 | AQ69: =P69 -> 0 | AR69: =U69 -> 0 | AS69: =SUM(AO69:AR69) -> 0
Z70: =SUM(V70:Y70) -> 0 | AH70: =N70 -> 0 | AI70: =S70 -> 0 | AJ70: =E70 -> 0 | AK70: =J70 -> 0 | AL70: =O70 -> 0 | AM70: =T70 -> 0 | AN70: =SUM(AJ70:AM70) -> 0 | AO70: =F70 -> 0 | AP70: =K70 -> 0 | AQ70: =P70 -> 0 | AR70: =U70 -> 0 | AS70: =SUM(AO70:AR70) -> 0
Z71: =SUM(V71:Y71) -> 0 | AH71: =N71 -> 0 | AI71: =S71 -> 0 | AJ71: =E71 -> 0 | AK71: =J71 -> 0 | AL71: =O71 -> 0 | AM71: =T71 -> 0 | AN71: =SUM(AJ71:AM71) -> 0 | AO71: =F71 -> 0 | AP71: =K71 -> 0 | AQ71: =P71 -> 0 | AR71: =U71 -> 0 | AS71: =SUM(AO71:AR71) -> 0
... Z79: =SUM(V79:Y79) -> 0 | AH79: =N79 -> 0 | AI79: =S79 -> 0 | AJ79: =E79 -> 0 | AK79: =J79 -> 0 | AL79: =O79 -> 0 | AM79: =T79 -> 0 | AN79: =SUM(AJ79:AM79) -> 0 | AO79: =F79 -> 0 | AP79: =K79 -> 0 | AQ79: =P79 -> 0 | AR79: =U79 -> 0 | AS79: =SUM(AO79:AR79) -> 0
Z80: =SUM(V80:Y80) -> 0 | AH80: =N80 -> 0 | AI80: =S80 -> 0 | AJ80: =E80 -> 0 | AK80: =J80 -> 0 | AL80: =O80 -> 0 | AM80: =T80 -> 0 | AN80: =SUM(AJ80:AM80) -> 0 | AO80: =F80 -> 0 | AP80: =K80 -> 0 | AQ80: =P81 -> 0 | AR80: =U80 -> 0 | AS80: =SUM(AO80:AR80) -> 0
Z81: =SUM(V81:Y81) -> 0 | AH81: =N81 -> 0 | AI81: =S81 -> 0 | AJ81: =E81 -> 0 | AK81: =J81 -> 0 | AL81: =O81 -> 0 | AM81: =T81 -> 0 | AN81: =SUM(AJ81:AM81) -> 0 | AO81: =F81 -> 0 | AP81: =K81 -> 0 | AQ81: =#REF! -> #REF! | AR81: =U81 -> 0 | AS81: =SUM(AO81:AR81) -> #REF!
Z82: =SUM(V82:Y82) -> 0 | AH82: =N82 -> 0 | AI82: =S82 -> 0 | AJ82: =E82 -> 0 | AK82: =J82 -> 0 | AL82: =O82 -> 0 | AM82: =T82 -> 0 | AN82: =SUM(AJ82:AM82) -> 0 | AO82: =F82 -> 0 | AP82: =K82 -> 0 | AQ82: =P82 -> 0 | AR82: =U82 -> 0 | AS82: =SUM(AO82:AR82) -> 0
Z83: =SUM(V83:Y83) -> 0 | AH83: =N83 -> 0 | AI83: =S83 -> 0 | AJ83: =E83 -> 0 | AK83: =J83 -> 0 | AL83: =O83 -> 0 | AM83: =T83 -> 0 | AN83: =SUM(AJ83:AM83) -> 0 | AO83: =F83 -> 0 | AP83: =K83 -> 0 | AQ83: =P83 -> 0 | AR83: =U83 -> 0 | AS83: =SUM(AO83:AR83) -> 0
Z84: =SUM(V84:Y84) -> 0 | AH84: =N84 -> 0 | AI84: =S84 -> 0 | AJ84: =E84 -> 0 | AK84: =J84 -> 0 | AL84: =O84 -> 0 | AM84: =T84 -> 0 | AN84: =SUM(AJ84:AM84) -> 0 | AO84: =F84 -> 0 | AP84: =K84 -> 0 | AQ84: =P84 -> 0 | AR84: =U84 -> 0 | AS84: =SUM(AO84:AR84) -> 0
Z85: =SUM(V85:Y85) -> 0 | AH85: =N85 -> 0 | AI85: =S85 -> 0 | AJ85: =E85 -> 0 | AK85: =J85 -> 0 | AL85: =O85 -> 0 | AM85: =T85 -> 0 | AN85: =SUM(AJ85:AM85) -> 0 | AO85: =F85 -> 0 | AP85: =K85 -> 0 | AQ85: =P85 -> 0 | AR85: =U85 -> 0 | AS85: =SUM(AO85:AR85) -> 0
Z86: =SUM(V86:Y86) -> 0 | AH86: =N86 -> 0 | AI86: =S86 -> 0 | AJ86: =E86 -> 0 | AK86: =J86 -> 0 | AL86: =O86 -> 0 | AM86: =T86 -> 0 | AN86: =SUM(AJ86:AM86) -> 0 | AO86: =F86 -> 0 | AP86: =K86 -> 0 | AQ86: =P86 -> 0 | AR86: =U86 -> 0 | AS86: =SUM(AO86:AR86) -> 0
Z87: =SUM(V87:Y87) -> 0 | AH87: =N87 -> 0 | AI87: =S87 -> 0 | AJ87: =E87 -> 0 | AK87: =J87 -> 0 | AL87: =O87 -> 0 | AM87: =T87 -> 0 | AN87: =SUM(AJ87:AM87) -> 0 | AO87: =F87 -> 0 | AP87: =K87 -> 0 | AQ87: =P87 -> 0 | AR87: =U87 -> 0 | AS87: =SUM(AO87:AR87) -> 0

Sheet Organic Social (Monthly)
A1: Organic Social
B2: LinkedIn | C2: Instagram | D2: Facebook | E2: X | F2: TOTAL | G2: LinkedIn | H2: Instagram | I2: Facebook | J2: X | K2: TOTAL | L2: LinkedIn | M2: Instagram | N2: Facebook | O2: X | P2: TOTAL
A3: Notes >
A4: Month | B4: Impressions | C4: Impressions | D4: Impressions | E4: Impressions | F4: Impressions | G4: Followers | H4: Followers | I4: Followers | J4: Followers | K4: Followers | L4: Engagements | M4: Engagements | N4: Engagements | O4: Engagements | P4: Engagements
A5: 45658 | F5: =SUM(B5:E5) -> 0 | K5: =SUM(G5+H5+I5+J5) -> 0 | P5: =SUM(L5:O5) -> 0
A6: 45689 | F6: =SUM(B6:E6) -> 0 | K6: =SUM(G6+H6+I6+J6) -> 0 | P6: =SUM(L6:O6) -> 0
A7: 45717 | F7: =SUM(B7:E7) -> 0 | K7: =SUM(G7+H7+I7+J7) -> 0 | P7: =SUM(L7:O7) -> 0
A8: 45748 | F8: =SUM(B8:E8) -> 0 | K8: =SUM(G8+H8+I8+J8) -> 0 | P8: =SUM(L8:O8) -> 0
A9: 45778 | F9: =SUM(B9:E9) -> 0 | K9: =SUM(G9+H9+I9+J9) -> 0 | P9: =SUM(L9:O9) -> 0
A10: 45809 | B10: 882 | C10: 428 | D10: 697 | E10: 1248 | F10: =SUM(B10:E10) -> 3255 | G10: 1490 | H10: 922 | I10: 2309 | J10: 5626 | K10: =SUM(G10+H10+I10+J10) -> 10347 | L10: 27 | M10: 15 | N10: 24 | O10: 28 | P10: =SUM(L10:O10) -> 94
A11: 45839 | B11: 2174 | C11: 1316 | D11: 356 | E11: 1965 | F11: =SUM(B11:E11) -> 5811 | G11: 1491 | H11: 925 | I11: 2304 | J11: 5639 | K11: =SUM(G11+H11+I11+J11) -> 10359 | L11: 39 | M11: 35 | N11: 5 | O11: 52 | P11: =SUM(L11:O11) -> 131
A12: 45870 | B12: 2041 | C12: 3626 | D12: 1100 | E12: 3108 | F12: =SUM(B12:E12) -> 9875 | G12: 1506 | H12: 941 | I12: 2300 | J12: 5665 | K12: =SUM(G12+H12+I12+J12) -> 10412 | L12: 119 | M12: 65 | N12: 63 | O12: 195 | P12: =SUM(L12:O12) -> 442
A13: 45901 | B13: 863 | C13: 1835 | D13: 273 | E13: 2599 | F13: =SUM(B13:E13) -> 5570 | G13: 1516 | H13: 942 | I13: 2306 | J13: 5679 | K13: =SUM(G13+H13+I13+J13) -> 10443 | L13: 26 | M13: 11 | N13: 7 | O13: 61 | P13: =SUM(L13:O13) -> 105
A14: 45931 | B14: 1174 | C14: 3915 | D14: 212 | E14: 1753 | F14: =SUM(B14:E14) -> 7054 | G14: 1520 | H14: 959 | I14: 2307 | J14: 5678 | K14: =SUM(G14+H14+I14+J14) -> 10464 | L14: 35 | M14: 27 | N14: 11 | O14: 54 | P14: =SUM(L14:O14) -> 127
A15: 45962 | B15: 2395 | C15: 4323 | D15: 299 | E15: 1848 | F15: =SUM(B15:E15) -> 8865 | G15: 1538 | H15: 972 | I15: 2309 | J15: 5675 | K15: =SUM(G15+H15+I15+J15) -> 10494 | L15: 46 | M15: 26 | N15: 8 | O15: 46 | P15: =SUM(L15:O15) -> 126
A16: 45992 | B16: 1924 | C16: 2034 | D16: 369 | E16: 1012 | F16: =SUM(B16:E16) -> 5339 | G16: 1565 | H16: 981 | I16: 2306 | J16: 5680 | K16: =SUM(G16+H16+I16+J16) -> 10532 | L16: 68 | M16: 32 | N16: 10 | O16: 39 | P16: =SUM(L16:O16) -> 149
A17: 46023 | B17: 1214 | C17: 838 | D17: 424 | E17: 1061 | F17: =SUM(B17:E17) -> 3537 | G17: 1575 | H17: 987 | I17: 2315 | J17: 5682 | K17: =SUM(G17+H17+I17+J17) -> 10559 | L17: 37 | M17: 9 | N17: 4 | O17: 45 | P17: =SUM(L17:O17) -> 95
A18: 46054 | B18: 2040 | C18: 2713 | D18: 1286 | E18: 1706 | F18: =SUM(B18:E18) -> 7745 | G18: 1596 | H18: 1015 | I18: 2340 | J18: 5702 | K18: =SUM(G18+H18+I18+J18) -> 10653 | L18: 145 | M18: 84 | N18: 16 | O18: 86 | P18: =SUM(L18:O18) -> 331
A19: 46082 | B19: 1573 | C19: 1976 | D19: 1681 | E19: 1709 | F19: =SUM(B19:E19) -> 6939 | G19: 1624 | H19: 1068 | I19: 2365 | J19: 5704 | K19: =SUM(G19+H19+I19+J19) -> 10761 | L19: 122 | M19: 25 | N19: 15 | O19: 58 | P19: =SUM(L19:O19) -> 220
A20: 46113 | B20: 4534 | C20: 1703 | D20: 1057 | E20: 3337 | F20: =SUM(B20:E20) -> 10631 | G20: 1677 | H20: 1103 | I20: 2388 | J20: 5710 | K20: =SUM(G20+H20+I20+J20) -> 10878 | L20: 367 | M20: 28 | N20: 20 | O20: 168 | P20: =SUM(L20:O20) -> 583
A21: 46143 | B21: 5163 | C21: 2249 | D21: 1766 | E21: 3007 | F21: =SUM(B21:E21) -> 12185 | G21: 1726 | H21: 1126 | I21: 2422 | J21: 5717 | K21: =SUM(G21+H21+I21+J21) -> 10991 | L21: 193 | M21: 45 | N21: 34 | O21: 70 | P21: =SUM(L21:O21) -> 342
A22: 46174 | K22: =SUM(G22+H22+I22+J22) -> 0 | P22: =SUM(L22:O22) -> 0
A23: 46204 | K23: =SUM(G23+H23+I23+J23) -> 0 | P23: =SUM(L23:O23) -> 0
A24: 46235 | K24: =SUM(G24+H24+I24+J24) -> 0 | P24: =SUM(L24:O24) -> 0
K25: =SUM(G25+H25+I25+J25) -> 0 | P25: =SUM(L25:O25) -> 0
K26: =SUM(G26+H26+I26+J26) -> 0 | P26: =SUM(L26:O26) -> 0
P27: =SUM(L27:O27) -> 0
P28: =SUM(L28:O28) -> 0
P29: =SUM(L29:O29) -> 0
P30: =SUM(L30:O30) -> 0
A49: TOTALS | B49: =#REF!/#REF! -> #REF! | E49: =#REF!/#REF! -> #REF! | F49: =SUM(F5:F46) -> 86806 | G49: =#REF!/#REF! -> #REF! | J49: =#REF!/#REF! -> #REF! | K49: =SUM(K5:K46) -> 126893 | L49: =#REF!/#REF! -> #REF! | O49: =#REF!/#REF! -> #REF! | P49: =SUM(P5:P46) -> 2745
A50: BUDGET | K50: 160 | P50: 160
A51: REMAINING | F51: =F50-F49 -> -86806 | K51: =K50-K49 -> -126733 | P51: =P50-P49 -> -2585

Sheet Website (Weekly)
A1: Website
H2: New User Primary Channel
A3: Notes > | B3: New Users | C3: %change | D3: Total Users | E3: Returning Users | G3: Avg Engagement Time Per Active User (seconds) | H3: Referral | I3: Organic Search | J3: Direct | K3: Organic Social | L3: Email | M3: Unassigned | N3: Paid Social | O3: Paid Search
A4: Week Starting
A5: 2024 Average
A6: 45901 | C6: =(B6-#REF!)/#REF! -> #REF! | F6: =(E6-#REF!)/#REF! -> #REF!
A7: 45908 | C7: =(B7-B6)/B6 -> #DIV/0! | F7: =(E7-E6)/E6 -> #DIV/0!
A8: 45915 | C8: =(B8-B7)/B7 -> #DIV/0! | F8: =(E8-E7)/E7 -> #DIV/0!
A9: 45922 | C9: =(B9-B8)/B8 -> #DIV/0! | F9: =(E9-E8)/E8 -> #DIV/0!
A10: 45929 | B10: 2099 | C10: =(B10-B9)/B9 -> #DIV/0! | D10: 2338 | E10: 235 | F10: =(E10-E9)/E9 -> #DIV/0! | G10: 22 | H10: 78 | I10: 374 | J10: 1419 | K10: 2 | L10: 224 | M10: 2
A11: 45936 | B11: 2453 | C11: =(B11-B10)/B10 -> 0.16865174 | D11: 2735 | E11: 281 | F11: =(E11-E10)/E10 -> 0.19574468 | G11: 22 | H11: 89 | I11: 361 | J11: 1627 | K11: 8 | L11: 356 | M11: 12
A12: 45943 | B12: 4602 | C12: =(B12-B11)/B11 -> 0.87607012 | D12: 4869 | E12: 318 | F12: =(E12-E11)/E11 -> 0.1316726 | G12: 22 | H12: 103 | I12: 430 | J12: 1857 | K12: 8 | L12: 2195 | M12: 9
A13: 45950 | B13: 1592 | C13: =(B13-B12)/B12 -> -0.65406345 | D13: 1914 | E13: 391 | F13: =(E13-E12)/E12 -> 0.22955975 | G13: 62 | H13: 98 | I13: 528 | J13: 583 | K13: 16 | L13: 358 | M13: 6
A14: 45957 | B14: 1307 | C14: =(B14-B13)/B13 -> -0.1790201 | D14: 1703 | E14: 498 | F14: =(E14-E13)/E13 -> 0.27365729 | G14: 96 | H14: 87 | I14: 644 | J14: 453 | K14: 15 | L14: 78 | M14: 30
A15: 45964 | B15: 2636 | C15: =(B15-B14)/B14 -> 1.0168324 | D15: 2010 | E15: 911 | F15: =(E15-E14)/E14 -> 0.82931727 | G15: 209 | H15: 119 | I15: 877 | J15: 827 | K15: 2 | L15: 165 | M15: 18
A16: 45971 | B16: 4420 | C16: =(B16-B15)/B15 -> 0.676783 | D16: 5876 | E16: 2549 | F16: =(E16-E15)/E15 -> 1.7980241 | G16: 490 | H16: 180 | I16: 1633 | J16: 2184 | K16: 6 | L16: 398 | M16: 19
A17: 45978 | B17: 2554 | C17: =(B17-B16)/B16 -> -0.42217195 | D17: 4055 | E17: 1844 | F17: =(E17-E16)/E16 -> -0.27657905 | G17: 491 | H17: 140 | I17: 955 | J17: 1079 | K17: 6 | L17: 361 | M17: 13
A18: 45985 | B18: 860 | C18: =(B18-B17)/B17 -> -0.6632733 | D18: 1326 | E18: 382 | F18: =(E18-E17)/E17 -> -0.79284165 | G18: 49 | H18: 86 | I18: 305 | J18: 435 | K18: 9 | L18: 6 | M18: 17
A19: 45992 | B19: 1103 | C19: =(B19-B18)/B18 -> 0.28255814 | D19: 1481 | E19: 392 | F19: =(E19-E18)/E18 -> 0.02617801 | G19: 38 | H19: 88 | I19: 384 | J19: 337 | K19: 8 | L19: 278 | M19: 8
A20: 45999 | B20: 818 | C20: =(B20-B19)/B19 -> -0.25838622 | D20: 1171 | E20: 349 | F20: =(E20-E19)/E19 -> -0.10969388 | G20: 41 | H20: 88 | I20: 369 | J20: 348 | K20: 5 | L20: 3 | M20: 5
A21: 46006 | B21: 1319 | C21: =(B21-B20)/B20 -> 0.61246944 | D21: 1629 | E21: 330 | F21: =(E21-E20)/E20 -> -0.054441261 | G21: 31 | H21: 108 | I21: 310 | J21: 382 | K21: 12 | L21: 423 | M21: 6
... A27: 46048 | B27: 3584 | C27: =(B27-B26)/B26 -> 0.83606557 | D27: 4123 | E27: 916 | F27: =(E27-E26)/E26 -> 0.86558045 | G27: 58 | H27: 166 | I27: 756 | J27: 659 | K27: 25 | L27: 991 | M27: 6
A28: 46055 | B28: 4067 | C28: =(B28-B27)/B27 -> 0.13476562 | D28: 4807 | E28: 938 | F28: =(E28-E27)/E27 -> 0.024017467 | G28: 72 | H28: 157 | I28: 505 | J28: 752 | K28: 17 | L28: 1488 | M28: 38 | N28: 565 | O28: 514
A29: 46062 | B29: 3554 | C29: =(B29-B28)/B28 -> -0.1261372 | D29: 4365 | E29: 941 | F29: =(E29-E28)/E28 -> 0.0031982942 | G29: 80 | H29: 144 | I29: 552 | J29: 634 | K29: 12 | L29: 1411 | M29: 17 | N29: 398 | O29: 382
A30: 46069 | B30: 3854 | C30: =(B30-B29)/B29 -> 0.08441193 | D30: 5093 | E30: 1640 | F30: =(E30-E29)/E29 -> 0.74282678 | G30: 69 | H30: 265 | I30: 866 | J30: 1198 | K30: 22 | L30: 530 | M30: 9 | N30: 492 | O30: 461
A31: 46076 | B31: 3242 | C31: =(B31-B30)/B30 -> -0.15879606 | D31: 4389 | E31: 1413 | F31: =(E31-E30)/E30 -> -0.13841463 | G31: 88 | H31: 276 | I31: 661 | J31: 1010 | K31: 19 | L31: 478 | M31: 9 | N31: 356 | O31: 425
A32: 46083 | B32: 4418 | C32: =(B32-B31)/B31 -> 0.36273905 | D32: 5736 | E32: 1692 | F32: =(E32-E31)/E31 -> 0.19745223 | G32: 132 | H32: 285 | I32: 709 | J32: 1751 | K32: 33 | L32: 754 | M32: 11 | N32: 329 | O32: 537
A33: 46090 | B33: 2291 | C33: =(B33-B32)/B32 -> -0.48143957 | D33: 3277 | E33: 1035 | F33: =(E33-E32)/E32 -> -0.38829787 | G33: 66 | H33: 145 | I33: 394 | J33: 838 | K33: 12 | L33: 70 | M33: 8 | N33: 246 | O33: 553
A34: 46097 | B34: 2574 | C34: =(B34-B33)/B33 -> 0.12352684 | D34: 3474 | E34: 960 | F34: =(E34-E33)/E33 -> -0.072463768 | G34: 57 | H34: 197 | I34: 334 | J34: 798 | K34: 8 | L34: 365 | M34: 22 | N34: 299 | O34: 544
A35: 46104 | B35: 2099 | C35: =(B35-B34)/B34 -> -0.18453768 | D35: 2985 | E35: 982 | F35: =(E35-E34)/E34 -> 0.022916667 | G35: 62 | H35: 229 | I35: 432 | J35: 616 | K35: 14 | L35: 89 | M35: 20 | N35: 276 | O35: 417
A36: 46111 | B36: 3588 | C36: =(B36-B35)/B35 -> 0.70938542 | D36: 4440 | E36: 966 | F36: =(E36-E35)/E35 -> -0.016293279 | G36: 46 | H36: 195 | I36: 393 | J36: 554 | K36: 12 | L36: 1692 | M36: 20 | N36: 242 | O36: 472
A37: 46118 | B37: 2097 | C37: =(B37-B36)/B36 -> -0.41555184 | D37: 2919 | E37: 906 | F37: =(E37-E36)/E36 -> -0.062111801 | G37: 76 | H37: 144 | I37: 394 | J37: 548 | K37: 15 | L37: 124 | M37: 19 | N37: 293 | O37: 553
A38: 46125 | B38: 3155 | C38: =(B38-B37)/B37 -> 0.50453028 | D38: 4067 | E38: 1103 | F38: =(E38-E37)/E37 -> 0.21743929 | G38: 66 | H38: 159 | I38: 522 | J38: 838 | K38: 29 | L38: 748 | M38: 16 | N38: 215 | O38: 623
A39: 46132 | B39: 4630 | C39: =(B39-B38)/B38 -> 0.46751189 | D39: 5591 | E39: 1148 | F39: =(E39-E38)/E38 -> 0.040797824 | G39: 52 | H39: 209 | I39: 530 | J39: 891 | K39: 15 | L39: 2128 | M39: 5 | N39: 217 | O39: 615
... A46: 46181 | B46: 6233 | C46: =(B46-B45)/B45 -> -0.052303482 | D46: 8066 | E46: 2191 | F46: =(E46-E45)/E45 -> 0.14472309 | G46: 73 | H46: 211 | I46: 759 | J46: 1369 | K46: 53 | L46: 666 | M46: 24 | N46: 62 | O46: 3026
A47: 46188 | C47: =(B47-B46)/B46 -> -1 | F47: =(E47-E46)/E46 -> -1
A48: 46195 | C48: =(B48-B47)/B47 -> #DIV/0! | F48: =(E48-E47)/E47 -> #DIV/0!
A49: 46202 | C49: =(B49-B48)/B48 -> #DIV/0! | F49: =(E49-E48)/E48 -> #DIV/0!
A50: 46209 | C50: =(B50-B49)/B49 -> #DIV/0! | F50: =(E50-E49)/E49 -> #DIV/0!

Sheet Website (Monthly)
A1: Website
B2: Avg Engagement Time Per Session | C2: Avg Users
A3: Notes > | B3: Time on entire site | C3: New Website Users | D3: Total Website Users | E3: % new users
A4: Month
A5: 2024 Average | E5: 0.98192845
A6: January | E6: =C6/D6 -> #DIV/0!
A7: February | E7: =C7/D7 -> #DIV/0!
A8: March | E8: =C8/D8 -> #DIV/0!
A9: April | E9: =C9/D9 -> #DIV/0!
A10: May | E10: =C10/D10 -> #DIV/0!
A11: June | B11: 19 | C11: 4446 | D11: 4560 | E11: =C11/D11 -> 0.975
A12: July | B12: 16 | C12: 5587 | D12: 5820 | E12: =C12/D12 -> 0.95996564
A13: August | B13: 48 | C13: 7313 | D13: 7662 | E13: =C13/D13 -> 0.95445054
A14: September | B14: 20 | C14: 5370 | D14: 5820 | E14: =C14/D14 -> 0.92268041
A15: October | B15: 29 | C15: 10990 | D15: 11550 | E15: =C15/D15 -> 0.95151515
A16: November | B16: 191 | C16: 10095 | D16: 11542 | E16: =C16/D16 -> 0.87463178
A17: December | B17: 27 | C17: 4105 | D17: 4965 | E17: =C17/D17 -> 0.82678751
A18: January | B18: 37 | C18: 10801 | D18: 11747 | E18: =C18/D18 -> 0.9194688
A19: February | B19: 53 | C19: 14750 | D19: 16596 | E19: =C19/D19 -> 0.88876838
A20: March | B20: 54 | C20: 12555 | D20: 14968 | E20: =C20/D20 -> 0.83878942
A21: April | B21: 64 | C21: 16955 | D21: 19017 | E21: =C21/D21 -> 0.8915707
A22: May | B22: 39 | C22: 26735 | D22: 28853 | E22: =C22/D22 -> 0.92659342
E23: =C23/D23 -> #DIV/0!
E24: =C24/D24 -> #DIV/0!
E25: =C25/D25 -> #DIV/0!

Sheet Website (Monthly by Channel)
A1: Website
B2: Avg Engagement Time Per Session | N2: New Users | Z2: Total Users
A3: Notes > | B3: Paid LinkedIn | C3: Paid Facebook | D3: Paid Search | E3: Organic Twitter | F3: Organic Instagram | G3: Organic LinkedIn | H3: Organic Facebook | I3: Organic Search | J3: Direct | K3: Referral | L3: Display | M3: Email | N3: Paid LinkedIn | O3: Paid Facebook | P3: Paid Search | Q3: Organic Twitter | R3: Organic Instagram | S3: Organic LinkedIn | T3: Organic Facebook | U3: Organic Search | V3: Direct | W3: Referral | X3: Display | Y3: Email | Z3: Paid LinkedIn | AA3: Paid Facebook | AB3: Paid Search | AC3: Organic Twitter | AD3: Organic Instagram | AE3: Organic LinkedIn | AF3: Organic Facebook | AG3: Organic Search | AH3: Direct | AI3: Referral | AJ3: Display | AK3: Email
A4: Month
A5: 2024 Average
A6: January
A7: February
A8: March
A9: April
A10: May
A11: June
A12: July
A13: August
A14: September | B14: - | C14: - | D14: - | E14: 0 | F14: 4 | G14: 1 | H14: 18 | I14: 27 | J14: 17 | K14: 34 | L14: - | M14: 10 | N14: - | O14: - | P14: - | S14: 6 | T14: 5 | U14: =1017+166+9 -> 1192 | V14: 2570 | W14: =216+72+12+9+4+6+4 -> 323 | X14: - | Y14: 1187 | Z14: - | AA14: - | AB14: - | AE14: 5 | AF14: 5 | AG14: =216+1175+12 -> 1403 | AH14: 2705 | AI14: =268+85+15+9+5+6+4 -> 392 | AJ14: - | AK14: 1216
A15: October | B15: - | C15: - | D15: - | E15: 0 | F15: 67 | G15: 17 | H15: 0 | I15: 35 | J15: 35 | K15: 53 | L15: - | M15: 9 | N15: - | O15: - | P15: - | Q15: 7 | R15: 4 | S15: 8 | T15: 6 | U15: =1738+267+36+17+8+8 -> 2074 | V15: 5370 | W15: =263+81+13+13+6 -> 376 | X15: - | Y15: 3005 | Z15: - | AA15: - | AB15: - | AC15: 7 | AD15: 4 | AE15: 9 | AF15: 6 | AG15: =1942+327+40+37+19+18+18 -> 2401 | AH15: 5414 | AI15: =294+87+87+15+12 -> 495 | AJ15: - | AK15: 3032
A16: November | B16: - | C16: - | D16: - | E16: 0 | F16: 41 | G16: 0 | H16: 12 | I16: 27 | J16: 421 | K16: 102 | L16: - | M16: 12 | N16: - | O16: - | P16: - | Q16: 1 | R16: 4 | S16: 6 | T16: 4 | U16: 3340 | V16: 4626 | W16: =278+169+33 -> 480 | Y16: 932 | Z16: - | AA16: - | AB16: - | AC16: 1 | AD16: 4 | AE16: 6 | AF16: 4 | AG16: 3982 | AH16: 5017 | AI16: =406+214+41 -> 661 | AJ16: - | AK16: 1032
A17: December | B17: - | C17: - | D17: - | E17: 0 | F17: 2 | G17: 10 | H17: 0 | I17: 36 | J17: 16 | K17: 45 | L17: - | M17: 16 | N17: - | O17: - | P17: - | Q17: 3 | R17: 5 | S17: 6 | T17: 15 | U17: =1186+168+17 -> 1371 | V17: 1439 | W17: =165+166 -> 331 | X17: - | Y17: 727 | Z17: - | AA17: - | AC17: 3 | AD17: 5 | AE17: 8 | AF17: 15 | AG17: =1574+241+19 -> 1834 | AH17: 1674 | AI17: =226+190 -> 416 | AJ17: - | AK17: 775
A18: January | B18: 0 | C18: 3 | D18: 33 | E18: 0 | F18: 2 | G18: 29 | H18: 155 | I18: 40 | J18: 43 | K18: 79 | L18: 0 | M18: 20 | N18: 276 | O18: 345 | P18: =156+46 -> 202 | Q18: 1 | R18: 4 | S18: 10 | T18: 11 | U18: =2623+292 -> 2915 | V18: 2486 | W18: =263+273+177 -> 713 | X18: 17 | Y18: =3414+143 -> 3557 | Z18: 277 | AA18: 345 | AB18: =158+46 -> 204 | AC18: 1 | AD18: 4 | AE18: 10 | AF18: 11 | AG18: =2965+373 -> 3338 | AH18: 2596 | AI18: =304+285+179 -> 768 | AJ18: 17 | AK18: =3457+143 -> 3600
A19: February | N19: 832 | O19: 1045 | P19: =1055+695 -> 1750 | Q19: 4 | R19: 18 | S19: 9 | T19: 5 | U19: =2110+385+47 -> 2542 | V19: 3563 | W19: 743 | X19: 36 | Y19: 3892 | Z19: 842 | AA19: 1057 | AB19: 1969 | AC19: 4 | AD19: 19 | AE19: 13 | AF19: 28 | AG19: 3752 | AH19: 4086 | AI19: 1379 | AJ19: 36 | AK19: 4123

Sheet PR DATA
B2: LINK TO FULL PR DASHBOARD | E2: ATC 2026 PR Tracker.xlsx

Sheet Paid Media
A1: Paid Media
B2: LinkedIn (LI) | J2: Meta | R2: Google Search | Z2: Google Display | AH2: Totals
A3: Notes > | B3: Times someone sees our ads | C3: Times someone clicks our ads | D3: Amount spent on ads for this channel | E3: Cost divided by Clicks | F3: Clicks divided by Impressions | G3: Registrations attributed to ads on this channel | H3: Conversions divided by clicks | I3: Cost divided by Conversions | J3: Times someone sees our ads | K3: Times someone clicks our ads | L3: Amount spent on ads for this channel | M3: Cost divided by Clicks | N3: Clicks divided by Impressions | O3: Registrations attributed to ads on this channel | P3: Conversions divided by clicks | Q3: Cost divided by Conversions | R3: Times someone sees our ads | S3: Times someone clicks our ads | T3: Amount spent on ads for this channel | U3: Cost divided by Clicks | V3: Clicks divided by Impressions | W3: Registrations attributed to ads on this channel | X3: Conversions divided by clicks | Y3: Cost divided by Conversions | Z3: Times someone sees our ads | AA3: Times someone clicks our ads | AB3: Amount spent on ads for this channel | AC3: Cost divided by Clicks | AD3: Clicks divided by Impressions | AE3: Registrations attributed to ads on this channel | AF3: Conversions divided by clicks | AG3: Cost divided by Conversions | AH3: Times someone sees our ads | AI3: Times someone clicks our ads | AJ3: Amount spent on ads for this channel | AK3: Cost divided by Clicks | AL3: Clicks divided by Impressions | AM3: Registrations attributed to ads on this channel | AN3: Conversions divided by clicks | AO3: Cost divided by Conversions
A4: Week Starting | B4: LI Impressions | C4: LI Clicks | D4: LI Cost | E4: LI Cost Per Click | F4: LI Click-Through-Rate | G4: LI Registrations | H4: LI Conversion Rate | I4: LI Cost Per Acquisition | J4: FB Impressions | K4: FB Clicks | L4: FB Cost | M4: FB Cost Per Click | N4: FB Click-Through-Rate | O4: FB Registrations | P4: FB Conversion Rate | Q4: FB Cost Per Acquisition | R4: GS Impressions | S4: GS Clicks | T4: GS Cost | U4: GS Cost Per Click | V4: GS Click-Through-Rate | W4: GS Registrations | X4: GS Conversion Rate | Y4: GS Cost Per Acquisition | Z4: GD Impressions | AA4: GD Clicks | AB4: GD Cost | AC4: GD Cost Per Click | AD4: GD Click-Through-Rate | AE4: GD Registrations | AF4: GD Conversion Rate | AG4: GD Cost Per Acquisition | AH4: Impressions | AI4: Clicks | AJ4: Total Cost | AK4: Avg Cost Per Click | AL4: Avg Click-Through-Rate | AM4: Registrations | AN4: Conversion Rate | AO4: Cost Per Acquisition
A5: 46027
A6: 46034
A7: 46041
A8: 46048 | B8: 13775 | C8: 127 | D8: 70 | E8: 0.55 | F8: 0.0092 | G8: 0 | H8: 0 | I8: 0 | J8: =11732+3119+2598 -> 17449 | K8: =229+52+26 -> 307 | L8: =150.97+38.44+40.23 -> 229.64 | M8: 0.98 | N8: 0.0154 | O8: 4 | P8: =4/307 -> 0.013029316 | Q8: =229.64/4 -> 57.41 | R8: 1612 | S8: 286 | T8: 176.33 | U8: 0.62 | V8: 0.1774 | W8: 0 | X8: 0 | Y8: 0 | Z8: 8657 | AA8: 76 | AB8: 27.86 | AC8: 0.37 | AD8: 0.0088 | AE8: 0 | AF8: 0 | AG8: 0 | AH8: =SUM(B8+J8+R8+Z8) -> 41493 | AI8: =SUM(C8+K8+S8+AA8) -> 796 | AJ8: =SUM(AB8+T8+L8+D8) -> 503.83 | AM8: =SUM(AE8+W8+O8+G8) -> 4 | AN8: =AM8/AH8 -> 9.6401803e-05 | AO8: =AJ8/AM8 -> 125.9575
A9: 46055 | B9: 28025 | C9: 212 | D9: 78.22 | E9: 0.37 | F9: 0.0076 | G9: 0 | H9: =G9/C9 -> 0 | J9: 24522 | K9: 266 | L9: 318.55 | M9: 1.2 | N9: 0.0108 | O9: 1 | R9: 2657 | S9: 707 | T9: 233.01 | U9: 0.33 | V9: 0.2661 | W9: 6 | Z9: 27335 | AA9: 479 | AB9: 127.96 | AC9: 0.27 | AD9: 0.0075 | AH9: =SUM(B9+J9+R9+Z9) -> 82539 | AI9: =SUM(C9+K9+S9+AA9) -> 1664 | AJ9: =SUM(AB9+T9+L9+D9) -> 757.74 | AM9: =SUM(AE9+W9+O9+G9) -> 7 | AN9: =AM9/AH9 -> 8.4808394e-05 | AO9: =AJ9/AM9 -> 108.24857
A10: 46062 | B10: 14952 | C10: 117 | D10: 79.58 | E10: 0.69 | F10: 0.0078 | G10: 0 | H10: =G10/C10 -> 0 | J10: 10334 | K10: 273 | L10: 320.82 | M10: 1.18 | N10: 0.0102 | O10: 11 | R10: 2538 | S10: 493 | T10: 172.12 | U10: 0.7 | V10: 0.1942 | W10: 2 | X10: 0.0041 | Y10: 172.12 | Z10: 24762 | AA10: 348 | AB10: 104.86 | AC10: 0.3 | AD10: 0.0141 | AE10: 0 | AF10: 0 | AG10: 0 | AH10: =SUM(B10+J10+R10+Z10) -> 52586 | AI10: =SUM(C10+K10+S10+AA10) -> 1231 | AJ10: =SUM(AB10+T10+L10+D10) -> 677.38 | AM10: =SUM(AE10+W10+O10+G10) -> 13 | AN10: =AM10/AH10 -> 0.00024721409 | AO10: =AJ10/AM10 -> 52.106154
A11: 46069 | B11: 12668 | C11: 101 | D11: 73.44 | E11: 0.73 | F11: 0.008 | G11: 0 | H11: =G11/C11 -> 0 | J11: 12332 | K11: 395 | L11: 324.18 | M11: 0.82 | N11: 0.0133 | O11: 11 | P11: =11/395 -> 0.027848101 | Q11: =324.18/11 -> 29.470909 | R11: 1434 | S11: 754 | T11: 177.74 | U11: 0.24 | V11: =754/1434 -> 0.52580195 | W11: 30 | X11: 0.0409 | Y11: 5.76 | Z11: 24725 | AA11: 459 | AB11: 110.35 | AC11: 0.24 | AD11: 0.0065 | AE11: 3 | AF11: 0.0065 | AG11: 36.78 | AH11: =SUM(B11+J11+R11+Z11) -> 51159 | AI11: =SUM(C11+K11+S11+AA11) -> 1709 | AJ11: =SUM(AB11+T11+L11+D11) -> 685.71 | AM11: =SUM(AE11+W11+O11+G11) -> 44 | AN11: =AM11/AH11 -> 0.00086006372 | AO11: =AJ11/AM11 -> 15.584318
A12: 46076 | B12: 8183 | C12: 87 | D12: 35.11 | E12: 0.4 | F12: 0.0106 | H12: =G12/C12 -> 0 | J12: 33118 | K12: 270 | L12: 311.72 | M12: 1.15 | N12: 0.0172 | O12: 22 | P12: =22/270 -> 0.081481481 | Q12: 14.47 | R12: 1489 | S12: 756 | T12: 160.58 | U12: 0.21 | V12: 0.5077 | W12: 79 | X12: 0.1047 | Y12: 2.03 | Z12: 22815 | AA12: 402 | AB12: 94.15 | AC12: 0.23 | AD12: 0.0176 | AE12: 1 | AF12: 0.0025 | AG12: 94.15 | AH12: =SUM(B12+J12+R12+Z12) -> 65605 | AI12: =SUM(C12+K12+S12+AA12) -> 1515 | AJ12: =SUM(AB12+T12+L12+D12) -> 601.56 | AM12: =SUM(AE12+W12+O12+G12) -> 102 | AN12: =AM12/AH12 -> 0.0015547595 | AO12: =AJ12/AM12 -> 5.8976471
A13: 46083 | B13: 454 | C13: 4 | D13: 19.67 | E13: 4.92 | F13: 0.0088 | G13: 0 | H13: =G13/C13 -> 0 | J13: 38838 | K13: 195 | L13: 307.73 | M13: 1.58 | N13: 0.005 | O13: 72 | P13: =72/307 -> 0.23452769 | Q13: 4.27 | R13: 1880 | S13: 949 | T13: 228.1 | U13: 0.24 | V13: 0.5048 | W13: 200.92 | X13: 0.2117 | Y13: 1.14 | Z13: 26990 | AA13: 273 | AB13: 99.1 | AC13: 0.36 | AD13: 0.0101 | AE13: 9 | AF13: 0.0189 | AG13: 11.01 | AH13: =SUM(B13+J13+R13+Z13) -> 68162 | AI13: =SUM(C13+K13+S13+AA13) -> 1421 | AJ13: =SUM(AB13+T13+L13+D13) -> 654.6 | AM13: =SUM(AE13+W13+O13+G13) -> 281.92 | AN13: =AM13/AH13 -> 0.0041360289 | AO13: =AJ13/AM13 -> 2.3219353
A14: 46090 | B14: 4166 | C14: 45 | D14: 77.04 | E14: 1.71 | F14: 0.0108 | H14: =G14/C14 -> 0 | J14: 33648 | K14: 155 | L14: 310.82 | M14: 2.01 | N14: 0.0046 | O14: 7 | P14: =72/307 -> 0.23452769 | Q14: 44.4 | R14: 2394 | S14: 885 | T14: 265.39 | U14: 0.3 | V14: 0.3697 | W14: 53 | X14: 0.0607 | Y14: 4.94 | Z14: 39836 | AA14: 731 | AB14: 97.99 | AC14: 0.13 | AD14: 0.0184 | AE14: 0 | AF14: 0 | AG14: 0 | AH14: =SUM(B14+J14+R14+Z14) -> 80044 | AI14: =SUM(C14+K14+S14+AA14) -> 1816 | AJ14: =SUM(AB14+T14+L14+D14) -> 751.24 | AM14: =SUM(AE14+W14+O14+G14) -> 60 | AN14: =AM14/AH14 -> 0.00074958773 | AO14: =AJ14/AM14 -> 12.520667
A15: 46097 | B15: 6681` | C15: 83 | D15: 76.95 | E15: 0.93 | F15: 0.0124 | G15: 2 | H15: =G15/C15 -> 0.024096386 | I15: =D15/G15 -> 38.475 | J15: 31272 | K15: 328 | L15: 316.8 | M15: 1.52 | N15: 0.0067 | O15: 10 | P15: =10/328 -> 0.030487805 | Q15: 31.68 | R15: 2603 | S15: 894 | T15: 296.38 | U15: 0.33 | V15: 0.3434 | W15: 40 | X15: 0.0452 | Y15: 7.33 | Z15: 24081 | AA15: 903 | AB15: 79.25 | AC15: 0.09 | AD15: 0.0375 | AE15: 1 | AF15: 0.0011 | AG15: 79.25 | AH15: =SUM(B15+J15+R15+Z15) -> #VALUE! | AI15: =SUM(C15+K15+S15+AA15) -> 2208 | AJ15: =SUM(AB15+T15+L15+D15) -> 769.38 | AM15: =SUM(AE15+W15+O15+G15) -> 53 | AN15: =AM15/AH15 -> #VALUE! | AO15: =AJ15/AM15 -> 14.516604
A16: 46104 | B16: 5396 | C16: 75 | D16: 75.85 | E16: 1.01 | F16: 0.0139 | H16: =G16/C16 -> 0 | J16: 30816 | K16: 174 | L16: 310.93 | M16: 1.79 | N16: 0.0056 | O16: 6 | P16: =6/174 -> 0.034482759 | Q16: 51.82 | R16: 2405 | S16: 1059 | T16: 349.99 | U16: 0.33 | V16: 0.4403 | W16: 33 | X16: 0.0313 | Y16: 10.56 | Z16: 30196 | AA16: 259 | AB16: 100.77 | AC16: 0.39 | AD16: 0.0086 | AE16: 3 | AF16: 0.0012 | AG16: 33.59 | AH16: =SUM(B16+J16+R16+Z16) -> 68813 | AI16: =SUM(C16+K16+S16+AA16) -> 1567 | AJ16: =SUM(AB16+T16+L16+D16) -> 837.54 | AM16: =SUM(AE16+W16+O16+G16) -> 42 | AN16: =AM16/AH16 -> 0.00061034979 | AO16: =AJ16/AM16 -> 19.941429
A17: 46111 | B17: 5486 | C17: 66 | D17: 76.85 | E17: 1.16 | F17: 0.012 | G17: 3 | H17: =G17/C17 -> 0.045454545 | I17: =D17/G17 -> 25.616667 | J17: 30248 | K17: 210 | L17: 308.29 | M17: 1.47 | N17: 0.0069 | O17: 10 | P17: =10/210 -> 0.047619048 | Q17: =308.29/20 -> 15.4145 | R17: 2065 | S17: 811 | T17: 253.67 | U17: 0.31 | V17: 0.3927 | W17: 42 | X17: 0.0521 | Y17: 6 | Z17: 28080 | AA17: 1671 | AB17: 82.33 | AC17: 0.05 | AD17: 0.0595 | AE17: 2 | AF17: 0.0012 | AG17: 41.17 | AH17: =SUM(B17+J17+R17+Z17) -> 65879 | AI17: =SUM(C17+K17+S17+AA17) -> 2758 | AJ17: =SUM(AB17+T17+L17+D17) -> 721.14 | AM17: =SUM(AE17+W17+O17+G17) -> 57 | AN17: =AM17/AH17 -> 0.00086522261 | AO17: =AJ17/AM17 -> 12.651579
A18: 46118 | B18: 5175 | C18: 45 | D18: 86.07 | E18: 1.91 | F18: 0.0087 | G18: 7 | H18: =G18/C18 -> 0.15555556 | I18: =D18/G18 -> 12.295714 | J18: 34774 | K18: 248 | L18: 317.13 | M18: 1.28 | N18: 0.0071 | O18: 6 | P18: =6/248 -> 0.024193548 | Q18: 52.86 | R18: 2169 | S18: 876 | T18: 312.45 | U18: 0.36 | V18: 0.4039 | W18: 40 | X18: 0.0468 | Y18: 7.62 | Z18: 24254 | AA18: 2031 | AB18: 91.16 | AC18: 0.36 | AD18: 0.0837 | AE18: 0.71 | AF18: =0.71/2031 -> 0.00034958149 | AG18: 129.27 | AH18: =SUM(B18+J18+R18+Z18) -> 66372 | AI18: =SUM(C18+K18+S18+AA18) -> 3200 | AJ18: =SUM(AB18+T18+L18+D18) -> 806.81 | AM18: =SUM(AE18+W18+O18+G18) -> 53.71 | AN18: =AM18/AH18 -> 0.00080922678 | AO18: =AJ18/AM18 -> 15.021597
A19: 46125 | B19: 3554 | C19: 30 | D19: 81.95 | E19: 2.73 | F19: 0.0084 | G19: 3 | H19: =G19/C19 -> 0.1 | I19: =D19/G19 -> 27.316667 | J19: 32153 | K19: 204 | L19: 312.24 | M19: 1.53 | N19: 0.0063 | O19: 14 | P19: =O19/K19 -> 0.068627451 | Q19: =L19/O19 -> 22.302857 | R19: 2619 | S19: 974 | T19: 288.47 | U19: 0.3 | V19: 0.3719 | W19: 69 | X19: =W19/S19 -> 0.070841889 | Y19: =T19/W19 -> 4.1807246 | Z19: 28166 | AA19: 2143 | AB19: 87.07 | AC19: 0.04 | AD19: 0.0761 | AE19: 0 | AF19: 0 | AG19: 0 | AH19: =SUM(B19+J19+R19+Z19) -> 66492 | AI19: =SUM(C19+K19+S19+AA19) -> 3351 | AJ19: =SUM(AB19+T19+L19+D19) -> 769.73 | AM19: =SUM(AE19+W19+O19+G19) -> 86 | AN19: =AM19/AH19 -> 0.0012933887 | AO19: =AJ19/AM19 -> 8.9503488
A20: 46132 | B20: 3822 | C20: 39 | D20: 85.5 | E20: 2.19 | F20: 0.0102 | G20: 6 | H20: =G20/C20 -> 0.15384615 | I20: =D20/G20 -> 14.25 | J20: 39316 | K20: 238 | L20: 321.28 | M20: 1.35 | N20: 0.0061 | O20: 12 | P20: =O20/K20 -> 0.050420168 | Q20: =L20/O20 -> 26.773333 | R20: 2965 | S20: 1076 | T20: 286.36 | U20: 0.27 | V20: 0.3629 | W20: 60 | X20: =W20/S20 -> 0.055762082 | Y20: =T20/W20 -> 4.7726667 | Z20: 22284 | AA20: 1467 | AB20: 80.76 | AC20: 0.06 | AD20: 0.0658 | AE20: 0 | AF20: 0 | AG20: 0 | AH20: =SUM(B20+J20+R20+Z20) -> 68387 | AI20: =SUM(C20+K20+S20+AA20) -> 2820 | AJ20: =SUM(AB20+T20+L20+D20) -> 773.9 | AM20: =SUM(AE20+W20+O20+G20) -> 78 | AN20: =AM20/AH20 -> 0.0011405677 | AO20: =AJ20/AM20 -> 9.9217949
A21: 46139 | B21: 5872 | C21: 65 | D21: 220.12 | E21: 3.39 | F21: 1,11% | G21: 21 | H21: =G21/C21 -> 0.32307692 | I21: =D21/G21 -> 10.481905 | J21: 37096 | K21: 169 | L21: 285.62 | M21: 1.69 | N21: 0.0046 | O21: 38 | P21: =O21/K21 -> 0.22485207 | Q21: =L21/O21 -> 7.5163158 | R21: 3413 | S21: 1274 | T21: 299.61 | U21: 0.24 | V21: 0.3733 | W21: 114 | X21: =W21/S21 -> 0.089481947 | Y21: =T21/W21 -> 2.6281579 | Z21: 129934 | AA21: 9595 | AB21: 395.09 | AC21: 0.04 | AD21: 0.0738 | AE21: 0 | AF21: 0 | AG21: 0 | AH21: =SUM(B21+J21+R21+Z21) -> 176315 | AI21: =SUM(C21+K21+S21+AA21) -> 11103 | AJ21: =SUM(AB21+T21+L21+D21) -> 1200.44 | AM21: =SUM(AE21+W21+O21+G21) -> 173 | AN21: =AM21/AH21 -> 0.00098119842 | AO21: =AJ21/AM21 -> 6.9389595
A22: 46146 | B22: 0 | C22: 0 | D22: 0 | E22: 0 | F22: 0 | G22: 0 | H22: 0 | I22: 0 | J22: 29766 | K22: 146 | L22: 258.46 | M22: 1.77 | N22: 0.0049 | O22: 11 | P22: =O22/K22 -> 0.075342466 | Q22: =L22/O22 -> 23.496364 | R22: 3851 | S22: 1199 | T22: 404.86 | U22: 0.34 | V22: 0.3113 | W22: 30 | X22: =W22/S22 -> 0.025020851 | Y22: =T22/W22 -> 13.495333 | Z22: 36300 | AA22: 5974 | AB22: 80.18 | AC22: 0.01 | AD22: 0.1646 | AE22: 0 | AF22: 0 | AG22: 0 | AH22: =SUM(B22+J22+R22+Z22) -> 69917 | AI22: =SUM(C22+K22+S22+AA22) -> 7319 | AJ22: =SUM(AB22+T22+L22+D22) -> 743.5 | AM22: =SUM(AE22+W22+O22+G22) -> 41 | AN22: =AM22/AH22 -> 0.0005864096 | AO22: =AJ22/AM22 -> 18.134146
A23: 46153 | B23: 0 | C23: 0 | D23: 0 | E23: 0 | F23: 0 | G23: 0 | H23: 0 | I23: 0 | J23: 27061 | K23: 132 | L23: 234.58 | M23: 1.78 | N23: 0.0049 | O23: 10 | P23: =O23/K23 -> 0.075757576 | Q23: 23.46 | R23: 4545 | S23: 1311 | T23: 386.16 | U23: 0.29 | V23: 0.2884 | W23: 52.12 | X23: 0.0298 | Y23: =T23/W23 -> 7.409056 | Z23: 39504 | AA23: 4972 | AB23: 93.24 | AC23: 0.02 | AD23: 0.1259 | AE23: 10 | AF23: 0.002 | AG23: 9.32 | AH23: =SUM(B23+J23+R23+Z23) -> 71110 | AI23: =SUM(C23+K23+S23+AA23) -> 6415 | AJ23: =SUM(AB23+T23+L23+D23) -> 713.98 | AM23: =SUM(AE23+W23+O23+G23) -> 72.12 | AN23: =AM23/AH23 -> 0.0010142033 | AO23: =AJ23/AM23 -> 9.8998891
A24: 46160 | B24: 0 | C24: 0 | D24: 0 | E24: 0 | F24: 0 | G24: 0 | H24: 0 | I24: 0 | J24: 22774 | K24: 135 | L24: 239.99 | M24: 1.78 | N24: 0.0059 | O24: 12 | P24: =O24/K24 -> 0.088888889 | Q24: =L24/O24 -> 19.999167 | R24: 2997 | S24: 1331 | T24: 338.87 | U24: 0.25 | V24: 0.4441 | W24: 25.27 | X24: 0.019 | Y24: =T24/W24 -> 13.409972 | Z24: 40235 | AA24: 3176 | AB24: 80.5 | AC24: 0.03 | AD24: 0.0794 | AE24: 5 | AF24: 0.16 | AG24: 16.1 | AH24: =SUM(B24+J24+R24+Z24) -> 66006 | AI24: =SUM(C24+K24+S24+AA24) -> 4642 | AJ24: =SUM(AB24+T24+L24+D24) -> 659.36 | AM24: =SUM(AE24+W24+O24+G24) -> 42.27 | AN24: =AM24/AH24 -> 0.00064039633 | AO24: =AJ24/AM24 -> 15.59877
A25: 46167 | J25: 25367 | K25: 162 | L25: 235.8 | M25: 1.27 | N25: 0.0073 | O25: 11 | P25: =O25/K25 -> 0.067901235 | Q25: =L25/O25 -> 21.436364 | R25: 3956 | S25: 1345 | T25: 366.93 | U25: 0.27 | V25: 0.34 | W25: 48 | X25: 0.0359 | Y25: =T25/W25 -> 7.644375 | Z25: 37173 | AA25: 2270 | AB25: 76.14 | AC25: 0.03 | AD25: 0.0611 | AE25: 10 | AF25: 0.0044 | AG25: 7.61
A26: 46174 | J26: 24677 | K26: 120 | L26: 262.81 | M26: 2.6 | N26: 0.0041 | O26: 13 | P26: =O26/K26 -> 0.10833333 | Q26: =L26/O26 -> 20.216154 | R26: 3754 | S26: 1679 | T26: 293.18 | U26: 0.17 | V26: 0.4473 | W26: 54 | X26: 0.0327 | Y26: =T26/W26 -> 5.4292593 | Z26: 44643 | AA26: 2215 | AB26: 88.43 | AC26: 0.04 | AD26: 0.0496 | AE26: 15 | AF26: 0.0068 | AG26: 5.9
A27: 46181 | J27: 23630 | K27: 93 | L27: 248.15 | M27: 5.68 | N27: 0.0022 | O27: 27 | P27: =O27/K27 -> 0.29032258 | Q27: =L27/O27 -> 9.1907407 | R27: 4477 | S27: 1990 | T27: 387.86 | U27: 0.19 | V27: 0.4445 | W27: 47 | X27: 0.024 | Y27: =T27/W27 -> 8.2523404 | Z27: 34662 | AA27: 2357 | AB27: 85.8 | AC27: 0.04 | AD27: 0.068 | AE27: 8 | AF27: 0.0034 | AG27: 10.72
A28: 46188 | Y28: =T28/W28 -> #DIV/0!
A29: 46195 | Y29: =T29/W29 -> #DIV/0!
A30: 46202 | Y30: =T30/W30 -> #DIV/0!
A31: 46209 | Y31: =T31/W31 -> #DIV/0!
A34: TOTALS | B34: =SUM(B5:B31) -> 111528 | C34: =SUM(C5:C31) -> 1096 | D34: =SUM(D5:D31) -> 1136.35 | E34: =D34/C34 -> 1.0368157 | F34: =C34/B34 -> 0.0098271286 | G34: =SUM(G5:G9) -> 0 | H34: =G34/C34 -> 0 | I34: =D34/G34 -> #DIV/0! | J34: =SUM(J5:J25) -> 510884 | K34: =SUM(K5:K25) -> 4007 | L34: =SUM(L8:L25) -> 5264.58 | M34: =L34/K34 -> 1.3138458 | N34: =K34/J34 -> 0.0078432677 | O34: =SUM(O5:O9) -> 5 | P34: =O34/K34 -> 0.0012478163 | Q34: =L34/O34 -> 1052.916 | R34: =SUM(R5:R31) -> 55823 | S34: =SUM(S5:S9) -> 993 | T34: =SUM(T5:T22) -> 3905.06 | U34: =T34/S34 -> 3.9325881 | V34: =S34/R34 -> 0.017788367 | W34: =SUM(W14:W33) -> 707.39 | X34: =W34/S34 -> 0.71237664 | Y34: =T34/W34 -> 5.5203777 | Z34: =SUM(Z5:Z22) -> 498415 | AA34: =SUM(AA5:AA9) -> 555 | AB34: =SUM(AB5:AB22) -> 1658.88 | AC34: =AB34/AA34 -> 2.988973 | AD34: =AA34/Z34 -> 0.0011135299 | AE34: =SUM(AE5:AE9) -> 0 | AF34: =AE34/AA34 -> 0 | AG34: =AB34/AE34 -> #DIV/0! | AH34: =SUM(AH5:AH22) -> #VALUE! | AI34: =SUM(AI5:AI9) -> 2460 | AJ34: =SUM(AJ5:AJ22) -> 11254.5 | AK34: =AJ34/AI34 -> 4.575 | AL34: =AI34/AH34 -> #VALUE! | AM34: =SUM(AM5:AM9) -> 11 | AN34: =AM34/AI34 -> 0.0044715447 | AO34: =AJ34/AM34 -> 1023.1364
A35: BUDGET
A36: REMAINING | L36: =L35-L34 -> -5264.58

Sheet Sheet1
C3: Paid Advertising Revenue | D3: 1638500
C4: Ad Spend | D4: 13700
D24: Spend | E24: Budget Left | F24: Budget
C25: Meta | D25: 5617.42 | E25: =F25-D25 -> 246.23 | F25: 5863.65
C26: LinkedIn | D26: 1136.35 | E26: 0 | F26: 1136.35
C27: Search | D27: 5517.19 | E27: =F27-D27 -> 482.81 | F27: 6000
C28: Google Display | D28: 1997.36 | E28: =F28-D28 -> 2.64 | F28: 2000
D29: =SUM(D25:D28) -> 14268.32
C33: Meta | D33: 5385.37 | E33: =F33-D33 -> 114.63 | F33: 5500
C34: LinkedIn | D34: 1136.35 | E34: 363.65 | F34: 1500
C35: Search | D35: 3535.74 | E35: 2464.26 | F35: 6000
C36: Google Display | D36: 1560.13 | E36: 439.87 | F36: 2000

Sheet EVENT DATA -->
B2: Excludes cancelled, duplicate, main contact, problem resolution, post cancellation, training, cancelled exhibitor, unapproved press, denied press, problem payment, membership problem, denied student, group key, pending student, staff, vendor
B3: Includes exhibitor, patient, non-member, member doctoral, member non-doctoral, member trainee, medical student, member senior emeritus, speaker in-person, VIP
B4: PAID
B5: Includes non-member, member doctoral, member non-doctoral, member trainee, patient

Sheet Total Registrations
A1: American Transplant Congress
A2: REGISTRATIONS
A4: WEEKLY ATTENDEES
J6: 2026 EARLY BIRD ENDS | N6: 2024 early bird | R6: ADVANCE ENDS | AA6: ATC is
A7: Weekly Total Attendees | B7: 24 | C7: 23 | D7: 22 | E7: 21 | F7: 20 | G7: 19 | H7: 18 | I7: 17 | J7: 16 | K7: 15 | L7: 14 | M7: 13 | N7: 12 | O7: 11 | P7: 10 | Q7: 9 | R7: 8 | S7: 7 | T7: 6 | U7: 5 | V7: 4 | W7: 3 | X7: 2 | Y7: 1 | Z7: 0
A8: 2024 DATES ->>> | C8: 12/25-12/31 | D8: 1/1-1/7 | E8: 1/8-1/14 | F8: 1/15-1/21 | G8: 1/22-1/28 | H8: 1/29-2/4 | I8: 2/5-2/11 | J8: 2/12-2/18 | K8: 2/19-2/25 | L8: 2/26-3/3 | M8: 3/4 - 3/10 | N8: 3/11-3/17 | O8: 3/18-3/24 | P8: 3/25-3/31 | Q8: 4/1-4/7 | R8: 4/8-4/14 | S8: 4/15-4/21 | T8: 4/22-4/28 | U8: 4/29-5/5 | V8: 5/6-5/12 | W8: 5/13-5/19 | X8: 5/20-5/26 | Y8: 5/27-6/2 | Z8: 6/3-6/9
A9: 2026 DATES ->>> | B9: 1/5 - 1/11 | C9: 1/12 - 1/18 | D9: 1/19 - 1/25 | E9: 1/26 - 2/1 | F9: 2/2 - 2/8 | G9: 2/9 - 2/15 | H9: 2/16 - 2/22 | I9: 2/23 - 3/1 | J9: 3/2 - 3/8 | K9: 3/9 - 3/15 | L9: 3/16 - 3/22 | M9: 3/23 - 3/29 | N9: 3/30 - 4/5 | O9: 4/6 - 4/12 | P9: 4/13 - 4/19 | Q9: 4/20 - 4/26 | R9: 4/27 - 4/3 | S9: 5/4 - 5/10 | T9: 5/11 - 5/17 | U9: 5/18 - 5/24 | V9: 5/25 - 5/31 | W9: 6/1 - 6/7 | X9: 6/8 - 6/14 | Y9: 6/15 - 6/21 | Z9: 6/22 - 6/28 | AA9: Post-event registrations
A10: 2023 | B10: 0 | C10: 0 | D10: 4 | E10: 18 | F10: 21 | G10: 140 | H10: 54 | I10: 273 | J10: 134 | K10: 163 | L10: 188 | M10: 236 | N10: 161 | O10: 148 | P10: 177 | Q10: 202 | R10: 245 | S10: 257 | T10: 496 | U10: 1029 | V10: 157 | W10: 163 | X10: 285 | Y10: 256 | Z10: 170 | AA10: 19
A11: 2024 | B11: 0 | C11: 0 | D11: 0 | E11: 0 | F11: 0 | G11: 0 | H11: 0 | I11: 0 | J11: 0 | K11: 62 | L11: 477 | M11: 483 | N11: 883 | O11: 155 | P11: 184 | Q11: 139 | R11: 197 | S11: 324 | T11: 226 | U11: 361 | V11: 199 | W11: 217 | X11: 271 | Y11: 441 | Z11: 34
A12: 2026 | K12: =K20+K27 -> 791 | L12: =L20+L27 -> 113 | M12: =M20+M27 -> 119 | N12: =N20+N27 -> 89 | O12: =O20+O27 -> 78 | P12: =P20+P27 -> 77 | Q12: =Q20+Q27 -> 171 | R12: =R20+R27 -> 163 | S12: =S20+S27 -> 422 | T12: =T36-S36 -> 130 | U12: =U36-T36 -> 133 | V12: =V36-U36 -> 140 | W12: 181 | X12: 278
AA14: ATC is
A15: Weeks Out | B15: 24 | C15: 23 | D15: 22 | E15: 21 | F15: 20 | G15: 19 | H15: 18 | I15: 17 | J15: 16 | K15: 15 | L15: 14 | M15: 13 | N15: 12 | O15: 11 | P15: 10 | Q15: 9 | R15: 8 | S15: 7 | T15: 6 | U15: 5 | V15: 4 | W15: 3 | X15: 2 | Y15: 1 | Z15: 0
A16: Weekly Paid Attendees | B16: 1/5 - 1/11 | C16: 1/12 - 1/18 | D16: 1/19 - 1/25 | E16: 1/26 - 2/1 | F16: 2/2 - 2/8 | G16: 2/9 - 2/15 | H16: 2/16 - 2/22 | I16: 2/23 - 3/1 | J16: 3/2 - 3/8 | K16: 3/9 - 3/15 | L16: 3/16 - 3/22 | M16: 3/23 - 3/29 | N16: 3/30 - 4/5 | O16: 4/6 - 4/12 | P16: 4/13 - 4/19 | Q16: 4/20 - 4/26 | R16: 4/27 - 4/3 | S16: 5/4 - 5/10 | T16: 5/11 - 5/17 | U16: 5/18 - 5/24 | V16: 5/25 - 5/31 | W16: 6/1 - 6/7 | X16: 6/8 - 6/14 | Y16: 6/15 - 6/21 | Z16: 6/22 - 6/28 | AA16: Post-event registrations
A17: 2023 | B17: 0 | C17: 0 | D17: 0 | E17: 0 | F17: 0 | G17: 0 | H17: 0 | I17: 247 | J17: 118 | K17: 121 | L17: 164 | M17: 179 | N17: 161 | O17: 137 | P17: 144 | Q17: 164 | R17: 203 | S17: 223 | T17: 404 | U17: 823 | V17: 121 | W17: 108 | X17: 86 | Y17: 145 | Z17: 86
A18: 2024 | B18: 0 | C18: 0 | D18: 0 | E18: 0 | F18: 0 | G18: 0 | H18: 0 | I18: 0 | J18: 0 | K18: 55 | L18: 317 | M18: 394 | N18: 811 | O18: 121 | P18: 159 | Q18: 117 | R18: 169 | S18: 278 | T18: 144 | U18: 272 | V18: 122 | W18: 141 | X18: 154 | Y18: 255 | Z18: 19
A19: 2026 | B19: 13 | C19: 18 | D19: 4 | E19: 115 | F19: 54 | G19: 45 | H19: 115 | I19: 231 | J19: 748 | K19: 97 | L19: 91 | M19: 75 | N19: 67 | O19: 66 | P19: 125 | Q19: 150
A20: 2026 REG TEAM NUMBERS | K20: 743 | L20: 99 | M20: 101 | N20: 76 | O20: 65 | P20: 68 | Q20: 134 | R20: 145 | S20: =S49-R49 -> 358 | T20: =T49-S49 -> 102 | U20: =U49-T49 -> 93 | V20: =V49-U49 -> 95 | W20: 141 | X20: 228
A22: Weeks Out | B22: 24 | C22: 23 | D22: 22 | E22: 21 | F22: 20 | G22: 19 | H22: 18 | I22: 17 | J22: 16 | K22: 15 | L22: 14 | M22: 13 | N22: 12 | O22: 11 | P22: 10 | Q22: 9 | R22: 8 | S22: 7 | T22: 6 | U22: 5 | V22: 4 | W22: 3 | X22: 2 | Y22: 1 | Z22: 0
A23: Weekly Comp Attendees | B23: 1/5 - 1/11 | C23: 1/12 - 1/18 | D23: 1/19 - 1/25 | E23: 1/26 - 2/1 | F23: 2/2 - 2/8 | G23: 2/9 - 2/15 | H23: 2/16 - 2/22 | I23: 2/23 - 3/1 | J23: 3/2 - 3/8 | K23: 3/9 - 3/15 | L23: 3/16 - 3/22 | M23: 3/23 - 3/29 | N23: 3/30 - 4/5 | O23: 4/6 - 4/12 | P23: 4/13 - 4/19 | Q23: 4/20 - 4/26 | R23: 4/27 - 4/3 | S23: 5/4 - 5/10 | T23: 5/11 - 5/17 | U23: 5/18 - 5/24 | V23: 5/25 - 5/31 | W23: 6/1 - 6/7 | X23: 6/8 - 6/14 | Y23: 6/15 - 6/21 | Z23: 6/22 - 6/28 | AA23: Post-event registrations
A24: 2023 | B24: =B10-B17 -> 0 | C24: =C10-C17 -> 0 | D24: =D10-D17 -> 4 | E24: =E10-E17 -> 18 | F24: =F10-F17 -> 21 | G24: =G10-G17 -> 140 | H24: =H10-H17 -> 54 | I24: =I10-I17 -> 26 | ... Z24: =Z10-Z17 -> 84
A25: 2024 | B25: =B11-B18 -> 0 | C25: =C11-C18 -> 0 | D25: =D11-D18 -> 0 | E25: =E11-E18 -> 0 | F25: =F11-F18 -> 0 | G25: =G11-G18 -> 0 | H25: =H11-H18 -> 0 | I25: =I11-I18 -> 0 | ... Z25: =Z11-Z18 -> 15
A26: 2026 | B26: 63 | C26: 60 | D26: =D12-D19 -> -4 | E26: 38 | F26: 30 | G26: 19 | H26: 13 | I26: 33 | J26: =J12-J19 -> -748 | K26: 12 | L26: 19 | M26: 13 | N26: 11 | O26: 9 | P26: 31 | Q26: 14
A27: 2026 REG TEAM NUMBERS | K27: 48 | L27: 14 | M27: 18 | N27: 13 | O27: 13 | P27: 9 | Q27: 37 | R27: 18 | S27: 64 | T27: =T43-S43 -> 28 | U27: =U43-T43 -> 40 | V27: =V43-U43 -> 45 | W27: 40 | X27: 50
A29: CUMULATIVE ATTENDEES
A31: Weeks Out | B31: 24 | C31: 23 | D31: 22 | E31: 21 | F31: 20 | G31: 19 | H31: 18 | I31: 17 | J31: 16 | K31: 15 | L31: 14 | M31: 13 | N31: 12 | O31: 11 | P31: 10 | Q31: 9 | R31: 8 | S31: 7 | T31: 6 | U31: 5 | V31: 4 | W31: 3 | X31: 2 | Y31: 1 | Z31: 0
A32: Cumulative Total Attendees | B32: 1/5 - 1/11 | C32: 1/12 - 1/18 | D32: 1/19 - 1/25 | E32: 1/26 - 2/1 | F32: 2/2 - 2/8 | G32: 2/9 - 2/15 | H32: 2/16 - 2/22 | I32: 2/23 - 3/1 | J32: 3/2 - 3/8 | K32: 3/9 - 3/15 | L32: 3/16 - 3/22 | M32: 3/23 - 3/29 | N32: 3/30 - 4/5 | O32: 4/6 - 4/12 | P32: 4/13 - 4/19 | Q32: 4/20 - 4/26 | R32: 4/27 - 4/3 | S32: 5/4 - 5/10 | T32: 5/11 - 5/17 | U32: 5/18 - 5/24 | V32: 5/25 - 5/31 | W32: 6/1 - 6/7 | X32: 6/8 - 6/14 | Y32: 6/15 - 6/21 | Z32: 6/22 - 6/28 | AA32: Post-event registrations
A33: 2023 | C33: =SUM($B$10:C10) -> 0 | D33: =SUM($B$10:D10) -> 4 | E33: =SUM($B$10:E10) -> 22 | F33: =SUM($B$10:F10) -> 43 | G33: =SUM($B$10:G10) -> 183 | H33: =SUM($B$10:H10) -> 237 | I33: =SUM($B$10:I10) -> 510 | J33: =SUM($B$10:J10) -> 644 | ... Z33: =SUM($B$10:Z10) -> 4977 | AA33: 19
A34: 2024 | C34: =SUM($B$11:C11) -> 0 | D34: =SUM($B$11:D11) -> 0 | E34: =SUM($B$11:E11) -> 0 | F34: =SUM($B$11:F11) -> 0 | G34: =SUM($B$11:G11) -> 0 | H34: =SUM($B$11:H11) -> 0 | I34: =SUM($B$11:I11) -> 0 | J34: =SUM($B$11:J11) -> 0 | ... Z34: =SUM($B$11:Z11) -> 4653
A35: 2026 | B35: 76 | C35: =SUM($B$12:C12) -> 0 | D35: =SUM($B$12:D12) -> 0 | E35: =SUM($B$12:E12) -> 0 | F35: =SUM($B$12:F12) -> 0 | G35: =SUM($B$12:G12) -> 0 | H35: =SUM($B$12:H12) -> 0 | I35: =SUM($B$12:I12) -> 0 | J35: =SUM($B$12:J12) -> 0 | ... N35: =SUM($B$12:N12) -> 1112 | O35: 2134 | P35: 2289 | Q35: 2453 | R35: 2452 | S35: 2874
A36: 2026 REG TEAM NUMBERS | J36: 851 | K36: 1642 | L36: 1755 | M36: 1874 | N36: 1963 | O36: 2041 | P36: 2118 | Q36: 2289 | R36: 2452 | S36: 2874 | T36: =T43+T49 -> 3004 | U36: =U43+U49 -> 3137 | V36: =V43+V49 -> 3277 | W36: =W43+W49 -> 3471 | X36: 3964 | Y36: =Y43+Y49 -> 0 | Z36: =Z43+Z49 -> 0
A38: Weeks Out | B38: 24 | C38: 23 | D38: 22 | E38: 21 | F38: 20 | G38: 19 | H38: 18 | I38: 17 | J38: 16 | K38: 15 | L38: 14 | M38: 13 | N38: 12 | O38: 11 | P38: 10 | Q38: 9 | R38: 8 | S38: 7 | T38: 6 | U38: 5 | V38: 4 | W38: 3 | X38: 2 | Y38: 1 | Z38: 0
A39: Cumulative Comp Attendees | B39: 1/5 - 1/11 | C39: 1/12 - 1/18 | D39: 1/19 - 1/25 | E39: 1/26 - 2/1 | F39: 2/2 - 2/8 | G39: 2/9 - 2/15 | H39: 2/16 - 2/22 | I39: 2/23 - 3/1 | J39: 3/2 - 3/8 | K39: 3/9 - 3/15 | L39: 3/16 - 3/22 | M39: 3/23 - 3/29 | N39: 3/30 - 4/5 | O39: 4/6 - 4/12 | P39: 4/13 - 4/19 | Q39: 4/20 - 4/26 | R39: 4/27 - 4/3 | S39: 5/4 - 5/10 | T39: 5/11 - 5/17 | U39: 5/18 - 5/24 | V39: 5/25 - 5/31 | W39: 6/1 - 6/7 | X39: 6/8 - 6/14 | Y39: 6/15 - 6/21 | Z39: 6/22 - 6/28 | AA39: Post-event registrations
A40: 2023 | C40: =SUM($B$24:C24) -> 0 | D40: =SUM($B$24:D24) -> 4 | E40: =SUM($B$24:E24) -> 22 | F40: =SUM($B$24:F24) -> 43 | G40: =SUM($B$24:G24) -> 183 | H40: =SUM($B$24:H24) -> 237 | I40: =SUM($B$24:I24) -> 263 | J40: =SUM($B$24:J24) -> 279 | ... Z40: =SUM($B$24:Z24) -> 1343
A41: 2024 | C41: =SUM($B$25:C25) -> 0 | D41: =SUM($B$25:D25) -> 0 | E41: =SUM($B$25:E25) -> 0 | F41: =SUM($B$25:F25) -> 0 | G41: =SUM($B$25:G25) -> 0 | H41: =SUM($B$25:H25) -> 0 | I41: =SUM($B$25:I25) -> 0 | J41: =SUM($B$25:J25) -> 0 | ... Z41: =SUM($B$25:Z25) -> 1125
A42: 2026 | B42: 63 | C42: 123 | D42: 139 | E42: 177 | F42: 207 | G42: 226 | H42: 239 | I42: 272 | J42: 323 | K42: 335 | L42: 354 | M42: 367 | N42: 378 | O42: 387 | P42: 418 | Q42: 432
A43: 2026 REG TEAM NUMBERS | J43: 274 | K43: 322 | L43: 336 | M43: 354 | N43: 367 | O43: 380 | P43: 389 | Q43: 426 | R43: 444 | S43: 508 | T43: 536 | U43: 576 | V43: 621 | W43: 683 | X43: 733
A45: Weeks Out | B45: 24 | C45: 23 | D45: 22 | E45: 21 | F45: 20 | G45: 19 | H45: 18 | I45: 17 | J45: 16 | K45: 15 | L45: 14 | M45: 13 | N45: 12 | O45: 11 | P45: 10 | Q45: 9 | R45: 8 | S45: 7 | T45: 6 | U45: 5 | V45: 4 | W45: 3 | X45: 2 | Y45: 1 | Z45: 0
A46: Cumulative Paid Attendees | B46: 1/5 - 1/11 | C46: 1/12 - 1/18 | D46: 1/19 - 1/25 | E46: 1/26 - 2/1 | F46: 2/2 - 2/8 | G46: 2/9 - 2/15 | H46: 2/16 - 2/22 | I46: 2/23 - 3/1 | J46: 3/2 - 3/8 | K46: 3/9 - 3/15 | L46: 3/16 - 3/22 | M46: 3/23 - 3/29 | N46: 3/30 - 4/5 | O46: 4/6 - 4/12 | P46: 4/13 - 4/19 | Q46: 4/20 - 4/26 | R46: 4/27 - 4/3 | S46: 5/4 - 5/10 | T46: 5/11 - 5/17 | U46: 5/18 - 5/24 | V46: 5/25 - 5/31 | W46: 6/1 - 6/7 | X46: 6/8 - 6/14 | Y46: 6/15 - 6/21 | Z46: 6/22 - 6/28 | AA46: Post-event registrations
A47: 2023 | C47: =SUM($B$17:C17) -> 0 | D47: =SUM($B$17:D17) -> 0 | E47: =SUM($B$17:E17) -> 0 | F47: =SUM($B$17:F17) -> 0 | G47: =SUM($B$17:G17) -> 0 | H47: =SUM($B$17:H17) -> 0 | I47: =SUM($B$17:I17) -> 247 | J47: =SUM($B$17:J17) -> 365 | ... Z47: =SUM($B$17:Z17) -> 3634
A48: 2024 | C48: =SUM($B$18:C18) -> 0 | D48: =SUM($B$18:D18) -> 0 | E48: =SUM($B$18:E18) -> 0 | F48: =SUM($B$18:F18) -> 0 | G48: =SUM($B$18:G18) -> 0 | H48: =SUM($B$18:H18) -> 0 | I48: =SUM($B$18:I18) -> 0 | J48: =SUM($B$18:J18) -> 0 | ... Z48: =SUM($B$18:Z18) -> 3528
A49: 2026 | B49: 13 | C49: =SUM($B$19:C19) -> 31 | D49: =SUM($B$19:D19) -> 35 | E49: =SUM($B$19:E19) -> 150 | F49: =SUM($B$19:F19) -> 204 | G49: =SUM($B$19:G19) -> 249 | H49: =SUM($B$19:H19) -> 364 | I49: 595 | J49: =71+506 -> 577 | K49: =1116+204 -> 1320 | L49: =1185+234 -> 1419 | M49: =287+1233 -> 1520 | N49: =1295+301 -> 1596 | O49: =310+1351 -> 1661 | P49: =1409+320 -> 1729 | Q49: =1498+365 -> 1863 | R49: =408+1600 -> 2008 | S49: =1820+546 -> 2366 | T49: =1865+603 -> 2468 | U49: =640+1921 -> 2561 | V49: =1965+691 -> 2656 | W49: 2788 | X49: 2948
A50: PROJECTED PAID 2026 | C50: 25 | D50: 75 | E50: 125 | F50: 300 | G50: 540 | H50: 720 | I50: 1080 | J50: 1438 | K50: 1500 | L50: 1562 | M50: 1624 | N50: 1686 | O50: 1748 | P50: 1810 | Q50: 1872 | R50: 1934 | S50: 1996 | T50: 2055 | U50: 2230 | V50: 2430 | W50: 2630 | X50: 2830 | Y50: 3055 | Z50: 3098
A53: 2026 Objectives
A54: Cumulative Attendees | B54: Actual | C54: Goal | D54: % to Goal
A55: Total Attendees | B55: 1821 | C55: 4937 | D55: =B55/C55 -> 0.36884748
A56: Paid Attendees | B56: 1476 | C56: 3855 | D56: =B56/C56 -> 0.38287938
A57: Comp Attendees | B57: 351 | C57: 1082 | D57: =B57/C57 -> 0.32439926

Sheet GA4 Registrations
A1: American Transplant Congress
A2: REGISTRATIONS
A3: TRAFFIC ACQUISITION | O3: EARLY BIRD ENDS | R3: Advance Ends | AA3: ATC is
A4: Weeks Out | B4: 24 | C4: 23 | D4: 22 | E4: 21 | F4: 20 | G4: 19 | H4: 18 | I4: 17 | J4: 16 | K4: 15 | L4: 14 | M4: 13 | N4: 12 | O4: 11 | P4: 10 | Q4: 9 | R4: 8 | S4: 7 | T4: 6 | U4: 5 | V4: 4 | W4: 3 | X4: 2 | Y4: 1 | Z4: 0
A6: Weekly Total Attendees (2026) | B6: 1/5 - 1/11 | C6: 1/12 - 1/18 | D6: 1/19 - 1/25 | E6: 1/26 - 2/1 | F6: 2/2 - 2/8 | G6: 2/9 - 2/15 | H6: 2/16 - 2/22 | I6: 2/23 - 3/1 | J6: 3/2 - 3/8 | K6: 3/9 - 3/15 | L6: 3/16 - 3/22 | M6: 3/23 - 3/29 | N6: 3/30 - 4/5 | O6: 4/6 - 4/12 | P6: 4/13 - 4/19 | Q6: 4/20 - 4/26 | R6: 4/27 - 5/3 | S6: 5/4 - 5/10 | T6: 5/11 - 5/17 | U6: 5/18 - 5/24 | V6: 5/25 - 5/31 | W6: 6/1 - 6/7 | X6: 6/8 - 6/14 | Y6: 6/15 - 6/21 | Z6: 6/22 - 6/28 | AA6: Total Registrations
A7: Organic Search | B7: 14 | C7: 10 | D7: 0 | E7: 44 | F7: 22 | G7: 20 | H7: 56 | I7: 78 | J7: 242 | K7: 32 | L7: 26 | M7: 30 | N7: 24 | O7: 23 | P7: 27 | Q7: 42 | R7: 110 | S7: 28 | T7: 45 | U7: 30 | V7: 38 | W7: 34 | X7: 78 | AA7: =SUM(B7:Z7) -> 1053
A8: Email | B8: 2 | C8: 0 | D8: 1 | E8: 48 | F8: 12 | G8: 8 | H8: 26 | I8: 51 | J8: 124 | K8: 6 | L8: 4 | M8: 6 | N8: 13 | O8: 6 | P8: 20 | Q8: 25 | R8: 52 | S8: 7 | T8: 9 | U8: 7 | V8: 8 | W8: 11 | X8: 20 | AA8: =SUM(B8:Z8) -> 466
A9: Direct | B9: 16 | C9: 20 | D9: 5 | E9: 25 | F9: 12 | G9: 14 | H9: 13 | I9: 68 | J9: 124 | K9: 28 | L9: 32 | M9: 32 | N9: 21 | O9: 22 | P9: 55 | Q9: 62 | R9: 128 | S9: 57 | T9: 42 | U9: 42 | V9: 68 | W9: 80 | X9: 91 | AA9: =SUM(B9:Z9) -> 1057
A10: Paid Social | B10: 0 | C10: 0 | D10: 0 | E10: 0 | F10: 1 | G10: 0 | H10: 1 | I10: 1 | J10: 2 | K10: 0 | L10: 0 | M10: 0 | N10: 0 | O10: 0 | P10: 0 | Q10: 1 | R10: 1 | S10: 0 | T10: 0 | U10: 0 | V10: 0 | W10: 0 | X10: 0 | AA10: =SUM(B10:Z10) -> 7
A11: Referral | B11: 59 | C11: 55 | D11: 19 | E11: 19 | F11: 33 | G11: 22 | H11: 20 | I11: 69 | J11: 141 | K11: 22 | L11: 18 | M11: 11 | N11: 23 | O11: 23 | P11: 11 | Q11: 18 | R11: 36 | S11: 11 | T11: 12 | U11: 15 | V11: 15 | W11: 25 | X11: 32 | AA11: =SUM(B11:Z11) -> 709
A12: Paid Search | B12: 0 | C12: 0 | D12: 0 | E12: 4 | F12: 12 | G12: 9 | H12: 13 | I12: 40 | J12: 179 | K12: 39 | L12: 26 | M12: 23 | N12: 28 | O12: 41 | P12: 40 | Q12: 48 | R12: 82 | S12: 30 | T12: 75 | U12: 54 | V12: 68 | W12: 85 | X12: 92 | AA12: =SUM(B12:Z12) -> 988
A13: Unassigned | B13: 0 | C13: 0 | D13: 0 | E13: 0 | F13: 0 | G13: 0 | H13: 0 | I13: 0 | J13: 5 | K13: 0 | L13: 3 | M13: 0 | N13: 0 | O13: 0 | P13: 1 | Q13: 0 | R13: 0 | S13: 0 | T13: 3 | U13: 0 | V13: 1 | W13: 2 | X13: 2 | AA13: =SUM(B13:Z13) -> 17
A14: Organic Social | B14: 0 | C14: 0 | D14: 0 | E14: 0 | F14: 0 | G14: 0 | H14: 0 | I14: 0 | J14: 2 | K14: 0 | L14: 0 | M14: 0 | N14: 0 | O14: 0 | P14: 0 | Q14: 0 | R14: 2 | S14: 0 | T14: 0 | U14: 0 | V14: 0 | W14: 1 | X14: 0 | AA14: =SUM(B14:Z14) -> 5
A15: Cross-network | B15: 0 | C15: 0 | D15: 0 | E15: 0 | F15: 0 | G15: 0 | H15: 0 | I15: 0 | J15: 0 | K15: 0 | L15: 0 | M15: 0 | N15: 0 | O15: 0 | P15: 0 | Q15: 0 | R15: 1 | S15: 0 | T15: 0 | U15: 0 | V15: 0 | W15: 4 | X15: 0 | AA15: =SUM(B15:Z15) -> 5
B34: Total Registrations to Date by Source
B35: Source | C35: Registrations
B36: Organic Search | C36: 975
B37: Email | C37: 446
B38: Direct | C38: 966
B39: Paid Social | C39: 7
B40: Referral | C40: 677
B41: Paid Search | C41: 896
B42: Unassigned | C42: 15
B43: Organic Social | C43: 5
B44: Cross Network | C44: 5
B57: Source | C57: Registrations
B58: Email #3b | C58: 1
B59: Email #4b | C59: 5

Sheet Abstracts
B1: Late-Breaking Submissions
B2: Year | C2: Submissions
B3: 2024 | C3: 112
B4: 2026 | C4: 142

Sheet PROJECTIONS -->

Sheet 5.12 Projections
G2: Members | H2: =H9+H15+H21 -> 1396972
G3: Nonmembers | H3: =H33 -> 1166844.8
G4: Student/trainee/emeritus/patient | H4: =H27+H42+H43+H44 -> 179324.64
G5: Exhibitor | H5: =H41 -> 145418
G6: Discounts | H6: =H46 -> -23400
O7: USA: 100% Canada: 50% Other Intl: 50% | P7: Total Paid Attendees | Q7: US - Projected | R7: US - Actual | S7: Canada - Projected | T7: Canada - Actual | U7: Other - Projected | V7: Other - Actual
B8: USA: 100% Canada: 50% Other Intl: 50% | C8: Projected Paid Attendees | D8: Actual Paid Attendees | E8: MODEL REVENUE | F8: Actual Revenue | G8: New Projection as of 3.9 | H8: New Projection as of 5/12 | O8: Member Doctoral | P8: 1055.9418 | Q8: 1000.36 | S8: 16.298 | U8: 39.2838
B9: Member Doctoral | C9: 1055.9418 | E9: 923550.75 | G9: =SUM(G10:G13) -> 868227.52 | H9: =SUM(H10:H13) -> 973503.01 | O9: Member Doctoral Early | P9: 558.97275 | Q9: 529.55 | R9: 426 | S9: 8.6275 | T9: 15 | U9: 20.79525 | V9: 53
B10: Member Doctoral Early | C10: 558.97275 | D10: 499 | E10: 446619.23 | F10: 398701 | G10: =387301+3995 -> 391296 | H10: =F10 -> 398701 | O10: Member Doctoral Advance | P10: 215.13405 | Q10: 203.81 | S10: 3.3205 | U10: 8.00355
B11: Member Doctoral Advance | C11: 215.13405 | D11: 324 | E11: 193405.51 | F11: 291276 | G11: 193405.51 | H11: =F11 -> 291276 | O11: Member Doctoral Regular | P11: 262.10655 | Q11: 248.31 | S11: 4.0455 | U11: 9.75105
B12: Member Doctoral Regular | C12: 262.10655 | E12: 261844.44 | G12: 261844.44 | H12: 261844.44 | O12: Member Doctoral On-Site | P12: 19.72845 | Q12: 18.69 | S12: 0.3045 | U12: 0.73395
B13: Member Doctoral On-Site | C13: 19.72845 | E13: 21681.567 | G13: 21681.567 | H13: 21681.567
O14: Member Non-Medical Doctoral | P14: 332.5653 | Q14: 315.06 | S14: 5.133 | U14: 12.3723
B15: Member Non-Medical Doctoral | C15: 332.5653 | E15: 251440.03 | G15: =SUM(G16:G19) -> 239379.41 | H15: =SUM(H16:H19) -> 261351.46 | O15: Member Non-Medical Doctoral Early | P15: 206.679 | Q15: 195.8 | R15: 125 | S15: 3.19 | T15: 4 | U15: 7.689 | V15: 6
B16: Member Non-Medical Doctoral Early | C16: 206.679 | D16: 190 | E16: 144468.62 | F16: 132810 | G16: =131010+1398 -> 132408 | H16: =F16 -> 132810 | O16: Member Non-Medical Doctoral Advance | P16: 62.0037 | Q16: 58.74 | S16: 0.957 | U16: 2.3067
B17: Member Non-Medical Doctoral Advance | C17: 62.0037 | D17: 89 | E17: 49540.956 | F17: 71111 | G17: 49540.956 | H17: =F17 -> 71111 | O17: Member Non-Medical Doctoral Regular | P17: 63.8826 | Q17: 60.52 | S17: 0.986 | U17: 2.3766
B18: Member Non-Medical Doctoral Regular | C18: 63.8826 | E18: 57430.457 | G18: 57430.457 | H18: =E18 -> 57430.457 | O18: Member Non-Medical Doctoral On-Site | P18: 0 | Q18: 0 | S18: 0 | U18: 0
B19: Member Non-Medical Doctoral On-Site | C19: 0 | E19: 0 | G19: 0
O20: Member Non-Doctoral | P20: 317.5341 | Q20: 300.82 | S20: 4.901 | U20: 11.8131
B21: Member Non-Doctoral | C21: 317.5341 | E21: 165210.66 | G21: =SUM(G22:G25) -> 155711.93 | H21: =SUM(H22:H25) -> 162117.53 | O21: Member Non-Doctoral Early | P21: 167.2221 | Q21: 158.42 | R21: 142 | S21: 2.581 | T21: 0 | U21: 6.2211 | V21: 3
B22: Member Non-Doctoral Early | C22: 167.2221 | D22: 147 | E22: 75082.723 | F22: 66003 | G22: =65135+449 -> 65584 | H22: =F22 -> 66003 | O22: Member Non-Doctoral Advance | P22: 76.09545 | Q22: 72.09 | S22: 1.1745 | U22: 2.83095
B23: Member Non-Doctoral Advance | C23: 76.09545 | D23: 87 | E23: 41776.402 | F23: 47763 | G23: 41776.402 | H23: =F23 -> 47763 | O23: Member Non-Doctoral Regular | P23: 72.33765 | Q23: 68.53 | S23: 1.1165 | U23: 2.69115
B24: Member Non-Doctoral Regular | C24: 72.33765 | E24: 46947.135 | G24: 46947.135 | H24: =E24 -> 46947.135 | O24: Member Non-Doctoral On-Site | P24: 1.8789 | Q24: 1.78 | S24: 0.029 | U24: 0.0699
B25: Member Non-Doctoral On-Site | C25: 1.8789 | E25: 1404.3961 | G25: 1404.3961 | H25: =E25 -> 1404.3961
O26: Member Trainee | P26: 533.6076 | Q26: 505.52 | S26: 8.236 | U26: 19.8516
B27: Member Trainee | C27: 533.6076 | E27: 180263.54 | G27: =SUM(G28:G31) -> 163716.94 | H27: =SUM(H28:H31) -> 167616.64 | O27: Member Trainee Early | P27: 273.37995 | Q27: 258.99 | R27: 192 | S27: 4.2195 | T27: 2 | U27: 10.17045 | V27: 15
B28: Member Trainee Early | C28: 273.37995 | D28: 211 | E28: 81740.605 | F28: 63089 | G28: =64596+598 -> 65194 | H28: =F28 -> 63089 | O28: Member Trainee Advance | P28: 111.79455 | Q28: 105.91 | S28: 1.7255 | U28: 4.15905
B29: Member Trainee Advance | C29: 111.79455 | D29: 129 | E29: 39016.298 | F29: 45021 | G29: 39016.298 | H29: =F29 -> 45021 | O29: Member Trainee Regular | P29: 142.7964 | Q29: 135.28 | S29: 2.204 | U29: 5.3124
B30: Member Trainee Regular | C30: 142.7964 | E30: 56975.764 | G30: 56975.764 | H30: =E30 -> 56975.764 | O30: Member Trainee On-Site | P30: 5.6367 | Q30: 5.34 | S30: 0.087 | U30: 0.2097
B31: Member Trainee On-Site | C31: 5.6367 | E31: 2530.8783 | G31: 2530.8783 | H31: =E31 -> 2530.8783
O32: Non-Member | P32: 719.055 | Q32: 580.29 | S32: 12.615 | U32: 126.15
B33: Non-Member (+ industry partner/transplant community new category) | C33: 719.055 | E33: 1163736.8 | G33: =SUM(G34:G37) -> 1042265.3 | H33: =SUM(H34:H37) -> 1166844.8 | O33: Non-Member Early | P33: 232.2465 | Q33: 187.427 | R33: 88 | S33: 4.0745 | T33: 0 | U33: 40.745 | V33: 66
B34: Non-Member Early | C34: 232.2465 | D34: =131+4+27 -> 162 | E34: 348137.5 | F34: =196369+43173+396+597 -> 240535 | G34: 226666 | H34: =F34 -> 240535 | O34: Non-Member Advance | P34: 152.076 | Q34: 122.728 | S34: 2.668 | U34: 26.68
B35: Non-Member Advance | C35: 152.076 | D35: =199+3+21 -> 223 | E35: 243169.52 | F35: =318201+35679 -> 353880 | G35: 243169.52 | H35: =F35 -> 353880 | O35: Non-Member Regular | P35: 297.54 | Q35: 240.12 | S35: 5.22 | U35: 52.2
B36: Non-Member Regular | C36: 297.54 | E36: 505520.46 | G36: 505520.46 | H36: =E36 -> 505520.46 | O36: Non-Member On-Site | P36: 37.1925 | Q36: 30.015 | S36: 0.6525 | U36: 6.525
B37: Non-Member On-Site | C37: 37.1925 | E37: 66909.307 | G37: 66909.307 | H37: =E37 -> 66909.307
B39: Other | E39: =SUM(E40:E44) -> 42434.163 | F39: =SUM(F40:F44) -> 157126 | G39: =SUM(G40:G43) -> 42434.163 | H39: =SUM(H40:H44) -> 157126 | O39: Non-Member Early | P39: 232.2465 | Q39: 187.427 | R39: 88 | S39: 4.0745 | T39: 0 | U39: 40.745 | V39: 66
B40: Patient | C40: 0 | E40: 0 | O40: Additional Exhibitor Badge | P40: 213.237 | Q40: 172.086 | S40: 3.741 | U40: 37.41
B41: Additional Exhibitor Badge | C41: 213.237 | D41: 182 | E41: 42434.163 | F41: 145418 | G41: 42434.163 | H41: =F41 -> 145418
B42: Member Affiliate | C42: 0 | D42: 5 | F42: 4995 | H42: =F42 -> 4995
B43: Member Senior Emeritus | C43: 0 | D43: 17 | F43: 833 | H43: =F43 -> 833
B44: Member Medical Student | C44: 0 | D44: 120 | F44: 5880 | H44: =F44 -> 5880
B45: Paid Meeting Registration | C45: 3171.9408 | E45: 2726635.9 | G45: =SUM(G41,G33,G27,G21,G15,G9) -> 2511735.3 | H45: =SUM(H39,H33,H27,H21,H15,H9) -> 2888559.4
B46: DISCOUNTS | F46: -23400 | H46: -23400
F47: =F45+F46 -> -23400 | H47: =H45+H46 -> 2865159.4
Q49: =Q9+Q15+Q21+Q27+Q33 -> 1330.187 | R49: =R9+R15+R21+R27+R33 -> 973 | S49: =R49/Q49 -> 0.7314761 | T49: =T9+T15+T21+T27+T33 -> 21 | V49: =V9+V15+V21+V27+V33 -> 143
C53: 3098

Sheet Actuals 5.12
D2: Actuals 5/12
D3: Members | E3: =E12+E13+E14+E18+E19+E20+E24+E25+E26 -> 1040478
D4: Non-Members | E4: =E36+E37+E38 -> 562142
D5: Student/Trainee/Emeritus/Patient | E5: =E30+E31+E32+E44+E45+E46 -> 124207
D6: Exhibitor | E6: =E43 -> 145418
D7: Discounts | E7: =E48 -> -23400
C10: USA: 100% Canada: 50% Other Intl: 50% | D10: Actual Paid Attendees | E10: Actual Revenue
C11: Member Doctoral
C12: Member Doctoral Early | D12: 499 | E12: 398701
C13: Member Doctoral Advance | D13: 324 | E13: 291276
C14: Member Doctoral Regular | E14: 21978
C15: Member Doctoral On-Site | E15: 0
C17: Member Non-Medical Doctoral
C18: Member Non-Medical Doctoral Early | D18: 190 | E18: 132810
C19: Member Non-Medical Doctoral Advance | D19: 89 | E19: 71111
C20: Member Non-Medical Doctoral Regular | E20: 6293
C21: Member Non-Medical Doctoral On-Site | E21: 0
C23: Member Non-Doctoral
C24: Member Non-Doctoral Early | D24: 147 | E24: 66003
C25: Member Non-Doctoral Advance | D25: 87 | E25: 47763
C26: Member Non-Doctoral Regular | E26: 4543
C27: Member Non-Doctoral On-Site | E27: 0
C29: Member Trainee
C30: Member Trainee Early | D30: 211 | E30: 63089
C31: Member Trainee Advance | D31: 129 | E31: 45021
C32: Member Trainee Regular | E32: 4389
C33: Member Trainee On-Site | E33: 0
C35: Non-Member (+ industry partner/transplant community new category)
C36: Non-Member Early | D36: 162 | E36: 196369
C37: Non-Member Advance | D37: 223 | E37: 318201
C38: Non-Member Regular | E38: 47572
C39: Non-Member On-Site
C41: Other | E41: 157126
C42: Patient
C43: Additional Exhibitor Badge | D43: 182 | E43: 145418
C44: Member Affiliate | D44: 5 | E44: 4995
C45: Member Senior Emeritus | D45: 17 | E45: 833
C46: Member Medical Student | D46: 120 | E46: 5880
C47: Paid Meeting Registration
C48: DISCOUNTS | E48: -23400
E49: -23400

Sheet Projections
K3: 2026 EARLY BIRD ENDS | U3: ADVANCE ENDS | AB3: ATC is
C4: 24 | D4: 23 | E4: 22 | F4: 21 | G4: 20 | H4: 19 | I4: 18 | J4: 17 | K4: 16 | L4: 15 | M4: 14 | N4: 13 | O4: 12 | P4: 11 | Q4: 10 | R4: 9 | S4: 8 | T4: 7 | U4: 6 | V4: 5 | W4: 4 | X4: 3 | Y4: 2 | Z4: 1 | AA4: 0
B5: 2024 DATES ->>> | D5: 12/25-12/31 | E5: 1/1-1/7 | F5: 1/8-1/14 | G5: 1/15-1/21 | H5: 1/22-1/28 | I5: 1/29-2/4 | J5: 2/5-2/11 | K5: 2/12-2/18 | L5: 2/19-2/25 | M5: 2/26-3/3 | N5: 3/4 - 3/10 | O5: 3/11-3/17 | P5: 3/18-3/24 | Q5: 3/25-3/31 | R5: 4/1-4/7 | S5: 4/8-4/14 | T5: 4/15-4/21 | U5: 4/22-4/28 | V5: 4/29-5/5 | W5: 5/6-5/12 | X5: 5/13-5/19 | Y5: 5/20-5/26 | Z5: 5/27-6/2 | AA5: 6/3-6/9
B6: 2026 DATES ->>> | C6: 1/5 - 1/11 | D6: 1/12 - 1/18 | E6: 1/19 - 1/25 | F6: 1/26 - 2/1 | G6: 2/2 - 2/8 | H6: 2/9 - 2/15 | I6: 2/16 - 2/22 | J6: 2/23 - 3/1 | K6: 3/2 - 3/8 | L6: 3/9 - 3/15 | M6: 3/16 - 3/22 | N6: 3/23 - 3/29 | O6: 3/30 - 4/5 | P6: 4/6 - 4/12 | Q6: 4/13 - 4/19 | R6: 4/20 - 4/26 | S6: 4/27 - 4/3 | T6: 5/4 - 5/10 | U6: 5/11 - 5/17 | V6: 5/18 - 5/24 | W6: 5/25 - 5/31 | X6: 6/1 - 6/7 | Y6: 6/8 - 6/14 | Z6: 6/15 - 6/21 | AA6: 6/22 - 6/28 | AB6: Post-event registrations
B7: Projected Total
B8: Projected Paid | D8: 25 | E8: 75 | F8: 125 | G8: 300 | H8: =180*3 -> 540 | I8: =180*4 -> 720 | J8: 1080 | K8: =232+273+167+207+559 -> 1438 | L8: =K8+62 -> 1500 | M8: =L8+62 -> 1562 | N8: =M8+62 -> 1624 | O8: =N8+62 -> 1686 | P8: =O8+62 -> 1748 | Q8: =P8+62 -> 1810 | R8: =Q8+62 -> 1872 | S8: =R8+62 -> 1934 | T8: =S8+62 -> 1996 | U8: =K8+215+62+76+112+152 -> 2055 | V8: =U8+175 -> 2230 | W8: =V8+200 -> 2430 | X8: =W8+200 -> 2630 | Y8: =X8+200 -> 2830 | Z8: =Y8+225 -> 3055 | AA8: 3098
B9: Projected Comp

Sheet OPERATIONS -->

Sheet Pass Types
A1: Pass Types: ATC 2024
A3: Pass Type | B3: 2023 Registrations | C3: 2024 Registrations | D3: Percent
A4: Member Doctoral | C4: 1030 | D4: =C4/SUM(C$4:C$13) -> 0.29572208
A5: Non-Member | C5: 649 | D5: =C5/SUM(C$4:C$13) -> 0.18633362
A6: Member Non-MD Doctoral | C6: 313 | D6: =C6/SUM(C$4:C$13) -> 0.089865059
A7: Member Non-Doctoral | C7: 298 | D7: =C7/SUM(C$4:C$13) -> 0.085558427
A8: Member trainee | C8: 492 | D8: =C8/SUM(C$4:C$13) -> 0.14125754
A9: Exhibitor | B9: 410 | C9: 280 | D9: =C9/SUM(C$4:C$13) -> 0.080390468
A10: Speaker In-Person | C10: 274 | D10: =C10/SUM(C$4:C$13) -> 0.078667815
A11: Member Senior Emeritus | C11: 15 | D11: =C11/SUM(C$4:C$13) -> 0.0043066322
A12: Medical Student | C12: 101 | D12: =C12/SUM(C$4:C$13) -> 0.02899799
A13: Patient | B13: 2 | C13: 31 | D13: =C13/SUM(C$4:C$13) -> 0.0089003732
A14: Media | B14: 23 | C14: 8 | D14: =C14/SUM(C$4:C$13) -> 0.0022968705
A15: Total | C15: =SUM(C4:C14) -> 3491 | D15: =SUM(D4:D13) -> 1
A25: Pass Type | C25: 2022 | D25: 2023 | E25: 2024 Registrations
A26: Member Doctoral | E26: 1030
A27: Non-Member | E27: 649
A28: Member Non-MD Doctoral | E28: 313
A29: Member Non-Doctoral | E29: 298
A30: Member trainee | E30: 492
A31: Exhibitor | E31: 280
A32: Speaker In-Person | E32: 274
A33: Member Senior Emeritus | E33: 15
A34: Medical Student | E34: 101
A35: Patient | E35: 31
A36: Media | E36: 8
A37: Total | E37: =SUM(E26:E35) -> 3483
A45: Pass Type | C45: 2023
A46: Member | C46: 2746
A47: Non-Member | C47: 1336
A48: Exhibitor | C48: 411
A49: Press | C49: 23
A50: Unknown | C50: =5038-C53 -> 522
A51: Dual | C51: 192
A52: ATC staff | C52: 10
A53: Total | C53: =SUM(C46:C49) -> 4516

Sheet Optimizations
A1: Month | B1: Channel | C1: Control (the "A") | D1: Test (the "B") | E1: Results | F1: Conclusions / Recommendations
A2: November
A3: December
A4: January
A5: February
A6: March
A7: April
A8: May
A9: June
A10: July
A11: August
A12: September
A13: October
... A15: December

Sheet ARCHIVE -->

Sheet OLD Total Registrations
A1: American Transplant Congress
A2: REGISTRATIONS
J3: 2026 EARLY BIRD ENDS | N3: 2024 early bird | R3: ADVANCE ENDS | AA3: ATC is
A4: Weekly Total Attendees | B4: 24 | C4: 23 | D4: 22 | E4: 21 | F4: 20 | G4: 19 | H4: 18 | I4: 17 | J4: 16 | K4: 15 | L4: 14 | M4: 13 | N4: 12 | O4: 11 | P4: 10 | Q4: 9 | R4: 8 | S4: 7 | T4: 6 | U4: 5 | V4: 4 | W4: 3 | X4: 2 | Y4: 1 | Z4: 0
A5: 2024 DATES ->>> | C5: 12/25-12/31 | D5: 1/1-1/7 | E5: 1/8-1/14 | F5: 1/15-1/21 | G5: 1/22-1/28 | H5: 1/29-2/4 | I5: 2/5-2/11 | J5: 2/12-2/18 | K5: 2/19-2/25 | L5: 2/26-3/3 | M5: 3/4 - 3/10 | N5: 3/11-3/17 | O5: 3/18-3/24 | P5: 3/25-3/31 | Q5: 4/1-4/7 | R5: 4/8-4/14 | S5: 4/15-4/21 | T5: 4/22-4/28 | U5: 4/29-5/5 | V5: 5/6-5/12 | W5: 5/13-5/19 | X5: 5/20-5/26 | Y5: 5/27-6/2 | Z5: 6/3-6/9
A6: 2026 DATES ->>> | B6: 1/5 - 1/11 | C6: 1/12 - 1/18 | D6: 1/19 - 1/25 | E6: 1/26 - 2/1 | F6: 2/2 - 2/8 | G6: 2/9 - 2/15 | H6: 2/16 - 2/22 | I6: 2/23 - 3/1 | J6: 3/2 - 3/8 | K6: 3/9 - 3/15 | L6: 3/16 - 3/22 | M6: 3/23 - 3/29 | N6: 3/30 - 4/5 | O6: 4/6 - 4/12 | P6: 4/13 - 4/19 | Q6: 4/20 - 4/26 | R6: 4/27 - 5/3 | S6: 5/4 - 5/10 | T6: 5/11 - 5/17 | U6: 5/18 - 5/24 | V6: 5/25 - 5/31 | W6: 6/1 - 6/7 | X6: 6/8 - 6/14 | Y6: 6/15 - 6/21 | Z6: 6/22 - 6/28 | AA6: Post-event registrations
A7: 2023 | B7: 0 | C7: 0 | D7: 4 | E7: 18 | F7: 21 | G7: 140 | H7: 54 | I7: 273 | J7: 134 | K7: 163 | L7: 188 | M7: 236 | N7: 161 | O7: 148 | P7: 177 | Q7: 202 | R7: 245 | S7: 257 | T7: 496 | U7: 1029 | V7: 157 | W7: 163 | X7: 285 | Y7: 256 | Z7: 170 | AA7: 19
A8: 2024 | B8: 0 | C8: 0 | D8: 0 | E8: 0 | F8: 0 | G8: 0 | H8: 0 | I8: 0 | J8: 0 | K8: 62 | L8: 477 | M8: 483 | N8: 883 | O8: 155 | P8: 184 | Q8: 139 | R8: 197 | S8: 324 | T8: 226 | U8: 361 | V8: 199 | W8: 217 | X8: 271 | Y8: 441 | Z8: 34
A9: 2026 | B9: 76 | C9: 78 | D9: 20 | E9: 153 | F9: 84 | G9: 64 | H9: 128 | I9: 264 | J9: 799 | K9: 109 | L9: 110 | M9: 88 | N9: 78 | O9: 75 | P9: 156 | Q9: 164 | R9: 422 | S9: 125
K10: 791 | L10: 113 | M10: 119 | N10: 89 | O10: 78 | P10: 77 | Q10: 171 | R10: 163 | S10: 422
AA11: ATC is
A12: Weeks Out | B12: 24 | C12: 23 | D12: 22 | E12: 21 | F12: 20 | G12: 19 | H12: 18 | I12: 17 | J12: 16 | K12: 15 | L12: 14 | M12: 13 | N12: 12 | O12: 11 | P12: 10 | Q12: 9 | R12: 8 | S12: 7 | T12: 6 | U12: 5 | V12: 4 | W12: 3 | X12: 2 | Y12: 1 | Z12: 0
A13: Paid Attendees | B13: 1/5 - 1/11 | C13: 1/12 - 1/18 | D13: 1/19 - 1/25 | E13: 1/26 - 2/1 | F13: 2/2 - 2/8 | G13: 2/9 - 2/15 | H13: 2/16 - 2/22 | I13: 2/23 - 3/1 | J13: 3/2 - 3/8 | K13: 3/9 - 3/15 | L13: 3/16 - 3/22 | M13: 3/23 - 3/29 | N13: 3/30 - 4/5 | O13: 4/6 - 4/12 | P13: 4/13 - 4/19 | Q13: 4/20 - 4/26 | R13: 4/27 - 5/3 | S13: 5/4 - 5/10 | T13: 5/11 - 5/17 | U13: 5/18 - 5/24 | V13: 5/25 - 5/31 | W13: 6/1 - 6/7 | X13: 6/8 - 6/14 | Y13: 6/15 - 6/21 | Z13: 6/22 - 6/28 | AA13: Post-event registrations
A14: 2023 | B14: 0 | C14: 0 | D14: 0 | E14: 0 | F14: 0 | G14: 0 | H14: 0 | I14: 247 | J14: 118 | K14: 121 | L14: 164 | M14: 179 | N14: 161 | O14: 137 | P14: 144 | Q14: 164 | R14: 203 | S14: 223 | T14: 404 | U14: 823 | V14: 121 | W14: 108 | X14: 86 | Y14: 145 | Z14: 86
A15: 2024 | B15: 0 | C15: 0 | D15: 0 | E15: 0 | F15: 0 | G15: 0 | H15: 0 | I15: 0 | J15: 0 | K15: 55 | L15: 317 | M15: 394 | N15: 811 | O15: 121 | P15: 159 | Q15: 117 | R15: 169 | S15: 278 | T15: 144 | U15: 272 | V15: 122 | W15: 141 | X15: 154 | Y15: 255 | Z15: 19
A16: 2026 | B16: 13 | C16: 18 | D16: 4 | E16: 115 | F16: 54 | G16: 45 | H16: 115 | I16: 231 | J16: 748 | K16: 97 | L16: 91 | M16: 75 | N16: 67 | O16: 66 | P16: 125 | Q16: 150 | R16: 357 | S16: 98
A17: 2026 REG TEAM NUMBERS | K17: 743 | L17: 99 | M17: 101 | N17: 76 | O17: 65 | P17: 68 | Q17: 134 | R17: 145
A19: Weeks Out | B19: 24 | C19: 23 | D19: 22 | E19: 21 | F19: 20 | G19: 19 | H19: 18 | I19: 17 | J19: 16 | K19: 15 | L19: 14 | M19: 13 | N19: 12 | O19: 11 | P19: 10 | Q19: 9 | R19: 8 | S19: 7 | T19: 6 | U19: 5 | V19: 4 | W19: 3 | X19: 2 | Y19: 1 | Z19: 0
A20: Comp Attendees | B20: 1/5 - 1/11 | C20: 1/12 - 1/18 | D20: 1/19 - 1/25 | E20: 1/26 - 2/1 | F20: 2/2 - 2/8 | G20: 2/9 - 2/15 | H20: 2/16 - 2/22 | I20: 2/23 - 3/1 | J20: 3/2 - 3/8 | K20: 3/9 - 3/15 | L20: 3/16 - 3/22 | M20: 3/23 - 3/29 | N20: 3/30 - 4/5 | O20: 4/6 - 4/12 | P20: 4/13 - 4/19 | Q20: 4/20 - 4/26 | R20: 4/27 - 5/3 | S20: 5/4 - 5/10 | T20: 5/11 - 5/17 | U20: 5/18 - 5/24 | V20: 5/25 - 5/31 | W20: 6/1 - 6/7 | X20: 6/8 - 6/14 | Y20: 6/15 - 6/21 | Z20: 6/22 - 6/28 | AA20: Post-event registrations
A21: 2023 | B21: =B7-B14 -> 0 | C21: =C7-C14 -> 0 | D21: =D7-D14 -> 4 | E21: =E7-E14 -> 18 | F21: =F7-F14 -> 21 | G21: =G7-G14 -> 140 | H21: =H7-H14 -> 54 | I21: =I7-I14 -> 26 | ... Z21: =Z7-Z14 -> 84
A22: 2024 | B22: =B8-B15 -> 0 | C22: =C8-C15 -> 0 | D22: =D8-D15 -> 0 | E22: =E8-E15 -> 0 | F22: =F8-F15 -> 0 | G22: =G8-G15 -> 0 | H22: =H8-H15 -> 0 | I22: =I8-I15 -> 0 | ... Z22: =Z8-Z15 -> 15
A23: 2026 | B23: 63 | C23: 60 | D23: =D9-D16 -> 16 | E23: 38 | F23: 30 | G23: 19 | H23: 13 | I23: 33 | J23: =J9-J16 -> 51 | K23: 12 | L23: 19 | M23: 13 | N23: 11 | O23: 9 | P23: 31 | Q23: 14 | R23: 65 | S23: 27
A24: 2026 REG TEAM NUMBERS | K24: 48 | L24: 14 | M24: 18 | N24: 13 | O24: 13 | P24: 9 | Q24: 37 | R24: 18 | S24: 64
A26: Weeks Out | B26: 24 | C26: 23 | D26: 22 | E26: 21 | F26: 20 | G26: 19 | H26: 18 | I26: 17 | J26: 16 | K26: 15 | L26: 14 | M26: 13 | N26: 12 | O26: 11 | P26: 10 | Q26: 9 | R26: 8 | S26: 7 | T26: 6 | U26: 5 | V26: 4 | W26: 3 | X26: 2 | Y26: 1 | Z26: 0
A27: Cumulative Total Attendees | B27: 1/5 - 1/11 | C27: 1/12 - 1/18 | D27: 1/19 - 1/25 | E27: 1/26 - 2/1 | F27: 2/2 - 2/8 | G27: 2/9 - 2/15 | H27: 2/16 - 2/22 | I27: 2/23 - 3/1 | J27: 3/2 - 3/8 | K27: 3/9 - 3/15 | L27: 3/16 - 3/22 | M27: 3/23 - 3/29 | N27: 3/30 - 4/5 | O27: 4/6 - 4/12 | P27: 4/13 - 4/19 | Q27: 4/20 - 4/26 | R27: 4/27 - 5/3 | S27: 5/4 - 5/10 | T27: 5/11 - 5/17 | U27: 5/18 - 5/24 | V27: 5/25 - 5/31 | W27: 6/1 - 6/7 | X27: 6/8 - 6/14 | Y27: 6/15 - 6/21 | Z27: 6/22 - 6/28 | AA27: Post-event registrations
A28: 2023 | C28: =SUM($B$7:C7) -> 0 | D28: =SUM($B$7:D7) -> 4 | E28: =SUM($B$7:E7) -> 22 | F28: =SUM($B$7:F7) -> 43 | G28: =SUM($B$7:G7) -> 183 | H28: =SUM($B$7:H7) -> 237 | I28: =SUM($B$7:I7) -> 510 | J28: =SUM($B$7:J7) -> 644 | ... Z28: =SUM($B$7:Z7) -> 4977 | AA28: 19
A29: 2024 | C29: =SUM($B$8:C8) -> 0 | D29: =SUM($B$8:D8) -> 0 | E29: =SUM($B$8:E8) -> 0 | F29: =SUM($B$8:F8) -> 0 | G29: =SUM($B$8:G8) -> 0 | H29: =SUM($B$8:H8) -> 0 | I29: =SUM($B$8:I8) -> 0 | J29: =SUM($B$8:J8) -> 0 | ... Z29: =SUM($B$8:Z8) -> 4653
A30: 2026 | B30: 76 | C30: =SUM($B$9:C9) -> 154 | D30: =SUM($B$9:D9) -> 174 | E30: =SUM($B$9:E9) -> 327 | F30: =SUM($B$9:F9) -> 411 | G30: =SUM($B$9:G9) -> 475 | H30: =SUM($B$9:H9) -> 603 | I30: =SUM($B$9:I9) -> 867 | J30: =SUM($B$9:J9) -> 1666 | ... N30: =SUM($B$9:N9) -> 2051 | O30: 2134 | P30: 2289 | Q30: 2453 | R30: 2875 | S30: 3000 | T30: 3043
A31: 2026 REG TEAM NUMBERS | J31: 851 | K31: 1642 | L31: 1755 | M31: 1874 | N31: 1963 | O31: 2041 | P31: 2118 | Q31: 2289 | R31: 2452 | S31: 2874
A33: Weeks Out | B33: 24 | C33: 23 | D33: 22 | E33: 21 | F33: 20 | G33: 19 | H33: 18 | I33: 17 | J33: 16 | K33: 15 | L33: 14 | M33: 13 | N33: 12 | O33: 11 | P33: 10 | Q33: 9 | R33: 8 | S33: 7 | T33: 6 | U33: 5 | V33: 4 | W33: 3 | X33: 2 | Y33: 1 | Z33: 0
A34: Cumulative Comp Attendees | B34: 1/5 - 1/11 | C34: 1/12 - 1/18 | D34: 1/19 - 1/25 | E34: 1/26 - 2/1 | F34: 2/2 - 2/8 | G34: 2/9 - 2/15 | H34: 2/16 - 2/22 | I34: 2/23 - 3/1 | J34: 3/2 - 3/8 | K34: 3/9 - 3/15 | L34: 3/16 - 3/22 | M34: 3/23 - 3/29 | N34: 3/30 - 4/5 | O34: 4/6 - 4/12 | P34: 4/13 - 4/19 | Q34: 4/20 - 4/26 | R34: 4/27 - 4/3 | S34: 5/4 - 5/10 | T34: 5/11 - 5/17 | U34: 5/18 - 5/24 | V34: 5/25 - 5/31 | W34: 6/1 - 6/7 | X34: 6/8 - 6/14 | Y34: 6/15 - 6/21 | Z34: 6/22 - 6/28 | AA34: Post-event registrations
A35: 2023 | C35: =SUM($B$21:C21) -> 0 | D35: =SUM($B$21:D21) -> 4 | E35: =SUM($B$21:E21) -> 22 | F35: =SUM($B$21:F21) -> 43 | G35: =SUM($B$21:G21) -> 183 | H35: =SUM($B$21:H21) -> 237 | I35: =SUM($B$21:I21) -> 263 | J35: =SUM($B$21:J21) -> 279 | ... Z35: =SUM($B$21:Z21) -> 1343
A36: 2024 | C36: =SUM($B$22:C22) -> 0 | D36: =SUM($B$22:D22) -> 0 | E36: =SUM($B$22:E22) -> 0 | F36: =SUM($B$22:F22) -> 0 | G36: =SUM($B$22:G22) -> 0 | H36: =SUM($B$22:H22) -> 0 | I36: =SUM($B$22:I22) -> 0 | J36: =SUM($B$22:J22) -> 0 | ... Z36: =SUM($B$22:Z22) -> 1125
A37: 2026 | B37: 63 | C37: 123 | D37: 139 | E37: 177 | F37: 207 | G37: 226 | H37: 239 | I37: 272 | J37: 323 | K37: 335 | L37: 354 | M37: 367 | N37: 378 | O37: 387 | P37: 418 | Q37: 432 | R37: 497 | S37: 524
A38: 2026 REG TEAM NUMBERS | J38: 274 | K38: 322 | L38: 336 | M38: 354 | N38: 367 | O38: 380 | P38: 389 | Q38: 426 | R38: 444 | S38: 508
A40: Weeks Out | B40: 24 | C40: 23 | D40: 22 | E40: 21 | F40: 20 | G40: 19 | H40: 18 | I40: 17 | J40: 16 | K40: 15 | L40: 14 | M40: 13 | N40: 12 | O40: 11 | P40: 10 | Q40: 9 | R40: 8 | S40: 7 | T40: 6 | U40: 5 | V40: 4 | W40: 3 | X40: 2 | Y40: 1 | Z40: 0
A41: Cumulative Paid Attendees | B41: 1/5 - 1/11 | C41: 1/12 - 1/18 | D41: 1/19 - 1/25 | E41: 1/26 - 2/1 | F41: 2/2 - 2/8 | G41: 2/9 - 2/15 | H41: 2/16 - 2/22 | I41: 2/23 - 3/1 | J41: 3/2 - 3/8 | K41: 3/9 - 3/15 | L41: 3/16 - 3/22 | M41: 3/23 - 3/29 | N41: 3/30 - 4/5 | O41: 4/6 - 4/12 | P41: 4/13 - 4/19 | Q41: 4/20 - 4/26 | R41: 4/27 - 4/3 | S41: 5/4 - 5/10 | T41: 5/11 - 5/17 | U41: 5/18 - 5/24 | V41: 5/25 - 5/31 | W41: 6/1 - 6/7 | X41: 6/8 - 6/14 | Y41: 6/15 - 6/21 | Z41: 6/22 - 6/28 | AA41: Post-event registrations
A42: 2023 | C42: =SUM($B$14:C14) -> 0 | D42: =SUM($B$14:D14) -> 0 | E42: =SUM($B$14:E14) -> 0 | F42: =SUM($B$14:F14) -> 0 | G42: =SUM($B$14:G14) -> 0 | H42: =SUM($B$14:H14) -> 0 | I42: =SUM($B$14:I14) -> 247 | J42: =SUM($B$14:J14) -> 365 | ... Z42: =SUM($B$14:Z14) -> 3634
A43: 2024 | C43: =SUM($B$15:C15) -> 0 | D43: =SUM($B$15:D15) -> 0 | E43: =SUM($B$15:E15) -> 0 | F43: =SUM($B$15:F15) -> 0 | G43: =SUM($B$15:G15) -> 0 | H43: =SUM($B$15:H15) -> 0 | I43: =SUM($B$15:I15) -> 0 | J43: =SUM($B$15:J15) -> 0 | ... Z43: =SUM($B$15:Z15) -> 3528
A44: 2026 | B44: 13 | C44: =SUM($B$16:C16) -> 31 | D44: =SUM($B$16:D16) -> 35 | E44: =SUM($B$16:E16) -> 150 | F44: =SUM($B$16:F16) -> 204 | G44: =SUM($B$16:G16) -> 249 | H44: =SUM($B$16:H16) -> 364 | I44: 595 | J44: =SUM($B$16:J16) -> 1343 | K44: 1440 | L44: 1531 | M44: 1606 | N44: 1673 | O44: 1739 | P44: 1864 | Q44: 2014 | R44: 2371 | S44: 2469
A45: 2026 REG TEAM NUMBERS | J45: =71+506 -> 577 | K45: =1116+204 -> 1320 | L45: =1185+234 -> 1419 | M45: =287+1233 -> 1520 | N45: =1295+301 -> 1596 | O45: =310+1351 -> 1661 | P45: =1409+320 -> 1729 | Q45: =1498+365 -> 1863 | R45: =408+1600 -> 2008
A46: PROJECTED PAID 2026 | C46: 25 | D46: 75 | E46: 125 | F46: 300 | G46: =180*3 -> 540 | H46: =180*4 -> 720 | I46: 1080 | J46: =232+273+167+207+559 -> 1438 | K46: =J46+62 -> 1500 | L46: =K46+62 -> 1562 | M46: =L46+62 -> 1624 | N46: =M46+62 -> 1686 | O46: =N46+62 -> 1748 | P46: =O46+62 -> 1810 | Q46: =P46+62 -> 1872 | R46: =Q46+62 -> 1934 | S46: =R46+62 -> 1996 | T46: =J46+215+62+76+112+152 -> 2055 | U46: =T46+175 -> 2230 | V46: =U46+200 -> 2430 | W46: =V46+200 -> 2630 | X46: =W46+200 -> 2830 | Y46: =X46+225 -> 3055 | Z46: 3172
A49: 2026 Objectives
A50: Cumulative Attendees | B50: Actual | C50: Goal | D50: % to Goal
A51: Total Attendees | B51: 3043 | C51: 4937 | D51: =B51/C51 -> 0.61636621
A52: Paid Attendees | B52: 2469 | C52: 3855 | D52: =B52/C52 -> 0.64046693
A53: Comp Attendees | B53: 524 | C53: 1082 | D53: =B53/C53 -> 0.48428835
